Workbook

Sheet AN
C1: Anaheim
C2: Per Restaurant
C3: Chage Order Deposits | D3: Change Order Received | E3: Initials | F3: Comments | H3: Cash over/ (Short) per R365 Flash report | I3: True Over/ (Short)
B4: =Control!$B$3 -> 46243 | C4: 0 | D4: 1100 | E4: AR | F4: Prior Period 8 owed $1,100 | I4: =H4-C4 -> 0
B5: =B4+1 -> 46244 | C5: 0 | D5: 0 | E5: Ld | H5: 0 | I5: =H5-C5 -> 0
B6: =B5+1 -> 46245 | C6: 0 | D6: 1800 | E6: AR | H6: 0 | I6: =H6-C6 -> 0
B7: =B6+1 -> 46246 | C7: 0 | D7: 0 | E7: Ld | H7: 0 | I7: =H7-C7 -> 0
B8: =B7+1 -> 46247 | C8: -1300 | D8: 0 | E8: AR | H8: 0 | I8: =H8-C8 -> 1300
B9: =B8+1 -> 46248 | C9: 0 | D9: 0 | H9: 0 | I9: =H9-C9 -> 0
B10: =B9+1 -> 46249 | C10: 0 | D10: 0 | H10: 0 | I10: =H10-C10 -> 0
B11: Total Week | C11: =SUM(C4:C10) -> -1300 | D11: =SUM(D4:D10) -> 2900 | H11: =SUM(H4:H10) -> 0 | I11: =SUM(I4:I10) -> 1300
B12: =B10+1 -> 46250 | C12: 0 | D12: 0 | I12: =H12-C12 -> 0
B13: =B12+1 -> 46251 | C13: 0 | D13: 0 | E13: Ld | I13: =H13-C13 -> 0
B14: =B13+1 -> 46252 | C14: 0 | D14: 0 | I14: =H14-C14 -> 0
B15: =B14+1 -> 46253 | C15: -1500 | D15: 700 | E15: AR | I15: =H15-C15 -> 1500
B16: =B15+1 -> 46254 | C16: 0 | D16: 0 | I16: =H16-C16 -> 0
B17: =B16+1 -> 46255 | C17: 0 | D17: 0 | I17: =H17-C17 -> 0
B18: =B17+1 -> 46256 | C18: 0 | D18: 0 | I18: =H18-C18 -> 0
B19: Total Week | C19: =SUM(C12:C18) -> -1500 | D19: =SUM(D12:D18) -> 700 | H19: =SUM(H12:H18) -> 0 | I19: =SUM(I12:I18) -> 1500
B20: =B18+1 -> 46257 | C20: 0 | D20: 0 | I20: =H20-C20 -> 0
B21: =B20+1 -> 46258 | C21: 0 | D21: 0 | I21: =H21-C21 -> 0
B22: =B21+1 -> 46259 | C22: 0 | D22: 2020 | E22: AR | I22: =H22-C22 -> 0
B23: =B22+1 -> 46260 | C23: -820 | D23: 0 | E23: AR | I23: =H23-C23 -> 820
B24: =B23+1 -> 46261 | C24: 0 | D24: 0 | I24: =H24-C24 -> 0
B25: =B24+1 -> 46262 | C25: 0 | D25: 0 | I25: =H25-C25 -> 0
B26: =B25+1 -> 46263 | C26: -800 | D26: 0 | I26: =H26-C26 -> 800
B27: Total Week | C27: =SUM(C20:C26) -> -1620 | D27: =SUM(D20:D26) -> 2020 | H27: =SUM(H20:H26) -> 0 | I27: =SUM(I20:I26) -> 1620
B28: =B26+1 -> 46264 | C28: 0 | D28: 0 | I28: =H28-C28 -> 0
B29: =B28+1 -> 46265 | C29: 0 | D29: 0 | I29: =H29-C29 -> 0
B30: =B29+1 -> 46266 | C30: 0 | D30: 0 | I30: =H30-C30 -> 0
B31: =B30+1 -> 46267 | C31: 0 | D31: 0 | I31: =H31-C31 -> 0
B32: =B31+1 -> 46268 | C32: 0 | D32: 0 | I32: =H32-C32 -> 0
B33: =B32+1 -> 46269 | C33: -1250 | D33: 2450 | E33: AR | I33: =H33-C33 -> 1250
B34: =B33+1 -> 46270 | C34: -300 | D34: 0 | E34: AR | I34: =H34-C34 -> 300
B35: Total Week | C35: =SUM(C28:C34) -> -1550 | D35: =SUM(D28:D34) -> 2450 | H35: =SUM(H28:H34) -> 0 | I35: =SUM(I28:I34) -> 1550
B36: Total Period | C36: =SUM(C35+C27+C19+C11) -> -5970 | D36: =SUM(D35+D27+D19+D11) -> 8070 | H36: =SUM(H35+H27+H19+H11) -> 0 | I36: =SUM(I35+I27+I19+I11) -> 5970
B37: Period Activity | C37: =D36+C36 -> 2100 | H37: =I36+H36 -> 5970 | I37: =J36+I36 -> 5970
C38: =B34+1 -> 46271 | D38: After Period Close
B39: Ending Period Count of Amount on hand | C39: 2100 | E39: AR
B41: Number of Cash Drawers | C41: 2
B43: Amount of Each Drawer | C43: 200
B45: Amount of Petty Cash | C45: 300
B47: Period10
B48: Sun 9-6 | C48: 0 | D48: 0 | E48: AR | F48: Prior period carryover was $2,100 | H48: 60 | I48: =H48-C48 -> 60
B49: Mon 9-7 | C49: 0 | D49: 0 | E49: AR | H49: 11 | I49: =H49-C49 -> 11
B50: Tue 9-8 | C50: 0 | D50: 0 | E50: AR | H50: 17 | I50: =H50-C50 -> 17
B51: Wed 9-9 | C51: 0 | D51: 0 | E51: AR | H51: -30 | I51: =H51-C51 -> -30
B52: Thu 9-10 | C52: 0 | D52: 2020 | E52: AR | H52: -13 | I52: =H52-C52 -> -13
B53: Fri 9-11 | C53: 0 | D53: 0 | E53: AR | H53: -7 | I53: =H53-C53 -> -7
B54: Sat 9-12 | C54: 0 | D54: 0 | E54: DS | H54: -49 | I54: =H54-C54 -> -49
B55: Total Week | D55: =SUM(D48:D54) -> 2020 | H55: =SUM(H48:H54) -> -11 | I55: =SUM(I48:I54) -> -11
B56: Sun 9-13 | C56: 0 | D56: 0 | E56: DS | H56: 51 | I56: =H56-C56 -> 51
B57: Mon 9-14 | C57: 0 | D57: 0 | E57: Ld | H57: -81 | I57: =H57-C57 -> -81
B58: Tue 9-15 | C58: 2100 | D58: 0 | E58: Ld | F58: This was from last period owed | H58: 2203 | I58: =H58-C58 -> 103
B59: Wed 9-16 | C59: 0 | D59: 0 | E59: Ld | H59: -14 | I59: =H59-C59 -> -14
B60: Thu 9-17 | C60: 0 | D60: 0 | E60: Ld | H60: 34 | I60: =H60-C60 -> 34
B61: Fri 9-18 | C61: 0 | D61: 0 | E61: AR | H61: 26 | I61: =H61-C61 -> 26
B62: Sat 9-19 | C62: 0 | D62: 0 | E62: AR | H62: -49 | I62: =H62-C62 -> -49
B63: Total Week | C63: =SUM(C56:C62) -> 2100 | D63: 0 | H63: =SUM(H56:H62) -> 2170 | I63: =SUM(I56:I62) -> 70
B64: Sun 9-20 | C64: 0 | D64: 0 | E64: Ld | H64: 38 | I64: =H64-C64 -> 38
B65: Mon 9-21 | C65: 0 | D65: 0 | E65: Ld | H65: 97.55 | I65: =H65-C65 -> 97.55
B66: Tue 9-22 | C66: 0 | D66: 0 | E66: Ld | H66: -89 | I66: =H66-C66 -> -89
B67: Wed 9-23 | C67: 0 | D67: 0 | E67: Ld | H67: 25 | I67: 25
B68: Thu 9-24 | C68: 0 | D68: 0 | E68: AR | F68: Tomorrow will reflect short $67 there was not enough cash to pay GY | H68: 81 | I68: =H68-C68 -> 81
B69: Fri 9-25 | C69: 1400 | D69: 1920 | E69: AR | H69: 1324 | I69: =H69-C69 -> -76
B70: Sat 9-26 | C70: 0 | D70: 0 | E70: Ld | H70: -29.51 | I70: =H70-C70 -> -29.51
B71: Total Week | C71: =SUM(C64:C70) -> 1400 | D71: =SUM(D64:D70) -> 1920 | H71: =SUM(H64:H70) -> 1447.04 | I71: =SUM(I64:I70) -> 47.04
B72: Sun 9-27 | C72: 0 | D72: 0 | E72: Ld | H72: -19.82 | I72: =H72-C72 -> -19.82
B73: Mon 9-28 | C73: 0 | D73: 0 | E73: Ld | H73: -16.42 | I73: =H73-C73 -> -16.42
B74: Tue 9-29 | C74: 0 | D74: 1400 | E74: DS | F74: Received Change order(unopened) | H74: 32.35 | I74: =H74-C74 -> 32.35
B75: Wed 9-30 | C75: 1240 | D75: 0 | E75: Ld | H75: 1234 | I75: =H75-C75 -> -6
B76: Thu 10-1 | C76: 0 | D76: 0 | E76: AR | H76: 21 | I76: =H76-C76 -> 21
B77: Fri 10-2 | D77: 0 | E77: AR | F77: shortage was $0 | H77: 0 | I77: =H77-C77 -> 0
B78: Sat 10-3 | C78: 1200 | D78: 0 | E78: AR | H78: 1165 | I78: =H78-C78 -> -35
B79: Total Week | C79: =SUM(C72:C78) -> 2440 | D79: =SUM(D72:D78) -> 1400 | H79: =SUM(H72:H78) -> 2416.11 | I79: =SUM(I72:I78) -> -23.89
B80: Total Period | C80: =SUM(C79+C71+C63+C55) -> 5940 | D80: =SUM(D79+D71+D63+D55) -> 5340 | H80: =SUM(H79+H71+H63+H55) -> 6022.15 | I80: =SUM(I79+I71+I63+I55) -> 82.15
B81: Period Activity | C81: =D80-C80 -> -600 | H81: =I80+H80 -> 6104.3 | I81: =J80+I80 -> 82.15
C82: Sun 10-4 | D82: After Period Close
B83: Ending Period Count of Amopunt on hand | C83: 1500 | E83: AR
B85: Number of Cash Drawers | C85: 2
B87: Amount of Each Drawer | C87: 200
B89: Amount of Petty Cash | C89: 300
B91: Period11
B92: Sun 10-4 | C92: 0 | D92: 0 | E92: AR | F92: Over deposited $100 will reflect tomorrow | H92: 95 | I92: =H92-C92 -> 95
B93: Mon 10-5 | C93: 0 | D93: 0 | E93: AR | H93: -138 | I93: =H93-C93 -> -138
B94: Tue 10-6 | C94: 0 | D94: 1525 | E94: AR | F94: Received Change order | H94: -8 | I94: =H94-C94 -> -8
B95: Wed 10-7 | C95: 1125 | D95: 0 | E95: AR | H95: 1107 | I95: =H95-C95 -> -18
B96: Thu 10-8 | C96: 0 | D96: 0 | E96: DS | H96: 2 | I96: =H96-C96 -> 2
B97: Fri 10-9 | C97: 0 | D97: 0 | E97: DS | H97: 4 | I97: =H97-C97 -> 4
B98: Sat 10-10 | C98: 0 | D98: 0 | E98: AR | H98: -4 | I98: =H98-C98 -> -4
B99: Total Week | C99: =SUM(C92:C98) -> 1125 | D99: =SUM(D92:D98) -> 1525 | H99: =SUM(H92:H98) -> 1058 | I99: =SUM(I92:I98) -> -67
B100: Sun 10-11 | C100: 0 | D100: 0 | H100: 0 | I100: =H100-C100 -> 0
B101: Mon 10-12 | C101: 0 | D101: 0 | H101: 0 | I101: =H101-C101 -> 0
B102: Tue 10-13 | C102: 0 | D102: 0 | H102: 0 | I102: =H102-C102 -> 0
B103: Wed 10-14 | C103: 0 | D103: 0 | H103: 0 | I103: =H103-C103 -> 0
B104: Thu 10-15 | C104: 0 | D104: 0 | H104: 0 | I104: =H104-C104 -> 0
B105: Fri 10-16 | C105: 0 | D105: 0 | H105: 0 | I105: =H105-C105 -> 0
B106: Sat 10-17 | C106: 0 | D106: 0 | H106: 0 | I106: =H106-C106 -> 0
B107: Total Week | C107: =SUM(C100:C106) -> 0 | D107: =SUM(D100:D106) -> 0 | H107: =SUM(H100:H106) -> 0 | I107: =SUM(I100:I106) -> 0
B108: Sun 10-18 | C108: 0 | D108: 0 | H108: 0 | I108: =H108-C108 -> 0
...

Sheet CL
C1: Claremont
C2: Per Restaurant
C3: Chage Order Deposits | D3: Change Order Received | E3: Initials | F3: Comments | H3: Cash over/ (Short) per R365 Flash report | I3: True Over/ (Short)
B4: =Control!$B$3 -> 46243 | C4: 0 | D4: 0 | I4: =H4-C4 -> 0
B5: =B4+1 -> 46244 | C5: 0 | D5: 0 | I5: =H5-C5 -> 0
B6: =B5+1 -> 46245 | C6: 0 | D6: 0 | I6: =H6-C6 -> 0
B7: =B6+1 -> 46246 | C7: -950 | D7: 2200 | E7: YT | I7: =H7-C7 -> 950
B8: =B7+1 -> 46247 | C8: 0 | D8: 0 | I8: =H8-C8 -> 0
B9: =B8+1 -> 46248 | C9: -500 | D9: 0 | E9: YT | I9: =H9-C9 -> 500
B10: =B9+1 -> 46249 | C10: 0 | D10: 0 | I10: =H10-C10 -> 0
B11: Total Week | C11: =SUM(C4:C10) -> -1450 | D11: =SUM(D4:D10) -> 2200 | H11: =SUM(H4:H10) -> 0 | I11: =SUM(I4:I10) -> 1450
B12: =B10+1 -> 46250 | C12: 0 | D12: 0 | I12: =H12-C12 -> 0
B13: =B12+1 -> 46251 | C13: 0 | D13: 0 | I13: =H13-C13 -> 0
B14: =B13+1 -> 46252 | C14: 0 | D14: 0 | I14: =H14-C14 -> 0
B15: =B14+1 -> 46253 | C15: 0 | D15: 1175 | E15: YT | I15: =H15-C15 -> 0
B16: =B15+1 -> 46254 | C16: -1500 | D16: 0 | E16: YT | I16: =H16-C16 -> 1500
B17: =B16+1 -> 46255 | C17: 0 | D17: 0 | I17: =H17-C17 -> 0
B18: =B17+1 -> 46256 | C18: -710 | D18: 0 | E18: YT | I18: =H18-C18 -> 710
B19: Total Week | C19: =SUM(C12:C18) -> -2210 | D19: =SUM(D12:D18) -> 1175 | H19: =SUM(H12:H18) -> 0 | I19: =SUM(I12:I18) -> 2210
B20: =B18+1 -> 46257 | C20: 0 | D20: 0 | I20: =H20-C20 -> 0
B21: =B20+1 -> 46258 | C21: 0 | D21: 0 | I21: =H21-C21 -> 0
B22: =B21+1 -> 46259 | C22: 0 | D22: 0 | I22: =H22-C22 -> 0
B23: =B22+1 -> 46260 | C23: -1110 | D23: 1550 | E23: YT | I23: =H23-C23 -> 1110
B24: =B23+1 -> 46261 | C24: 0 | D24: 0 | H24: 0 | I24: =H24-C24 -> 0
B25: =B24+1 -> 46262 | C25: 0 | D25: 0 | H25: 0 | I25: =H25-C25 -> 0
B26: =B25+1 -> 46263 | C26: 0 | D26: 0 | H26: 0 | I26: =H26-C26 -> 0
B27: Total Week | C27: =SUM(C20:C26) -> -1110 | D27: =SUM(D20:D26) -> 1550 | H27: =SUM(H20:H26) -> 0 | I27: =SUM(I20:I26) -> 1110
B28: =B26+1 -> 46264 | C28: 0 | D28: 0 | I28: 0
B29: =B28+1 -> 46265 | C29: 0 | D29: 0 | I29: =H29-C29 -> 0
B30: =B29+1 -> 46266 | D30: 2025 | E30: BH | F30: Chng order received | I30: =H30-C30 -> 0
B31: =B30+1 -> 46267 | C31: -2210 | E31: YT | F31: Chng order paid(Short $53 actual for the Day) | I31: =H31-C31 -> 2210
B32: =B31+1 -> 46268 | C32: 0 | D32: 0 | I32: =H32-C32 -> 0
B33: =B32+1 -> 46269 | C33: 0 | D33: 0 | I33: =H33-C33 -> 0
B34: =B33+1 -> 46270 | C34: 0 | D34: 0 | I34: =H34-C34 -> 0
B35: Total Week | C35: =SUM(C28:C34) -> -2210 | D35: =SUM(D28:D34) -> 2025 | H35: =SUM(H28:H34) -> 0 | I35: =SUM(I28:I34) -> 2210
B36: Total Period | C36: =SUM(C35+C27+C19+C11) -> -6980 | D36: =SUM(D35+D27+D19+D11) -> 6950 | H36: =SUM(H35+H27+H19+H11) -> 0 | I36: =SUM(I35+I27+I19+I11) -> 6980
B37: Period Activity | C37: =D36+C36 -> -30 | H37: =I36+H36 -> 6980 | I37: =J36+I36 -> 6980
C38: =B34+1 -> 46271 | D38: After Period Close
B39: Ending Period Count of Amount on hand | C39: 1630 | E39: YT
B41: Number of Cash Drawers | C41: 2
B43: Amount of Each Drawer | C43: 200
B45: Amount of Petty Cash | C45: 300
B47: Period10
B48: Sun 9-6 | C48: 0 | D48: 0 | E48: YT | H48: -35 | I48: =H48-C48 -> -35
B49: Mon 9-7 | C49: 800 | D49: 0 | E49: YT | H49: 828 | I49: =H49-C49 -> 28
B50: Tue 9-8 | C50: 0 | D50: 0 | E50: vs | H50: 1.18 | I50: =H50-C50 -> 1.18
B51: Wed 9-9 | C51: 700 | D51: 2150 | E51: YT | F51: Change order received & paid | H51: 676.53 | I51: =H51-C51 -> -23.47
B52: Thu 9-10 | C52: 0 | D52: 0 | E52: YT | H52: 25.83 | I52: =H52-C52 -> 25.83
B53: Fri 9-11 | C53: 0 | D53: 0 | E53: YT | H53: -29 | I53: =H53-C53 -> -29
B54: Sat 9-12 | C54: 850 | D54: 0 | E54: YT | F54: Change order paid | H54: 766.22 | I54: =H54-C54 -> -83.78
B55: Total Week | C55: =SUM(C48:C54) -> 2350 | D55: =SUM(D48:D54) -> 2150 | H55: =SUM(H48:H54) -> 2233.76 | I55: =SUM(I48:I54) -> -116.24
B56: Sun 9-13 | D56: 0 | E56: YT | H56: 31 | I56: =H56-C56 -> 31
B57: Mon 9-14 | C57: 0 | D57: 0 | E57: vs | H57: 26 | I57: =H57-C57 -> 26
B58: Tue 9-15 | C58: 0 | D58: 0 | E58: vs | H58: 12 | I58: =H58-C58 -> 12
B59: Wed 9-16 | C59: 1080 | D59: 2175 | E59: YT | F59: Changer order received & paid (Ordered Sunday 9.13.26) | H59: 1044.92 | I59: =H59-C59 -> -35.08
B60: Thu 9-17 | C60: 0 | D60: 0 | E60: YT | H60: -15.66 | I60: =H60-C60 -> -15.66
B61: Fri 9-18 | C61: 0 | D61: 0 | E61: YT | H61: 52.39 | I61: =H61-C61 -> 52.39
B62: Sat 9-19 | C62: 820 | D62: 0 | E62: YT | F62: Change order paid | H62: 755 | I62: =H62-C62 -> -65
B63: Total Week | C63: =SUM(C56:C62) -> 1900 | D63: =SUM(D56:D62) -> 2175 | H63: =SUM(H56:H62) -> 1905.65 | I63: =SUM(I56:I62) -> 5.65
B64: Sun 9-20 | C64: 0 | D64: 0 | E64: BH | H64: 18.61 | I64: =H64-C64 -> 18.61
B65: Mon 9-21 | C65: 0 | E65: vs | F65: Partial Closure due to shooting across the street | H65: 16 | I65: =H65-C65 -> 16
B66: Tue 9-22 | C66: 0 | D66: 2250 | E66: BH | F66: Change order received - BH (Ordered Sunday 9.20.26) | H66: 30.33 | I66: =H66-C66 -> 30.33
B67: Wed 9-23 | C67: 1230 | D67: 0 | E67: YT | F67: Change order paid | H67: 1159.91 | I67: =H67-C67 -> -70.09
B68: Thu 9-24 | C68: 0 | D68: 0 | E68: YT | F68: GY Shortage EP & H (Servers) will coach | H68: -53.34 | I68: =H68-C68 -> -53.34
B69: Fri 9-25 | C69: 0 | D69: 0 | E69: YT | F69: EP Coached by BH | H69: -20.16 | I69: =H69-C69 -> -20.16
B70: Sat 9-26 | C70: 800 | D70: 0 | E70: YT | F70: HA Coached by BH. Change Order Paid $800- SH | H70: 815.93 | I70: =H70-C70 -> 15.93
B71: Total Week | C71: =SUM(C64:C70) -> 2030 | D71: =SUM(D64:D70) -> 2250 | H71: =SUM(H64:H70) -> 1967.28 | I71: =SUM(I64:I70) -> -62.72
B72: Sun 9-27 | D72: 0 | E72: vs | F72: Dep not entered in ALOHA before 8AM $1,232 | H72: 8 | I72: =H72-C72 -> 8
B73: Mon 9-28 | C73: 0 | D73: 0 | E73: vs | H73: -23 | I73: =H73-C73 -> -23
B74: Tue 9-29 | C74: 800 | D74: 2270 | E74: BH | F74: Change order recieved by VS, Counted by BH (Ordered 09/27/2026) | H74: 810.73 | I74: =H74-C74 -> 10.73
B75: Wed 9-30 | D75: 0 | E75: vs | H75: -15.91 | I75: =H75-C75 -> -15.91
B76: Thu 10-1 | C76: 750 | D76: 0 | E76: EE | F76: Change order paid | H76: 742.46 | I76: =H76-C76 -> -7.54
B77: Fri 10-2 | C77: 0 | D77: 0 | E77: vs | H77: 18 | I77: =H77-C77 -> 18
B78: Sat 10-3 | D78: 0 | E78: vs | H78: -28 | I78: =H78-C78 -> -28
B79: Total Week | C79: =SUM(C72:C78) -> 1550 | D79: =SUM(D72:D78) -> 2270 | H79: =SUM(H72:H78) -> 1512.28 | I79: =SUM(I72:I78) -> -37.72
B80: Total Period | C80: =SUM(C79+C71+C63+C55) -> 7830 | D80: =SUM(D79+D71+D63+D55) -> 8845 | H80: =SUM(H79+H71+H63+H55) -> 7618.97 | I80: =SUM(I79+I71+I63+I55) -> -211.03
B81: Period Activity | C81: =D80-C80 -> 1015 | H81: =I80+H80 -> 7407.94 | I81: =J80+I80 -> -211.03
C82: Sun 10-4 | D82: After Period Close
B83: Ending Period Count of Amopunt on hand | C83: 2645 | E83: EE
B85: Number of Cash Drawers | C85: 2
B87: Amount of Each Drawer | C87: 200
B89: Amount of Petty Cash | C89: 300
B91: Period11
B92: Sun 10-4 | C92: 0 | D92: 0 | E92: vs | H92: 24 | I92: =H92-C92 -> 24
B93: Mon 10-5 | C93: 0 | D93: 0 | E93: vs | H93: 30 | I93: =H93-C93 -> 30
B94: Tue 10-6 | C94: 0 | D94: 0 | E94: EE | H94: 15 | I94: =H94-C94 -> 15
B95: Wed 10-7 | C95: 0 | D95: 0 | E95: EE | H95: 26 | I95: =H95-C95 -> 26
B96: Thu 10-8 | C96: 860 | D96: 0 | E96: EE | F96: Change order paid | H96: 823 | I96: =H96-C96 -> -37
B97: Fri 10-9 | C97: 0 | D97: 0 | E97: VS | H97: 10 | I97: =H97-C97 -> 10
B98: Sat 10-10 | C98: 0 | D98: 0 | E98: EE | H98: 4 | I98: =H98-C98 -> 4
B99: Total Week | C99: =SUM(C92:C98) -> 860 | D99: =SUM(D92:D98) -> 0 | H99: =SUM(H92:H98) -> 932 | I99: =SUM(I92:I98) -> 72
B100: Sun 10-11 | C100: 0 | D100: 0 | H100: 0 | I100: =H100-C100 -> 0
B101: Mon 10-12 | C101: 0 | D101: 0 | H101: 0 | I101: =H101-C101 -> 0
B102: Tue 10-13 | C102: 0 | D102: 0 | H102: 0 | I102: =H102-C102 -> 0
B103: Wed 10-14 | C103: 0 | D103: 0 | H103: 0 | I103: =H103-C103 -> 0
B104: Thu 10-15 | C104: 0 | D104: 0 | H104: 0 | I104: =H104-C104 -> 0
B105: Fri 10-16 | C105: 0 | D105: 0 | H105: 0 | I105: =H105-C105 -> 0
B106: Sat 10-17 | C106: 0 | D106: 0 | H106: 0 | I106: =H106-C106 -> 0
B107: Total Week | C107: =SUM(C100:C106) -> 0 | D107: =SUM(D100:D106) -> 0 | H107: =SUM(H100:H106) -> 0 | I107: =SUM(I100:I106) -> 0
B108: Sun 10-18 | C108: 0 | D108: 0 | H108: 0 | I108: =H108-C108 -> 0
...

Sheet CM
C1: Costa Mesa
C2: Per Restaurant
C3: Chage Order Deposits | D3: Change Order Received | E3: Initials | F3: Comments | H3: Cash over/ (Short) per R365 Flash report | I3: True Over/ (Short)
B4: =Control!$B$3 -> 46243 | C4: 0 | D4: 0 | I4: =H4-C4 -> 0
B5: =B4+1 -> 46244 | C5: 0 | D5: 0 | I5: =H5-C5 -> 0
B6: =B5+1 -> 46245 | C6: 0 | D6: 0 | I6: =H6-C6 -> 0
B7: =B6+1 -> 46246 | C7: 0 | D7: 1050 | E7: cn | I7: =H7-C7 -> 0
B8: =B7+1 -> 46247 | C8: 0 | D8: 0 | I8: =H8-C8 -> 0
B9: =B8+1 -> 46248 | C9: 0 | D9: 0 | I9: =H9-C9 -> 0
B10: =B9+1 -> 46249 | C10: 0 | D10: 0 | I10: =H10-C10 -> 0
B11: Total Week | C11: =SUM(C4:C10) -> 0 | D11: =SUM(D4:D10) -> 1050 | E11: cn | H11: =SUM(H4:H10) -> 0 | I11: =SUM(I4:I10) -> 0
B12: =B10+1 -> 46250 | C12: 0 | D12: 0 | I12: =H12-C12 -> 0
B13: =B12+1 -> 46251 | C13: 0 | D13: 0 | I13: =H13-C13 -> 0
B14: =B13+1 -> 46252 | C14: 0 | D14: 0 | I14: =H14-C14 -> 0
B15: =B14+1 -> 46253 | C15: -1050 | D15: 900 | E15: cn | I15: =H15-C15 -> 1050
B16: =B15+1 -> 46254 | C16: 0 | D16: 0 | I16: =H16-C16 -> 0
B17: =B16+1 -> 46255 | C17: 0 | D17: 0 | I17: =H17-C17 -> 0
B18: =B17+1 -> 46256 | C18: 0 | D18: 0 | I18: =H18-C18 -> 0
B19: Total Week | C19: =SUM(C12:C18) -> -1050 | D19: =SUM(D12:D18) -> 900 | E19: cn | H19: =SUM(H12:H18) -> 0 | I19: =SUM(I12:I18) -> 1050
B20: =B18+1 -> 46257 | C20: 0 | D20: 0 | I20: =H20-C20 -> 0
B21: =B20+1 -> 46258 | C21: 0 | D21: 0 | I21: =H21-C21 -> 0
B22: =B21+1 -> 46259 | C22: 0 | D22: 0 | I22: =H22-C22 -> 0
B23: =B22+1 -> 46260 | C23: -900 | D23: 620 | E23: cn | I23: =H23-C23 -> 900
B24: =B23+1 -> 46261 | C24: 0 | D24: 0 | I24: =H24-C24 -> 0
B25: =B24+1 -> 46262 | C25: 0 | D25: 0 | I25: =H25-C25 -> 0
B26: =B25+1 -> 46263 | C26: 0 | D26: 0 | I26: =H26-C26 -> 0
B27: Total Week | C27: =SUM(C20:C26) -> -900 | D27: =SUM(D20:D26) -> 620 | E27: cn | H27: =SUM(H20:H26) -> 0 | I27: =SUM(I20:I26) -> 900
B28: =B26+1 -> 46264 | C28: 0 | D28: 0 | I28: =H28-C28 -> 0
B29: =B28+1 -> 46265 | C29: 0 | D29: 0 | I29: =H29-C29 -> 0
B30: =B29+1 -> 46266 | C30: -620 | D30: 450 | E30: cn | I30: =H30-C30 -> 620
B31: =B30+1 -> 46267 | C31: 0 | D31: 0 | I31: =H31-C31 -> 0
B32: =B31+1 -> 46268 | C32: 0 | D32: 0 | I32: =H32-C32 -> 0
B33: =B32+1 -> 46269 | C33: 0 | D33: 0 | I33: =H33-C33 -> 0
B34: =B33+1 -> 46270 | C34: -450 | D34: 0 | E34: cn | I34: =H34-C34 -> 450
B35: Total Week | C35: =SUM(C28:C34) -> -1070 | D35: =SUM(D28:D34) -> 450 | E35: cn | H35: =SUM(H28:H34) -> 0 | I35: =SUM(I28:I34) -> 1070
B36: Total Period | C36: =SUM(C35+C27+C19+C11) -> -3020 | D36: =SUM(D35+D27+D19+D11) -> 3020 | E36: cn | H36: =SUM(H35+H27+H19+H11) -> 0 | I36: =SUM(I35+I27+I19+I11) -> 3020
B37: Period Activity | C37: 0 | H37: =I36+H36 -> 3020 | I37: =J36+I36 -> 3020
C38: =B34+1 -> 46271 | D38: After Period Close
B39: Ending Period Count of Amount on hand | C39: 0 | E39: cn
B41: Number of Cash Drawers | C41: 2
B43: Amount of Each Drawer | C43: 200
B45: Amount of Petty Cash | C45: 300
B47: Period10
B48: Sun 9-6 | C48: 0 | D48: 0 | E48: cn | H48: 12.51 | I48: =H48-C48 -> 12.51
B49: Mon 9-7 | C49: 0 | D49: 0 | E49: cn | F49: Labor day | H49: -3.08 | I49: =H49-C49 -> -3.08
B50: Tue 9-8 | C50: 0 | D50: 0 | E50: cn | H50: 2.88 | I50: =H50-C50 -> 2.88
B51: Wed 9-9 | C51: 0 | D51: 850 | E51: cn | F51: Change order received | H51: -5.05 | I51: =H51-C51 -> -5.05
B52: Thu 9-10 | C52: 0 | D52: 0 | E52: cn | H52: -75.73 | I52: =H52-C52 -> -75.73
B53: Fri 9-11 | C53: 0 | D53: 0 | E53: cn | H53: 135.93 | I53: =H53-C53 -> 135.93
B54: Sat 9-12 | C54: 0 | D54: 0 | E54: cn | H54: 0.93 | I54: =H54-C54 -> 0.93
B55: Total Week | C55: =SUM(C48:C54) -> 0 | D55: =SUM(D48:D54) -> 850 | H55: =SUM(H48:H54) -> 68.39 | I55: =SUM(I48:I54) -> 68.39
B56: Sun 9-13 | C56: 0 | D56: 0 | E56: cn | H56: 1.77 | I56: =H56-C56 -> 1.77
B57: Mon 9-14 | C57: 0 | D57: 0 | E57: cn | H57: 14.13 | I57: =H57-C57 -> 14.13
B58: Tue 9-15 | C58: 0 | D58: 650 | E58: cn | F58: Change order received | H58: 0.93 | I58: =H58-C58 -> 0.93
B59: Wed 9-16 | C59: 850 | D59: 0 | E59: cn | F59: Change order deposit | H59: 931.34 | I59: =H59-C59 -> 81.34
B60: Thu 9-17 | C60: 0 | D60: 0 | E60: cn | H60: -99.46 | I60: =H60-C60 -> -99.46
B61: Fri 9-18 | C61: 0 | D61: 0 | E61: cn | H61: 49.47 | I61: =H61-C61 -> 49.47
B62: Sat 9-19 | C62: 0 | D62: 0 | E62: cn | H62: -28 | I62: =H62-C62 -> -28
B63: Total Week | C63: =SUM(C56:C62) -> 850 | D63: =SUM(D56:D62) -> 650 | H63: =SUM(H56:H62) -> 870.18 | I63: =SUM(I56:I62) -> 20.18
B64: Sun 9-20 | C64: 0 | D64: 0 | E64: bl | H64: 42.54 | I64: =H64-C64 -> 42.54
B65: Mon 9-21 | C65: 0 | D65: 0 | E65: bl | H65: -19.35 | I65: =H65-C65 -> -19.35
B66: Tue 9-22 | C66: 0 | D66: 800 | E66: bl | F66: Change order received | H66: -5.06 | I66: =H66-C66 -> -5.06
B67: Wed 9-23 | C67: 650 | D67: 0 | E67: cn | F67: Change order deposit | H67: 548.78 | I67: =H67-C67 -> -101.22
B68: Thu 9-24 | C68: 0 | D68: 0 | E68: cn | F68: Norms 77 birthday | H68: 8.46 | I68: =H68-C68 -> 8.46
B69: Fri 9-25 | C69: 0 | D69: 0 | E69: cn | H69: -22.26 | I69: =H69-C69 -> -22.26
B70: Sat 9-26 | C70: 0 | D70: 0 | E70: bl | H70: 3.05 | I70: =H70-C70 -> 3.05
B71: Total Week | C71: =SUM(C64:C70) -> 650 | D71: =SUM(D64:D70) -> 800 | E71: cn | H71: =SUM(H64:H70) -> 556.16 | I71: =SUM(I64:I70) -> -93.84
B72: Sun 9-27 | C72: 0 | D72: 0 | E72: cn | H72: -37.16 | I72: =H72-C72 -> -37.16
B73: Mon 9-28 | C73: 0 | D73: 0 | E73: cn | H73: 100.34 | I73: =H73-C73 -> 100.34
B74: Tue 9-29 | C74: 800 | D74: 800 | E74: cn | F74: Change order received / change order deposit | H74: 731 | I74: =H74-C74 -> -69
B75: Wed 9-30 | C75: 0 | D75: 0 | E75: bl | H75: -18.81 | I75: =H75-C75 -> -18.81
B76: Thu 10-1 | C76: 0 | D76: 0 | E76: bl | H76: 1.17 | I76: =H76-C76 -> 1.17
B77: Fri 10-2 | C77: 0 | D77: 0 | E77: bl | H77: -89.05 | I77: =H77-C77 -> -89.05
B78: Sat 10-3 | C78: 800 | D78: 0 | E78: cn | F78: Change order deposit | H78: 844.41 | I78: =H78-C78 -> 44.41
B79: Total Week | C79: =SUM(C72:C78) -> 1600 | D79: =SUM(D72:D78) -> 800 | E79: cn | H79: =SUM(H72:H78) -> 1531.9 | I79: =SUM(I72:I78) -> -68.1
B80: Total Period | C80: =SUM(C79+C71+C63+C55) -> 3100 | D80: =SUM(D79+D71+D63+D55) -> 3100 | E80: cn | H80: =SUM(H79+H71+H63+H55) -> 3026.63 | I80: =SUM(I79+I71+I63+I55) -> -73.37
B81: Period Activity | C81: =D80+C80 -> 6200 | E81: cn | H81: =I80+H80 -> 2953.26 | I81: =J80+I80 -> -73.37
C82: Sun 10-4 | D82: After Period Close
B83: Ending Period Count of Amopunt on hand | C83: 0 | E83: cn
B85: Number of Cash Drawers | C85: 2
B87: Amount of Each Drawer | C87: 200
B89: Amount of Petty Cash | C89: 300
B91: Period11
B92: Sun 10-4 | C92: 0 | D92: 0 | E92: cn | H92: 12.1 | I92: =H92-C92 -> 12.1
B93: Mon 10-5 | C93: 0 | D93: 0 | E93: cn | H93: 9.77 | I93: =H93-C93 -> 9.77
B94: Tue 10-6 | C94: 0 | D94: 720 | E94: bl | F94: change order received | H94: 9.86 | I94: =H94-C94 -> 9.86
B95: Wed 10-7 | C95: 0 | D95: 0 | E95: bl | H95: 24.41 | I95: =H95-C95 -> 24.41
B96: Thu 10-8 | C96: 0 | D96: 0 | E96: cn | F96: miss count $80 from change order / will balance tomorrow | H96: -90 | I96: =H96-C96 -> -90
B97: Fri 10-9 | C97: 0 | D97: 0 | E97: bl | H97: 97.28 | I97: =H97-C97 -> 97.28
B98: Sat 10-10 | C98: 0 | D98: 0 | E98: bl | H98: 7.64 | I98: =H98-C98 -> 7.64
B99: Total Week | C99: =SUM(C92:C98) -> 0 | D99: =SUM(D92:D98) -> 720 | H99: =SUM(H92:H98) -> 71.06 | I99: =SUM(I92:I98) -> 71.06
B100: Sun 10-11 | C100: 0 | D100: 0 | H100: 0 | I100: =H100-C100 -> 0
B101: Mon 10-12 | C101: 0 | D101: 0 | H101: 0 | I101: =H101-C101 -> 0
B102: Tue 10-13 | C102: 0 | D102: 0 | H102: 0 | I102: =H102-C102 -> 0
B103: Wed 10-14 | C103: 0 | D103: 0 | H103: 0 | I103: =H103-C103 -> 0
B104: Thu 10-15 | C104: 0 | D104: 0 | H104: 0 | I104: =H104-C104 -> 0
B105: Fri 10-16 | C105: 0 | D105: 0 | H105: 0 | I105: =H105-C105 -> 0
B106: Sat 10-17 | C106: 0 | D106: 0 | H106: 0 | I106: =H106-C106 -> 0
B107: Total Week | C107: =SUM(C100:C106) -> 0 | D107: =SUM(D100:D106) -> 0 | H107: =SUM(H100:H106) -> 0 | I107: =SUM(I100:I106) -> 0
B108: Sun 10-18 | C108: 0 | D108: 0 | H108: 0 | I108: =H108-C108 -> 0
...

Sheet CR
C1: Carson
C2: Per Restaurant
C3: Chage Order Deposits | D3: Change Order Received | E3: Initials | F3: Comments | H3: Cash over/ (Short) per R365 Flash report | I3: True Over/ (Short)
B4: =Control!$B$3 -> 46243 | C4: 0 | D4: 0 | H4: 31.2 | I4: =H4-C4 -> 31.2
B5: =B4+1 -> 46244 | C5: 0 | D5: 0 | H5: 1081.44 | I5: =H5-C5 -> 1081.44
B6: =B5+1 -> 46245 | C6: 0 | D6: 0 | H6: -137.56 | I6: =H6-C6 -> -137.56
B7: =B6+1 -> 46246 | C7: 0 | D7: 0 | H7: -8.59 | I7: =H7-C7 -> -8.59
B8: =B7+1 -> 46247 | C8: 0 | D8: 0 | H8: 25.98 | I8: =H8-C8 -> 25.98
B9: =B8+1 -> 46248 | C9: 0 | D9: 0 | H9: -23.91 | I9: =H9-C9 -> -23.91
B10: =B9+1 -> 46249 | C10: 0 | D10: 0 | H10: -18.19 | I10: =H10-C10 -> -18.19
B11: Total Week | C11: =SUM(C4:C10) -> 0 | D11: =SUM(D4:D10) -> 0 | H11: =SUM(H4:H10) -> 950.37 | I11: =SUM(I4:I10) -> 950.37
B12: =B10+1 -> 46250 | C12: 0 | D12: 0 | H12: 200.32 | I12: =H12-C12 -> 200.32
B13: =B12+1 -> 46251 | C13: 0 | D13: 0 | H13: -189.65 | I13: =H13-C13 -> -189.65
B14: =B13+1 -> 46252 | C14: 0 | D14: 0 | H14: -22.4 | I14: =H14-C14 -> -22.4
B15: =B14+1 -> 46253 | C15: 0 | D15: 0 | H15: -21.06 | I15: =H15-C15 -> -21.06
B16: =B15+1 -> 46254 | C16: 0 | D16: 0 | H16: -0.46 | I16: =H16-C16 -> -0.46
B17: =B16+1 -> 46255 | C17: 0 | D17: 0 | H17: -34.57 | I17: =H17-C17 -> -34.57
B18: =B17+1 -> 46256 | C18: 0 | D18: 0 | H18: -37.49 | I18: =H18-C18 -> -37.49
B19: Total Week | C19: =SUM(C12:C18) -> 0 | D19: =SUM(D12:D18) -> 0 | H19: =SUM(H12:H18) -> -105.31 | I19: =SUM(I12:I18) -> -105.31
B20: =B18+1 -> 46257 | C20: 0 | D20: 0 | H20: -106 | I20: =H20-C20 -> -106
B21: =B20+1 -> 46258 | C21: 0 | D21: 0 | H21: 4 | I21: =H21-C21 -> 4
B22: =B21+1 -> 46259 | C22: 1400 | D22: 700 | E22: SM,NJ,TB | F22: Paid $ 1,400 Change Order /Recieved $700.00 | H22: 680 | I22: =H22-C22 -> -720
B23: =B22+1 -> 46260 | C23: 0 | H23: -9 | I23: =H23-C23 -> -9
B24: =B23+1 -> 46261 | C24: 0 | D24: 0 | H24: 19 | I24: =H24-C24 -> 19
B25: =B24+1 -> 46262 | C25: 0 | D25: 0 | H25: -49 | I25: =H25-C25 -> -49
B26: =B25+1 -> 46263 | C26: 0 | D26: 0 | H26: 13 | I26: =H26-C26 -> 13
B27: Total Week | C27: =SUM(C20:C26) -> 1400 | D27: =SUM(D20:D26) -> 700 | H27: =SUM(H20:H26) -> 552 | I27: =SUM(I20:I26) -> -848
B28: =B26+1 -> 46264 | C28: 0 | D28: 0 | H28: -1767 | I28: =H28-C28 -> -1767
B29: =B28+1 -> 46265 | C29: 0 | D29: 0 | H29: -1205 | I29: =H29-C29 -> -1205
B30: =B29+1 -> 46266 | C30: 700 | D30: 1500 | E30: SM,NJ,TB | F30: Paid$700.00 Change Order/Recieved $1,500 | H30: 720 | I30: =H30-C30 -> 20
B31: =B30+1 -> 46267 | C31: 0 | D31: 0 | H31: -21 | I31: =H31-C31 -> -21
B32: =B31+1 -> 46268 | C32: 0 | D32: 0 | H32: -798 | I32: =H32-C32 -> -798
B33: =B32+1 -> 46269 | C33: 0 | D33: 0 | H33: 0 | I33: =H33-C33 -> 0
B34: =B33+1 -> 46270 | C34: 0 | D34: 0 | H34: -20 | I34: =H34-C34 -> -20
B35: Total Week | C35: =SUM(C28:C34) -> 700 | D35: =SUM(D28:D34) -> 1500 | H35: =SUM(H28:H34) -> -3091 | I35: =SUM(I28:I34) -> -3791
B36: Total Period | C36: =SUM(C35+C27+C19+C11) -> 2100 | D36: =SUM(D35+D27+D19+D11) -> 2200 | H36: =SUM(H35+H27+H19+H11) -> -1693.94 | I36: =SUM(I35+I27+I19+I11) -> -3793.94
B37: Period Activity | C37: =D36+C36 -> 4300 | H37: =I36+H36 -> -5487.88 | I37: =J36+I36 -> -3793.94
C38: =B34+1 -> 46271 | D38: After Period Close
B39: Ending Period Count of Amount on hand | C39: 1500 | E39: NJ
B41: Number of Cash Drawers | C41: 2
B43: Amount of Each Drawer | C43: 200
B45: Amount of Petty Cash | C45: 300
B47: Period10
B48: Sun 9-6 | C48: 0 | D48: 0 | H48: -26 | I48: =H48-C48 -> -26
B49: Mon 9-7 | C49: 0 | D49: 0 | H49: -134 | I49: =H49-C49 -> -134
B50: Tue 9-8 | C50: 0 | D50: 0 | H50: -17 | I50: =H50-C50 -> -17
B51: Wed 9-9 | C51: 1500 | D51: 1760 | E51: SM,NJ,TB | H51: 1550 | I51: =H51-C51 -> 50
B52: Thu 9-10 | C52: 0 | D52: 0 | H52: 93 | I52: =H52-C52 -> 93
B53: Fri 9-11 | C53: 0 | D53: 0 | H53: -43 | I53: =H53-C53 -> -43
B54: Sat 9-12 | D54: 0 | H54: 8 | I54: =H54-C54 -> 8
B55: Total Week | C55: =SUM(C48:C54) -> 1500 | D55: =SUM(D48:D54) -> 1760 | H55: =SUM(H48:H54) -> 1431 | I55: =SUM(I48:I54) -> -69
B56: Sun 9-13 | C56: 0 | D56: 0 | E56: TB | H56: -103 | I56: =H56-C56 -> -103
B57: Mon 9-14 | C57: 0 | D57: 0 | E57: TB | H57: -59 | I57: =H57-C57 -> -59
B58: Tue 9-15 | C58: 0 | D58: 0 | E58: TB | H58: -13.81 | I58: =H58-C58 -> -13.81
B59: Wed 9-16 | C59: 0 | D59: 0 | E59: TB | H59: -56.53 | I59: =H59-C59 -> -56.53
B60: Thu 9-17 | C60: 0 | D60: 0 | E60: TB | H60: -50.84 | I60: =H60-C60 -> -50.84
B61: Fri 9-18 | C61: 0 | D61: 0 | E61: TB | H61: -10.16 | I61: =H61-C61 -> -10.16
B62: Sat 9-19 | C62: 0 | D62: 0 | E62: TB | H62: -4.58 | I62: =H62-C62 -> -4.58
B63: Total Week | C63: =SUM(C56:C62) -> 0 | D63: =SUM(D56:D62) -> 0 | H63: =SUM(H56:H62) -> -297.92 | I63: =SUM(I56:I62) -> -297.92
B64: Sun 9-20 | C64: 0 | D64: 0 | E64: YH | F64: 40$short Victor & Esme | H64: -83 | I64: =H64-C64 -> -83
B65: Mon 9-21 | C65: 0 | D65: 0 | E65: YH | H65: -1.4 | I65: =H65-C65 -> -1.4
B66: Tue 9-22 | C66: 0 | D66: 0 | E66: Yh | H66: -0.7 | I66: =H66-C66 -> -0.7
B67: Wed 9-23 | C67: 0 | D67: 0 | E67: YH | H67: 3.25 | I67: =H67-C67 -> 3.25
B68: Thu 9-24 | C68: 0 | D68: 0 | E68: SM | F68: Short $39 Victor Drawer | H68: -39 | I68: =H68-C68 -> -39
B69: Fri 9-25 | C69: 0 | D69: 0 | E69: TB | H69: 14 | I69: =H69-C69 -> 14
B70: Sat 9-26 | C70: 0 | D70: 0 | E70: YH | F70: Victor cashier | H70: -29 | I70: =H70-C70 -> -29
B71: Total Week | C71: =SUM(C64:C70) -> 0 | D71: =SUM(D64:D70) -> 0 | E71: YH | H71: =SUM(H64:H70) -> -135.85 | I71: =SUM(I64:I70) -> -135.85
B72: Sun 9-27 | C72: 0 | D72: 0 | E72: YH | F72: Cash refund to guest | H72: -17.19 | I72: =H72-C72 -> -17.19
B73: Mon 9-28 | C73: 0 | D73: 0 | E73: nj | H73: 96.99 | I73: =H73-C73 -> 96.99
B74: Tue 9-29 | C74: 0 | D74: 0 | E74: YH | F74: sean took $15 for product (Victor on register) | H74: -38.48 | I74: =H74-C74 -> -38.48
B75: Wed 9-30 | C75: 0 | D75: 0 | E75: YH | F75: ESme Cashier | H75: 3.46 | I75: =H75-C75 -> 3.46
B76: Thu 10-1 | C76: 0 | D76: 0 | E76: sm | F76: Over 105 | H76: 105.45 | I76: =H76-C76 -> 105.45
B77: Fri 10-2 | C77: 0 | D77: 0 | E77: SM | H77: 112.72 | I77: =H77-C77 -> 112.72
B78: Sat 10-3 | D78: 0 | E78: YH | H78: -61.9 | I78: =H78-C78 -> -61.9
B79: Total Week | C79: =SUM(C72:C78) -> 0 | D79: =SUM(D72:D78) -> 0 | H79: =SUM(H72:H78) -> 201.05 | I79: =SUM(I72:I78) -> 201.05
B80: Total Period | C80: =SUM(C79+C71+C63+C55) -> 1500 | D80: =SUM(D79+D71+D63+D55) -> 1760 | H80: =SUM(H79+H71+H63+H55) -> 1198.28 | I80: =SUM(I79+I71+I63+I55) -> -301.72
B81: Period Activity | C81: =D80+C80 -> 3260 | H81: =I80+H80 -> 896.56 | I81: =J80+I80 -> -301.72
C82: Sun 10-4 | D82: After Period Close
B83: Ending Period Count of Amopunt on hand | C83: 1760 | E83: NJ
B85: Number of Cash Drawers | C85: 2
B87: Amount of Each Drawer | C87: 200
B89: Amount of Petty Cash | C89: 300
B91: Period11
B92: Sun 10-4 | C92: 0 | D92: 0 | E92: YH | F92: Safe short $380 after putting cash back we will be -$43 short | H92: 336.96 | I92: =H92-C92 -> 336.96
B93: Mon 10-5 | D93: 1400 | E93: YH | H93: -385 | I93: =H93-C93 -> -385
B94: Tue 10-6 | C94: 1760 | D94: 0 | E94: YH | H94: 1763 | I94: =H94-C94 -> 3
B95: Wed 10-7 | C95: 0 | D95: 0 | E95: YH | H95: 3.58 | I95: =H95-C95 -> 3.58
B96: Thu 10-8 | C96: 0 | D96: 0 | E96: SM | H96: -7.04 | I96: =H96-C96 -> -7.04
B97: Fri 10-9 | C97: 0 | D97: 0 | E97: YH | F97: Alan received $80.00 in conterfeit $20's | H97: -67.46 | I97: =H97-C97 -> -67.46
B98: Sat 10-10 | C98: 0 | D98: 0 | F98: Register was short $100 | H98: 118.43 | I98: =H98-C98 -> 118.43
B99: Total Week | D99: 1400 | H99: =SUM(H92:H98) -> 1762.47 | I99: =SUM(I92:I98) -> 2.47
B100: Sun 10-11 | C100: 0 | D100: 0 | F100: Put back the $100 back to register | H100: -111.07 | I100: =H100-C100 -> -111.07
B101: Mon 10-12 | C101: 0 | D101: 0 | H101: 0 | I101: =H101-C101 -> 0
B102: Tue 10-13 | C102: 0 | D102: 0 | H102: 0 | I102: =H102-C102 -> 0
B103: Wed 10-14 | C103: 0 | D103: 0 | H103: 0 | I103: =H103-C103 -> 0
B104: Thu 10-15 | C104: 0 | D104: 0 | H104: 0 | I104: =H104-C104 -> 0
B105: Fri 10-16 | C105: 0 | D105: 0 | H105: 0 | I105: =H105-C105 -> 0
B106: Sat 10-17 | C106: 0 | D106: 0 | H106: 0 | I106: =H106-C106 -> 0
B107: Total Week | C107: =SUM(C100:C106) -> 0 | D107: =SUM(D100:D106) -> 0 | H107: =SUM(H100:H106) -> -111.07 | I107: =SUM(I100:I106) -> -111.07
B108: Sun 10-18 | C108: 0 | D108: 0 | H108: 0 | I108: =H108-C108 -> 0
...

Sheet DN
C1: Downey
C2: Per Restaurant
C3: Chage Order Deposits (Positive amount) | D3: Change Order Received | E3: Initials | F3: Comments | H3: Cash over/ (Short) per R365 Flash report | I3: True Over/ (Short)
B4: =Control!$B$3 -> 46243 | C4: 1000 | D4: 0 | E4: DJS | I4: =H4-C4 -> -1000
B5: =B4+1 -> 46244 | C5: 0 | D5: 0 | I5: =H5-C5 -> 0
B6: =B5+1 -> 46245 | C6: 0 | D6: 0 | I6: =H6-C6 -> 0
B7: =B6+1 -> 46246 | C7: 1000 | D7: 0 | E7: DJS | I7: =H7-C7 -> -1000
B8: =B7+1 -> 46247 | C8: 0 | D8: 3000 | E8: DJS | I8: =H8-C8 -> 0
B9: =B8+1 -> 46248 | C9: 0 | D9: 0 | I9: =H9-C9 -> 0
B10: =B9+1 -> 46249 | C10: 0 | D10: 0 | I10: =H10-C10 -> 0
B11: Total Week | C11: =SUM(C4:C10) -> 2000 | D11: =SUM(D4:D10) -> 3000 | H11: =SUM(H4:H10) -> 0 | I11: =SUM(I4:I10) -> -2000
B12: =B10+1 -> 46250 | C12: 1000 | D12: 0 | I12: =H12-C12 -> -1000
B13: =B12+1 -> 46251 | C13: 1000 | D13: 0 | E13: DJS | I13: =H13-C13 -> -1000
B14: =B13+1 -> 46252 | C14: 0 | D14: 0 | I14: =H14-C14 -> 0
B15: =B14+1 -> 46253 | C15: 0 | D15: 0 | I15: =H15-C15 -> 0
B16: =B15+1 -> 46254 | C16: 0 | D16: 0 | I16: =H16-C16 -> 0
B17: =B16+1 -> 46255 | C17: 0 | D17: 0 | I17: =H17-C17 -> 0
B18: =B17+1 -> 46256 | C18: 0 | D18: 0 | I18: =H18-C18 -> 0
B19: Total Week | C19: =SUM(C12:C18) -> 2000 | D19: =SUM(D12:D18) -> 0 | H19: =SUM(H12:H18) -> 0 | I19: =SUM(I12:I18) -> -2000
B20: =B18+1 -> 46257 | C20: 1000 | D20: 0 | E20: DJS | I20: =H20-C20 -> -1000
B21: =B20+1 -> 46258 | C21: 0 | D21: 0 | E21: DB | I21: =H21-C21 -> 0
B22: =B21+1 -> 46259 | C22: 0 | D22: 0 | E22: DB | I22: =H22-C22 -> 0
B23: =B22+1 -> 46260 | C23: 990 | D23: 2990 | E23: DB | H23: 1011 | I23: =H23-C23 -> 21
B24: =B23+1 -> 46261 | C24: 0 | D24: 0 | E24: djs | H24: 15 | I24: =H24-C24 -> 15
B25: =B24+1 -> 46262 | C25: 0 | D25: 0 | E25: djs | H25: 12 | I25: =H25-C25 -> 12
B26: =B25+1 -> 46263 | C26: 1000 | D26: 0 | E26: djs | H26: 1030 | I26: =H26-C26 -> 30
B27: Total Week | C27: =SUM(C20:C26) -> 2990 | D27: =SUM(D20:D26) -> 2990 | H27: =SUM(H20:H26) -> 2068 | I27: =SUM(I20:I26) -> -922
B28: =B26+1 -> 46264 | C28: 1000 | D28: 0 | E28: djs | H28: 19 | I28: =H28-C28 -> -981
B29: =B28+1 -> 46265 | C29: 0 | D29: 0 | E29: DB | H29: 3 | I29: =H29-C29 -> 3
B30: =B29+1 -> 46266 | C30: 0 | D30: 3000 | E30: djs | F30: Ordered on Sun 8.30.26 | H30: 3007 | I30: =H30-C30 -> 3007
B31: =B30+1 -> 46267 | C31: 0 | D31: 0 | E31: DB | H31: 17 | I31: =H31-C31 -> 17
B32: =B31+1 -> 46268 | C32: 1000 | D32: 0 | E32: DJS | H32: 1012 | I32: =H32-C32 -> 12
B33: =B32+1 -> 46269 | C33: 0 | D33: 0 | E33: djs | H33: 14 | I33: =H33-C33 -> 14
B34: =B33+1 -> 46270 | C34: 0 | D34: 0 | E34: djs | H34: 8 | I34: =H34-C34 -> 8
B35: Total Week | C35: =SUM(C28:C34) -> 2000 | D35: =SUM(D28:D34) -> 3000 | H35: =SUM(H28:H34) -> 4080 | I35: =SUM(I28:I34) -> 2080
B36: Total Period | C36: =SUM(C35+C27+C19+C11) -> 8990 | D36: =SUM(D35+D27+D19+D11) -> 8990 | H36: =SUM(H35+H27+H19+H11) -> 6148 | I36: =SUM(I35+I27+I19+I11) -> -2842
B37: Period Activity | C37: =D36+C36 -> 17980 | H37: =I36+H36 -> 3306 | I37: =J36+I36 -> -2842
C38: =B34+1 -> 46271 | D38: After Period Close
B39: Ending Period Count of Amount on hand | C39: 4000
B41: Number of Cash Drawers | C41: 2
B43: Amount of Each Drawer | C43: 200
B45: Amount of Petty Cash | C45: 300
B47: Period10
B48: Sun 9-6 | C48: 1000 | D48: 0 | E48: DJS | H48: 1014 | I48: =H48-C48 -> 14
B49: Mon 9-7 | C49: 1000 | D49: 0 | E49: DB | H49: 975 | I49: =H49-C49 -> -25
B50: Tue 9-8 | C50: 0 | D50: 0 | E50: DB | H50: 38.64 | I50: =H50-C50 -> 38.64
B51: Wed 9-9 | C51: 0 | D51: 3000 | E51: DB | F51: Ordered on Sun 9.7.26 | H51: 20.98 | I51: =H51-C51 -> 20.98
B52: Thu 9-10 | C52: 0 | D52: 0 | E52: djs | H52: -2 | I52: =H52-C52 -> -2
B53: Fri 9-11 | C53: 0 | D53: 0 | E53: djs | H53: -99 | I53: =H53-C53 -> -99
B54: Sat 9-12 | C54: 1000 | D54: 0 | E54: djs | H54: 1005 | I54: =H54-C54 -> 5
B55: Total Week | C55: =SUM(C48:C54) -> 3000 | D55: =SUM(D48:D54) -> 3000 | H55: =SUM(H48:H54) -> 2952.62 | I55: =SUM(I48:I54) -> -47.38
B56: Sun 9-13 | C56: 1000 | D56: 0 | E56: djs | H56: 1093 | I56: =H56-C56 -> 93
B57: Mon 9-14 | C57: 0 | D57: 0 | E57: DB | H57: -33 | I57: =H57-C57 -> -33
B58: Tue 9-15 | C58: 1000 | D58: 3000 | E58: LH | F58: Ordered on Sun 9.13.26 | H58: 979 | I58: =H58-C58 -> -21
B59: Wed 9-16 | C59: 0 | D59: 0 | E59: djs | H59: 45 | I59: =H59-C59 -> 45
B60: Thu 9-17 | C60: 0 | D60: 0 | E60: djs | H60: 29 | I60: =H60-C60 -> 29
B61: Fri 9-18 | C61: 1000 | D61: 0 | E61: djs | H61: 915 | I61: =H61-C61 -> -85
B62: Sat 9-19 | C62: 0 | D62: 0 | E62: djs | I62: =H62-C62 -> 0
B63: Total Week | C63: =SUM(C56:C62) -> 3000 | D63: =SUM(D56:D62) -> 3000 | H63: =SUM(H56:H62) -> 3028 | I63: =SUM(I56:I62) -> 28
B64: Sun 9-20 | C64: 1000 | D64: 0 | E64: DB | H64: 980 | I64: =H64-C64 -> -20
B65: Mon 9-21 | C65: 1000 | D65: 0 | E65: DB | H65: 988 | I65: =H65-C65 -> -12
B66: Tue 9-22 | C66: 0 | D66: 3000 | E66: LH | F66: Ordered on Sun 9.20.26 | H66: 19.34 | I66: =H66-C66 -> 19.34
B67: Wed 9-23 | C67: 1000 | D67: 0 | E67: djs | F67: Petty cash was short $31-- took from pm drawer to balance | H67: 946.05 | I67: =H67-C67 -> -53.95
B68: Thu 9-24 | C68: 0 | D68: 0 | E68: djs | H68: 14 | I68: =H68-C68 -> 14
B69: Fri 9-25 | C69: 0 | D69: 0 | E69: djs | H69: -1 | I69: =H69-C69 -> -1
B70: Sat 9-26 | C70: 0 | D70: 0 | E70: DB | H70: -4.77 | I70: =H70-C70 -> -4.77
B71: Total Week | C71: =SUM(C64:C70) -> 3000 | D71: =SUM(D64:D70) -> 3000 | H71: =SUM(H64:H70) -> 2941.62 | I71: =SUM(I64:I70) -> -58.38
B72: Sun 9-27 | C72: 1000 | D72: 0 | E72: DJS | H72: 1005.26 | I72: =H72-C72 -> 5.26
B73: Mon 9-28 | D73: 0 | E73: DB | H73: -23.55 | I73: =H73-C73 -> -23.55
B74: Tue 9-29 | C74: 1000 | D74: 3000 | E74: LH | F74: Ordered on 9.27.26 | H74: 1007.19 | I74: =H74-C74 -> 7.19
B75: Wed 9-30 | C75: 0 | D75: 0 | E75: DB | H75: 2.91 | I75: =H75-C75 -> 2.91
B76: Thu 10-1 | C76: 1000 | D76: 0 | E76: djs | H76: 990 | I76: =H76-C76 -> -10
B77: Fri 10-2 | C77: 0 | D77: 0 | E77: djs | H77: 24 | I77: =H77-C77 -> 24
B78: Sat 10-3 | D78: 0 | E78: djs | H78: -0.67 | I78: =H78-C78 -> -0.67
B79: Total Week | C79: =SUM(C72:C78) -> 3000 | D79: =SUM(D72:D78) -> 3000 | H79: =SUM(H72:H78) -> 3005.14 | I79: =SUM(I72:I78) -> 5.14
B80: Total Period | C80: =SUM(C79+C71+C63+C55) -> 12000 | D80: =SUM(D79+D71+D63+D55) -> 12000 | H80: =SUM(H79+H71+H63+H55) -> 11927.38 | I80: =SUM(I79+I71+I63+I55) -> -72.62
B81: Period Activity | C81: =D80+C80 -> 24000 | H81: =I80+H80 -> 11854.76 | I81: =J80+I80 -> -72.62
C82: Sun 10-4 | D82: After Period Close
B83: Ending Period Count of Amount on hand | C83: 4000 | E83: DJS
B85: Number of Cash Drawers | C85: 2
B87: Amount of Each Drawer | C87: 200
B89: Amount of Petty Cash | C89: 300
B91: Period11
B92: Sun 10-4 | C92: 1000 | D92: 0 | E92: DB | H92: 986.43 | I92: =H92-C92 -> -13.57
B93: Mon 10-5 | C93: 0 | D93: 0 | E93: DB | H93: 11.01 | I93: =H93-C93 -> 11.01
B94: Tue 10-6 | C94: 0 | D94: 3000 | E94: DB | F94: Ordered on 10.4.26 GY No Cash All Credit had to take from Bank Cash. | H94: 227.09 | I94: =H94-C94 -> 227.09
B95: Wed 10-7 | C95: 1000 | D95: 0 | E95: DB | F95: balance from yesterday. | H95: 825 | I95: =H95-C95 -> -175
B96: Thu 10-8 | C96: 0 | D96: 0 | E96: djs | F96: Not enough cash payments versus CC tips. Borrow $14 from am drawer to balance | H96: 16 | I96: =H96-C96 -> 16
B97: Fri 10-9 | C97: 1000 | E97: djs | H97: 1019 | I97: =H97-C97 -> 19
B98: Sat 10-10 | C98: 0 | D98: 0 | E98: DB | H98: -31.61 | I98: =H98-C98 -> -31.61
B99: Total Week | C99: =SUM(C92:C98) -> 3000 | D99: =SUM(D92:D98) -> 3000 | H99: =SUM(H92:H98) -> 3052.92 | I99: =SUM(I92:I98) -> 52.92
B100: Sun 10-11 | C100: 1000 | D100: 0 | E100: DB | H100: 1025.4 | I100: =H100-C100 -> 25.4
B101: Mon 10-12 | C101: 0 | D101: 0 | H101: 0 | I101: =H101-C101 -> 0
B102: Tue 10-13 | C102: 0 | D102: 0 | H102: 0 | I102: =H102-C102 -> 0
B103: Wed 10-14 | C103: 0 | D103: 0 | H103: 0 | I103: =H103-C103 -> 0
B104: Thu 10-15 | C104: 0 | D104: 0 | H104: 0 | I104: =H104-C104 -> 0
B105: Fri 10-16 | C105: 0 | D105: 0 | H105: 0 | I105: =H105-C105 -> 0
B106: Sat 10-17 | C106: 0 | D106: 0 | H106: 0 | I106: =H106-C106 -> 0
B107: Total Week | C107: =SUM(C100:C106) -> 1000 | D107: =SUM(D100:D106) -> 0 | H107: =SUM(H100:H106) -> 1025.4 | I107: =SUM(I100:I106) -> 25.4
B108: Sun 10-18 | C108: 0 | D108: 0 | H108: 0 | I108: =H108-C108 -> 0
...

Sheet EM
C1: El Monte
C2: Per Restaurant
C3: Chage Order Deposits | D3: Change Order Received | E3: Initials | F3: Comments | H3: Cash over/ (Short) per R365 Flash report | I3: True Over/ (Short)
B4: =Control!$B$3 -> 46243 | C4: 0 | E4: CV | H4: 16.57 | I4: =H4-C4 -> 16.57
B5: =B4+1 -> 46244 | C5: 0 | D5: 0 | E5: CV | H5: 12.63 | I5: =H5-C5 -> 12.63
B6: =B5+1 -> 46245 | C6: 0 | D6: 0 | E6: CV | H6: -3.06 | I6: =H6-C6 -> -3.06
B7: =B6+1 -> 46246 | C7: 0 | D7: 0 | E7: CV | H7: -4.55 | I7: =H7-C7 -> -4.55
B8: =B7+1 -> 46247 | C8: 0 | E8: CV | H8: 51.44 | I8: =H8-C8 -> 51.44
B9: =B8+1 -> 46248 | C9: 0 | D9: 0 | E9: CV | H9: -45.54 | I9: =H9-C9 -> -45.54
B10: =B9+1 -> 46249 | C10: 0 | D10: 0 | E10: CV | H10: 14.9 | I10: =H10-C10 -> 14.9
B11: Total Week | C11: =SUM(C4:C10) -> 0 | D11: =SUM(D4:D10) -> 0 | H11: =SUM(H4:H10) -> 42.39 | I11: =SUM(I4:I10) -> 42.39
B12: =B10+1 -> 46250 | C12: 0 | D12: 0 | E12: CV | H12: -4 | I12: =H12-C12 -> -4
B13: =B12+1 -> 46251 | C13: 0 | D13: 0 | E13: CV | H13: -118.41 | I13: =H13-C13 -> -118.41
B14: =B13+1 -> 46252 | C14: 0 | D14: 0 | E14: CV | H14: 132.6 | I14: =H14-C14 -> 132.6
B15: =B14+1 -> 46253 | C15: 0 | D15: 1500 | E15: CV | H15: -1489.72 | I15: =H15-C15 -> -1489.72
B16: =B15+1 -> 46254 | C16: 1495 | E16: CV | H16: -17.93 | I16: =H16-C16 -> -1512.93
B17: =B16+1 -> 46255 | C17: 0 | D17: 0 | E17: CV | H17: 110.74 | I17: =H17-C17 -> 110.74
B18: =B17+1 -> 46256 | C18: 0 | D18: 0 | E18: CV | H18: -95.72 | I18: =H18-C18 -> -95.72
B19: Total Week | C19: =SUM(C12:C18) -> 1495 | D19: =SUM(D12:D18) -> 1500 | H19: =SUM(H12:H18) -> -1482.44 | I19: =SUM(I12:I18) -> -2977.44
B20: =B18+1 -> 46257 | C20: 0 | D20: 0 | E20: CV | H20: 16.22 | I20: =H20-C20 -> 16.22
B21: =B20+1 -> 46258 | C21: 0 | D21: 0 | E21: CV | H21: 0.65 | I21: =H21-C21 -> 0.65
B22: =B21+1 -> 46259 | C22: 0 | D22: 0 | E22: CV | H22: 7.78 | I22: =H22-C22 -> 7.78
B23: =B22+1 -> 46260 | C23: 0 | D23: 0 | E23: CV | H23: -1.2 | I23: =H23-C23 -> -1.2
B24: =B23+1 -> 46261 | C24: 0 | D24: 0 | E24: CV | H24: -2.21 | I24: =H24-C24 -> -2.21
B25: =B24+1 -> 46262 | C25: 0 | D25: 0 | E25: CV | H25: -22 | I25: =H25-C25 -> -22
B26: =B25+1 -> 46263 | C26: 0 | D26: 1655 | E26: CV | H26: 13.2 | I26: =H26-C26 -> 13.2
B27: Total Week | C27: =SUM(C20:C26) -> 0 | D27: =SUM(D20:D26) -> 1655 | E27: CV | H27: =SUM(H20:H26) -> 12.44 | I27: =SUM(I20:I26) -> 12.44
B28: =B26+1 -> 46264 | C28: 0 | D28: 0 | E28: CV | H28: -3107.7 | I28: =H28-C28 -> -3107.7
B29: =B28+1 -> 46265 | C29: 0 | D29: 0 | E29: CV | H29: 59.91 | I29: =H29-C29 -> 59.91
B30: =B29+1 -> 46266 | C30: 0 | D30: 0 | E30: CV | H30: 10 | I30: =H30-C30 -> 10
B31: =B30+1 -> 46267 | C31: 0 | D31: 0 | E31: CV | H31: 17 | I31: =H31-C31 -> 17
B32: =B31+1 -> 46268 | D32: 0 | E32: CV | H32: 1522 | I32: =H32-C32 -> 1522
B33: =B32+1 -> 46269 | C33: 1500 | D33: 1660 | E33: CV | H33: -185 | I33: =H33-C33 -> -1685
B34: =B33+1 -> 46270 | C34: 0 | E34: CV | H34: 4.59 | I34: =H34-C34 -> 4.59
B35: Total Week | C35: =SUM(C28:C34) -> 1500 | D35: =SUM(D28:D34) -> 1660 | H35: =SUM(H28:H34) -> -1679.2 | I35: =SUM(I28:I34) -> -3179.2
B36: Total Period | C36: =SUM(C35+C27+C19+C11) -> 2995 | D36: =SUM(D35+D27+D19+D11) -> 4815 | H36: =SUM(H35+H27+H19+H11) -> -3106.81 | I36: =SUM(I35+I27+I19+I11) -> -6101.81
B37: Period Activity | C37: =D36+C36 -> 7810 | H37: =I36+H36 -> -9208.62 | I37: =J36+I36 -> -6101.81
C38: =B34+1 -> 46271 | D38: After Period Close
B39: Ending Period Count of Amount on hand
B41: Number of Cash Drawers | C41: 1
B43: Amount of Each Drawer | C43: 200
B45: Amount of Petty Cash | C45: 300
B47: Period10
B48: Sun 9-6 | D48: 0 | E48: CV | H48: 14.55 | I48: =H48-C48 -> 14.55
B49: Mon 9-7 | C49: 0 | D49: 1630 | E49: CV | H49: 1644 | I49: =H49-C49 -> 1644
B50: Tue 9-8 | C50: 0 | D50: 0 | E50: CV | H50: 38.55 | I50: =H50-C50 -> 38.55
B51: Wed 9-9 | C51: 0 | D51: 0 | E51: CV | H51: 8.63 | I51: =H51-C51 -> 8.63
B52: Thu 9-10 | C52: 0 | D52: 0 | E52: CV | H52: 1.85 | I52: =H52-C52 -> 1.85
B53: Fri 9-11 | C53: 0 | D53: 0 | E53: CV | H53: 16.08 | I53: =H53-C53 -> 16.08
B54: Sat 9-12 | C54: 0 | D54: 0 | E54: CV | H54: -1.68 | I54: =H54-C54 -> -1.68
B55: Total Week | C55: =SUM(C48:C54) -> 0 | D55: =SUM(D48:D54) -> 1630 | H55: =SUM(H48:H54) -> 1721.98 | I55: =SUM(I48:I54) -> 1721.98
B56: Sun 9-13 | C56: 0 | D56: 0 | E56: CV | H56: 3.83 | I56: =H56-C56 -> 3.83
B57: Mon 9-14 | C57: 0 | D57: 0 | E57: CV | H57: 6.37 | I57: =H57-C57 -> 6.37
B58: Tue 9-15 | C58: 0 | D58: 0 | E58: CV | H58: 8.61 | I58: =H58-C58 -> 8.61
B59: Wed 9-16 | C59: 1660 | D59: 1630 | E59: CV | H59: 1692.66 | I59: =H59-C59 -> 32.66
B60: Thu 9-17 | C60: 0 | D60: 0 | E60: AC | H60: 10.37 | I60: =H60-C60 -> 10.37
B61: Fri 9-18 | C61: 0 | D61: 0 | E61: CV | H61: 18.73 | I61: =H61-C61 -> 18.73
B62: Sat 9-19 | C62: 0 | D62: 1595 | E62: CV | H62: -1.1 | I62: =H62-C62 -> -1.1
B63: Total Week | C63: =SUM(C56:C62) -> 1660 | D63: =SUM(D56:D62) -> 3225 | E63: CV | H63: =SUM(H56:H62) -> 1739.47 | I63: =SUM(I56:I62) -> 79.47
B64: Sun 9-20 | D64: 0 | E64: AC | H64: 35 | I64: =H64-C64 -> 35
B65: Mon 9-21 | C65: 0 | D65: 0 | E65: Ac | H65: -2 | I65: =H65-C65 -> -2
B66: Tue 9-22 | C66: 0 | D66: 0 | E66: AC | H66: -2 | I66: =H66-C66 -> -2
B67: Wed 9-23 | C67: 0 | D67: 1595 | E67: CV | H67: 23.25 | I67: =H67-C67 -> 23.25
B68: Thu 9-24 | C68: 0 | D68: 0 | E68: AC | H68: -3.8 | I68: =H68-C68 -> -3.8
B69: Fri 9-25 | C69: 0 | D69: 0 | E69: CV | H69: 97.6 | I69: =H69-C69 -> 97.6
B70: Sat 9-26 | C70: 1630 | D70: 0 | E70: CV | H70: 1554.39 | I70: =H70-C70 -> -75.61
B71: Total Week | C71: =SUM(C64:C70) -> 1630 | D71: =SUM(D64:D70) -> 1595 | H71: =SUM(H64:H70) -> 1702.44 | I71: =SUM(I64:I70) -> 72.44
B72: Sun 9-27 | C72: 0 | D72: 0 | E72: Ac | H72: 23 | I72: =H72-C72 -> 23
B73: Mon 9-28 | C73: 0 | D73: 0 | E73: AC | H73: -3.42 | I73: =H73-C73 -> -3.42
B74: Tue 9-29 | C74: 0 | D74: 0 | E74: AC | H74: 7.18 | I74: =H74-C74 -> 7.18
B75: Wed 9-30 | C75: 0 | D75: 0 | E75: Ac | H75: -8.24 | I75: =H75-C75 -> -8.24
B76: Thu 10-1 | C76: 0 | D76: 0 | E76: CV | H76: 11.81 | I76: =H76-C76 -> 11.81
B77: Fri 10-2 | C77: 0 | D77: 0 | E77: CV | H77: 7 | I77: =H77-C77 -> 7
B78: Sat 10-3 | D78: 0 | E78: CV | H78: -32 | I78: =H78-C78 -> -32
B79: Total Week | C79: =SUM(C72:C78) -> 0 | D79: =SUM(D72:D78) -> 0 | H79: =SUM(H72:H78) -> 5.33 | I79: =SUM(I72:I78) -> 5.33
B80: Total Period | C80: =SUM(C79+C71+C63+C55) -> 3290 | D80: =SUM(D79+D71+D63+D55) -> 6450 | H80: =SUM(H79+H71+H63+H55) -> 5169.22 | I80: =SUM(I79+I71+I63+I55) -> 1879.22
B81: Period Activity | C81: =D80+C80 -> 9740 | H81: =I80+H80 -> 7048.44 | I81: =J80+I80 -> 1879.22
C82: Sun 10-4 | D82: After Period Close
B83: Ending Period Count of Amount on hand | C83: 1595 | E83: CV
B85: Number of Cash Drawers | C85: 1
B87: Amount of Each Drawer | C87: 200
B89: Amount of Petty Cash | C89: 300
B91: Period11
B92: Sun 10-4 | C92: 0 | D92: 0 | E92: Ac | H92: 19 | I92: =H92-C92 -> 19
B93: Mon 10-5 | C93: 0 | D93: 0 | E93: Ac | H93: 12 | I93: =H93-C93 -> 12
B94: Tue 10-6 | C94: 0 | D94: 0 | E94: Ac | H94: -8 | I94: =H94-C94 -> -8
B95: Wed 10-7 | C95: 1595 | D95: 1525 | E95: CV | F95: Dropped previous Brinks bag/ received new bag today. | H95: 1604 | I95: =H95-C95 -> 9
B96: Thu 10-8 | C96: 0 | D96: 0 | E96: Ac | H96: -24 | I96: =H96-C96 -> -24
B97: Fri 10-9 | C97: 0 | D97: 0 | H97: -14 | I97: =H97-C97 -> -14
B98: Sat 10-10 | C98: 0 | D98: 0 | H98: -2 | I98: =H98-C98 -> -2
B99: Total Week | C99: =SUM(C92:C98) -> 1595 | D99: =SUM(D92:D98) -> 1525 | H99: =SUM(H92:H98) -> 1587 | I99: =SUM(I92:I98) -> -8
B100: Sun 10-11 | C100: 0 | D100: 0 | H100: 0
B101: Mon 10-12 | C101: 0 | D101: 0 | H101: 0 | I101: =H101-C101 -> 0
B102: Tue 10-13 | C102: 0 | D102: 0 | H102: 0 | I102: =H102-C102 -> 0
B103: Wed 10-14 | C103: 0 | D103: 0 | H103: 0 | I103: =H103-C103 -> 0
B104: Thu 10-15 | C104: 0 | D104: 0 | H104: 0 | I104: =H104-C104 -> 0
B105: Fri 10-16 | C105: 0 | D105: 0 | H105: 0 | I105: =H105-C105 -> 0
B106: Sat 10-17 | C106: 0 | D106: 0 | H106: 0 | I106: =H106-C106 -> 0
B107: Total Week | C107: =SUM(C100:C106) -> 0 | D107: =SUM(D100:D106) -> 0 | H107: =SUM(H100:H106) -> 0 | I107: =SUM(I100:I106) -> 0
B108: Sun 10-18 | C108: 0 | D108: 0 | H108: 0 | I108: =H108-C108 -> 0
...

Sheet HW
C1: Hollywood
C2: Per Restaurant
C3: Chage Order Deposits | D3: Change Order Received | E3: Initials | F3: Comments | H3: Cash over/ (Short) per R365 Flash report | I3: True Over/ (Short)
B4: =Control!$B$3 -> 46243 | C4: 0 | D4: 0 | E4: RR | H4: -111 | I4: =H4-C4 -> -111
B5: =B4+1 -> 46244 | C5: 0 | D5: 0 | E5: RR | H5: -7 | I5: =H5-C5 -> -7
B6: =B5+1 -> 46245 | D6: 1000 | E6: RR | H6: 43 | I6: =H6-C6 -> 43
B7: =B6+1 -> 46246 | C7: -500 | E7: RR | H7: 6 | I7: =H7-C7 -> 506
B8: =B7+1 -> 46247 | C8: 0 | D8: 0 | E8: RR | H8: -9 | I8: =H8-C8 -> -9
B9: =B8+1 -> 46248 | D9: 980 | E9: RR | H9: -1001 | I9: =H9-C9 -> -1001
B10: =B9+1 -> 46249 | C10: -500 | D10: 500 | E10: RR | H10: 941 | I10: =H10-C10 -> 1441
B11: Total Week | C11: =SUM(C4:C10) -> -1000 | D11: =SUM(D4:D10) -> 2480 | E11: RR | H11: =SUM(H4:H10) -> -138 | I11: =SUM(I4:I10) -> 862
B12: =B10+1 -> 46250 | C12: 0 | D12: 0 | E12: RR | H12: 2 | I12: =H12-C12 -> 2
B13: =B12+1 -> 46251 | C13: 0 | D13: 0 | E13: RR | H13: -1 | I13: =H13-C13 -> -1
B14: =B13+1 -> 46252 | C14: 0 | D14: 0 | E14: RR | H14: -34 | I14: =H14-C14 -> -34
B15: =B14+1 -> 46253 | C15: -1000 | E15: RR | H15: 2038 | I15: =H15-C15 -> 3038
B16: =B15+1 -> 46254 | C16: 0 | D16: 0 | E16: RR | H16: -16 | I16: =H16-C16 -> -16
B17: =B16+1 -> 46255 | D17: 1600 | E17: RR | H17: -1591 | I17: =H17-C17 -> -1591
B18: =B17+1 -> 46256 | C18: 0 | D18: 0 | E18: RR | H18: -38 | I18: =H18-C18 -> -38
B19: Total Week | C19: =SUM(C12:C18) -> -1000 | D19: =SUM(D12:D18) -> 1600 | E19: RR | H19: =SUM(H12:H18) -> 360 | I19: =SUM(I12:I18) -> 1360
B20: =B18+1 -> 46257 | C20: 0 | D20: 0 | E20: RR | H20: -78 | I20: =H20-C20 -> -78
B21: =B20+1 -> 46258 | C21: 0 | D21: 0 | E21: RR | H21: 14 | I21: =H21-C21 -> 14
B22: =B21+1 -> 46259 | C22: 0 | D22: 0 | E22: RR | H22: -7 | I22: =H22-C22 -> -7
B23: =B22+1 -> 46260 | C23: -500 | E23: RR | H23: 1008 | I23: =H23-C23 -> 1508
B24: =B23+1 -> 46261 | C24: 0 | D24: 0 | E24: RR | H24: -1 | I24: =H24-C24 -> -1
B25: =B24+1 -> 46262 | C25: 0 | D25: 980 | E25: RR | H25: -1 | I25: =H25-C25 -> -1
B26: =B25+1 -> 46263 | C26: 0 | D26: 0 | E26: RR | H26: -7 | I26: =H26-C26 -> -7
B27: Total Week | C27: =SUM(C20:C26) -> -500 | D27: =SUM(D20:D26) -> 980 | E27: RR | H27: =SUM(H20:H26) -> 928 | I27: =SUM(I20:I26) -> 1428
B28: =B26+1 -> 46264 | C28: 0 | D28: 0 | E28: RR | H28: -193 | I28: =H28-C28 -> -193
B29: =B28+1 -> 46265 | C29: 0 | D29: 0 | E29: RR | H29: -144 | I29: =H29-C29 -> -144
B30: =B29+1 -> 46266 | C30: 0 | D30: 0 | E30: RR | H30: -1 | I30: =H30-C30 -> -1
B31: =B30+1 -> 46267 | C31: -500 | D31: 0 | E31: RR | H31: 308 | I31: =H31-C31 -> 808
B32: =B31+1 -> 46268 | C32: 0 | D32: 0 | E32: RR | H32: 208 | I32: =H32-C32 -> 208
B33: =B32+1 -> 46269 | C33: 0 | D33: 0 | E33: RR | H33: -35 | I33: =H33-C33 -> -35
B34: =B33+1 -> 46270 | C34: -500 | D34: 0 | E34: RR | H34: 506 | I34: =H34-C34 -> 1006
B35: Total Week | C35: =SUM(C28:C34) -> -1000 | D35: =SUM(D28:D34) -> 0 | H35: =SUM(H28:H34) -> 649 | I35: =SUM(I28:I34) -> 1649
B36: Total Period | C36: =SUM(C35+C27+C19+C11) -> -3500 | D36: =SUM(D35+D27+D19+D11) -> 5060 | H36: =SUM(H35+H27+H19+H11) -> 1799 | I36: =SUM(I35+I27+I19+I11) -> 5299
B37: Period Activity | C37: =D36+C36 -> 1560 | H37: =I36+H36 -> 7098 | I37: =J36+I36 -> 5299
C38: =B34+1 -> 46271 | D38: After Period Close
B39: Ending Period Count of Amopunt on hand | C39: 3080 | E39: RR JA
B41: Number of Cash Drawers | C41: 2
B43: Amount of Each Drawer | C43: 200
B45: Amount of Petty Cash | C45: 300
B47: Period10
B48: Sun 9-6 | C48: 955 | D48: 0 | E48: RR | F48: Change order deposited | H48: -49 | I48: =H48-C48 -> -1004
B49: Mon 9-7 | C49: 0 | D49: 0 | E49: RR | H49: 952 | I49: =H49-C49 -> 952
B50: Tue 9-8 | C50: 0 | D50: 0 | E50: RR | H50: -13 | I50: =H50-C50 -> -13
B51: Wed 9-9 | C51: 0 | D51: 0 | E51: RR | H51: 3 | I51: =H51-C51 -> 3
B52: Thu 9-10 | C52: 500 | D52: 1495 | E52: RR | F52: Change order received / Deposited | H52: 275
B53: Fri 9-11 | C53: 0 | D53: 0 | E53: RR | H53: -2 | I53: =H53-C53 -> -2
B54: Sat 9-12 | C54: 0 | D54: 0 | E54: RR | H54: -21 | I54: =H54-C54 -> -21
B55: Total Week | C55: =SUM(C48:C54) -> 1455 | D55: =SUM(D48:D54) -> 1495 | E55: RR | H55: =SUM(H48:H54) -> 1145 | I55: =SUM(I48:I54) -> -85
B56: Sun 9-13 | C56: 0 | D56: 0 | E56: RR | H56: -37 | I56: =H56-C56 -> -37
B57: Mon 9-14 | C57: 0 | D57: 0 | E57: RR | H57: 0 | I57: =H57-C57 -> 0
B58: Tue 9-15 | C58: 0 | D58: 0 | E58: RR | H58: 15 | I58: =H58-C58 -> 15
B59: Wed 9-16 | C59: 500 | D59: 0 | E59: RR | F59: Change order deposited | H59: 0 | I59: =H59-C59 -> -500
B60: Thu 9-17 | C60: 0 | D60: 0 | E60: RR | H60: 511 | I60: =H60-C60 -> 511
B61: Fri 9-18 | C61: 0 | D61: 0 | E61: RR | H61: -28 | I61: =H61-C61 -> -28
B62: Sat 9-19 | C62: 500 | D62: 0 | E62: RR | F62: Change order deposited | H62: 498 | I62: =H62-C62 -> -2
B63: Total Week | C63: =SUM(C56:C62) -> 1000 | D63: =SUM(D56:D62) -> 0 | E63: RR | H63: =SUM(H56:H62) -> 959 | I63: =SUM(I56:I62) -> -41
B64: Sun 9-20 | C64: 500 | D64: 0 | E64: RR | F64: Change order deposited | H64: 382 | I64: =H64-C64 -> -118
B65: Mon 9-21 | D65: 0 | E65: JA | H65: 3 | I65: =H65-C65 -> 3
B66: Tue 9-22 | C66: 480 | D66: 0 | E66: RR | F66: EOD deposit $100 was stuck in cash cartridge | H66: 597 | I66: =H66-C66 -> 117
B67: Wed 9-23 | C67: 0 | D67: 1490 | E67: RR | F67: Change order received / 0 short | H67: 0 | I67: =H67-C67 -> 0
B68: Thu 9-24 | C68: 0 | D68: 0 | E68: RR | H68: -2 | I68: =H68-C68 -> -2
B69: Fri 9-25 | C69: 0 | D69: 0 | E69: RR | H69: 6 | I69: =H69-C69 -> 6
B70: Sat 9-26 | C70: 0 | D70: 0 | E70: RR | H70: -23 | I70: =H70-C70 -> -23
B71: Total Week | C71: =SUM(C64:C70) -> 980 | D71: =SUM(D64:D70) -> 1490 | H71: =SUM(H64:H70) -> 963 | I71: =SUM(I64:I70) -> -17
B72: Sun 9-27 | C72: 0 | D72: 0 | E72: RR | H72: -27 | I72: =H72-C72 -> -27
B73: Mon 9-28 | C73: 0 | D73: 0 | E73: RR | H73: -7 | I73: =H73-C73 -> -7
B74: Tue 9-29 | D74: 0 | E74: JA | H74: 9 | I74: =H74-C74 -> 9
B75: Wed 9-30 | C75: 500 | D75: 0 | E75: RR | H75: 520 | I75: =H75-C75 -> 20
B76: Thu 10-1 | C76: 0 | D76: 0 | E76: RR | F76: Change order deposited | H76: 14 | I76: =H76-C76 -> 14
B77: Fri 10-2 | C77: 0 | D77: 995 | E77: RR | F77: Change order received - $500/$495 | H77: 12 | I77: =H77-C77 -> 12
B78: Sat 10-3 | D78: 0 | E78: RR | H78: 1 | I78: =H78-C78 -> 1
B79: Total Week | C79: =SUM(C72:C78) -> 500 | D79: =SUM(D72:D78) -> 995 | H79: =SUM(H72:H78) -> 522 | I79: =SUM(I72:I78) -> 22
B80: Total Period | C80: =SUM(C79+C71+C63+C55) -> 3935 | D80: =SUM(D79+D71+D63+D55) -> 3980 | H80: =SUM(H79+H71+H63+H55) -> 3589 | I80: =SUM(I79+I71+I63+I55) -> -121
B81: Period Activity | C81: =D80+C80 -> 7915 | H81: =I80+H80 -> 3468 | I81: =J80+I80 -> -121
C82: Sun 10-4 | D82: After Period Close
B83: Ending Period Count of Amopunt on hand | C83: 3125 | E83: RR
B85: Number of Cash Drawers | C85: 2
B87: Amount of Each Drawer | C87: 200
B89: Amount of Petty Cash | C89: 300
B91: Period11
B92: Sun 10-4 | C92: 0 | D92: 0 | E92: RR | H92: 25 | I92: =H92-C92 -> 25
B93: Mon 10-5 | C93: 0 | D93: 0 | E93: RR | H93: -7 | I93: =H93-C93 -> -7
B94: Tue 10-6 | C94: 0 | D94: 0 | E94: RR | H94: 12 | I94: =H94-C94 -> 12
B95: Wed 10-7 | C95: 0 | D95: 0 | E95: RR | H95: 11 | I95: =H95-C95 -> 11
B96: Thu 10-8 | C96: 0 | D96: 0 | E96: RR | H96: -5 | I96: =H96-C96 -> -5
B97: Fri 10-9 | C97: 640 | D97: 980 | E97: RR | F97: Received change order $500/$480 - Dropped paid $640 | H97: 0 | I97: =H97-C97 -> -640
B98: Sat 10-10 | C98: 0 | D98: 0 | H98: 0 | I98: =H98-C98 -> 0
B99: Total Week | C99: =SUM(C92:C98) -> 640 | D99: =SUM(D92:D98) -> 980 | H99: =SUM(H92:H98) -> 36 | I99: =SUM(I92:I98) -> -604
B100: Sun 10-11 | C100: 0 | D100: 0 | H100: 0 | I100: =H100-C100 -> 0
B101: Mon 10-12 | C101: 0 | D101: 0 | H101: 0 | I101: =H101-C101 -> 0
B102: Tue 10-13 | C102: 0 | D102: 0 | H102: 0 | I102: =H102-C102 -> 0
B103: Wed 10-14 | C103: 0 | D103: 0 | H103: 0 | I103: =H103-C103 -> 0
B104: Thu 10-15 | C104: 0 | D104: 0 | H104: 0 | I104: =H104-C104 -> 0
B105: Fri 10-16 | C105: 0 | D105: 0 | H105: 0 | I105: =H105-C105 -> 0
B106: Sat 10-17 | C106: 0 | D106: 0 | H106: 0 | I106: =H106-C106 -> 0
B107: Total Week | C107: =SUM(C100:C106) -> 0 | D107: =SUM(D100:D106) -> 0 | H107: =SUM(H100:H106) -> 0 | I107: =SUM(I100:I106) -> 0
B108: Sun 10-18 | C108: 0 | D108: 0 | H108: 0 | I108: =H108-C108 -> 0
...

Sheet HB
C1: Huntington Beach
C2: Per Restaurant
C3: Chage Order Deposits | D3: Change Order Received | E3: Initials | F3: Comments | H3: Cash over/ (Short) per R365 Flash report | I3: True Over/ (Short)
B4: =Control!$B$3 -> 46243 | C4: 0 | D4: 0 | I4: =H4-C4 -> 0
B5: =B4+1 -> 46244 | C5: 0 | D5: 0 | I5: =H5-C5 -> 0
B6: =B5+1 -> 46245 | C6: 0 | D6: 0 | I6: =H6-C6 -> 0
B7: =B6+1 -> 46246 | C7: 0 | D7: 1120 | E7: CM/JG | F7: We will pay back this money as soon as we get our next delivery | I7: =H7-C7 -> 0
B8: =B7+1 -> 46247 | C8: 0 | D8: 0 | I8: =H8-C8 -> 0
B9: =B8+1 -> 46248 | C9: 0 | D9: 0 | I9: =H9-C9 -> 0
B10: =B9+1 -> 46249 | C10: 0 | D10: 0 | I10: =H10-C10 -> 0
B11: Total Week | C11: =SUM(C4:C10) -> 0 | D11: =SUM(D4:D10) -> 1120 | H11: =SUM(H4:H10) -> 0 | I11: =SUM(I4:I10) -> 0
B12: =B10+1 -> 46250 | C12: 0 | D12: 0 | I12: =H12-C12 -> 0
B13: =B12+1 -> 46251 | C13: 0 | D13: 0 | I13: =H13-C13 -> 0
B14: =B13+1 -> 46252 | C14: 0 | D14: 0 | I14: =H14-C14 -> 0
B15: =B14+1 -> 46253 | C15: 0 | D15: 0 | I15: =H15-C15 -> 0
B16: =B15+1 -> 46254 | C16: 0 | D16: 0 | I16: =H16-C16 -> 0
B17: =B16+1 -> 46255 | C17: 0 | D17: 0 | I17: =H17-C17 -> 0
B18: =B17+1 -> 46256 | C18: 0 | D18: 0 | I18: =H18-C18 -> 0
B19: Total Week | C19: =SUM(C12:C18) -> 0 | D19: =SUM(D12:D18) -> 0 | H19: =SUM(H12:H18) -> 0 | I19: =SUM(I12:I18) -> 0
B20: =B18+1 -> 46257 | C20: 0 | D20: 0 | I20: =H20-C20 -> 0
B21: =B20+1 -> 46258 | C21: 0 | D21: 0 | I21: =H21-C21 -> 0
B22: =B21+1 -> 46259 | C22: 0 | D22: 0 | I22: =H22-C22 -> 0
B23: =B22+1 -> 46260 | C23: 0 | D23: 0 | I23: =H23-C23 -> 0
B24: =B23+1 -> 46261 | C24: 0 | D24: 0 | I24: =H24-C24 -> 0
B25: =B24+1 -> 46262 | C25: 0 | D25: 0 | I25: =H25-C25 -> 0
B26: =B25+1 -> 46263 | C26: 0 | D26: 0 | I26: =H26-C26 -> 0
B27: Total Week | C27: =SUM(C20:C26) -> 0 | D27: =SUM(D20:D26) -> 0 | H27: =SUM(H20:H26) -> 0 | I27: =SUM(I20:I26) -> 0
B28: =B26+1 -> 46264 | C28: 0 | D28: 0 | E28: FM | H28: -43.61 | I28: =H28-C28 -> -43.61
B29: =B28+1 -> 46265 | C29: 0 | D29: 0 | E29: JG | H29: 16.88 | I29: =H29-C29 -> 16.88
B30: =B29+1 -> 46266 | C30: 0 | D30: 0 | E30: JG | H30: -3.01 | I30: =H30-C30 -> -3.01
B31: =B30+1 -> 46267 | C31: 0 | D31: 0 | E31: FM | H31: -28.16 | I31: =H31-C31 -> -28.16
B32: =B31+1 -> 46268 | C32: 0 | D32: 0 | E32: CM | H32: -8.4 | I32: =H32-C32 -> -8.4
B33: =B32+1 -> 46269 | C33: 0 | D33: 0 | E33: CM | H33: 39.74 | I33: =H33-C33 -> 39.74
B34: =B33+1 -> 46270 | C34: 0 | D34: 0 | E34: CM | H34: -13.11 | I34: =H34-C34 -> -13.11
B35: Total Week | C35: =SUM(C28:C34) -> 0 | D35: =SUM(D28:D34) -> 0 | H35: =SUM(H28:H34) -> -39.67 | I35: =SUM(I28:I34) -> -39.67
B36: Total Period | C36: =SUM(C35+C27+C19+C11) -> 0 | D36: =SUM(D35+D27+D19+D11) -> 1120 | H36: =SUM(H35+H27+H19+H11) -> -39.67 | I36: =SUM(I35+I27+I19+I11) -> -39.67
B37: Period Activity | C37: =D36+C36 -> 1120 | H37: =I36+H36 -> -79.34 | I37: =J36+I36 -> -39.67
C38: =B34+1 -> 46271 | D38: After Period Close
B39: Ending Period Count of Amount on hand | C39: 1120 | E39: CM/JG | F39: We will pay back this money as soon as we get our next delivery
B41: Number of Cash Drawers | C41: 2
B43: Amount of Each Drawer | C43: 200
B45: Amount of Petty Cash | C45: 300
B47: Period10
B48: Sun 9-6 | C48: 0 | D48: 0 | E48: FM | H48: -5.48 | I48: =H48-C48 -> -5.48
B49: Mon 9-7 | C49: 0 | D49: 0 | E49: CM | H49: -23.51 | I49: =H49-C49 -> -23.51
B50: Tue 9-8 | C50: 0 | D50: 0 | E50: CM | H50: 62.73 | I50: =H50-C50 -> 62.73
B51: Wed 9-9 | C51: 0 | D51: 1275 | E51: FM | F51: We were supposed to received this order on 08/28/2026 | H51: 9.79 | I51: =H51-C51 -> 9.79
B52: Thu 9-10 | C52: 0 | D52: 0 | E52: JG | H52: -22.53 | I52: =H52-C52 -> -22.53
B53: Fri 9-11 | C53: 0 | D53: 0 | E53: JG | H53: 121.46 | I53: =H53-C53 -> 121.46
B54: Sat 9-12 | C54: 1120 | D54: 0 | E54: CM | F54: We paid change order received on 08/12/2026 | H54: 983 | I54: =H54-C54 -> -137
B55: Total Week | C55: =SUM(C48:C54) -> 1120 | D55: =SUM(D48:D54) -> 1275 | H55: =SUM(H48:H54) -> 1125.46 | I55: =SUM(I48:I54) -> 5.46
B56: Sun 9-13 | C56: 0 | D56: 0 | E56: JG | H56: 17.51 | I56: 18
B57: Mon 9-14 | C57: 0 | D57: 0 | E57: FM | H57: -66.31 | I57: =H57-C57 -> -66.31
B58: Tue 9-15 | C58: 0 | D58: 0 | E58: CM | H58: 54.41 | I58: =H58-C58 -> 54.41
B59: Wed 9-16 | C59: 0 | D59: 0 | E59: CM | H59: -10.11 | I59: =H59-C59 -> -10.11
B60: Thu 9-17 | C60: 0 | D60: 0 | E60: CM | H60: -17.66 | I60: =H60-C60 -> -17.66
B61: Fri 9-18 | C61: 0 | D61: 0 | E61: CM | H61: 36.87 | I61: =H61-C61 -> 36.87
B62: Sat 9-19 | C62: 0 | D62: 0 | E62: CM | H62: -15.74 | I62: =H62-C62 -> -15.74
B63: Total Week | C63: =SUM(C56:C62) -> 0 | D63: =SUM(D56:D62) -> 0 | H63: =SUM(H56:H62) -> -1.03 | I63: =SUM(I56:I62) -> -0.54
B64: Sun 9-20 | C64: 0 | D64: 0 | E64: CM | H64: 5.17 | I64: =H64-C64 -> 5.17
B65: Mon 9-21 | D65: 0 | E65: FM | F65: Petty cash was short $80.00 | H65: -92 | I65: =H65-C65 -> -92
B66: Tue 9-22 | C66: 0 | D66: 0 | E66: FM | H66: -20 | I66: =H66-C66 -> -20
B67: Wed 9-23 | D67: 0 | E67: CM | H67: 36.34 | I67: =H67-C67 -> 36.34
B68: Thu 9-24 | D68: 0 | E68: CM | H68: -40.12 | I68: =H68-C68 -> -40.12
B69: Fri 9-25 | C69: 0 | D69: 0 | E69: CM | H69: 54.92 | I69: =H69-C69 -> 54.92
B70: Sat 9-26 | C70: 0 | D70: 0 | E70: FM | H70: -59.23 | I70: =H70-C70 -> -59.23
B71: Total Week | C71: =SUM(C64:C70) -> 0 | D71: =SUM(D64:D70) -> 0 | H71: =SUM(H64:H70) -> -114.92 | I71: =SUM(I64:I70) -> -114.92
B72: Sun 9-27 | C72: 0 | D72: 0 | E72: CM | H72: 11.16 | I72: =H72-C72 -> 11.16
B73: Mon 9-28 | C73: 0 | D73: 0 | E73: CM | H73: 17.63 | I73: =H73-C73 -> 17.63
B74: Tue 9-29 | C74: 0 | D74: 1370 | E74: FM | F74: Change ordered received, placed on 09/24/2026 | H74: 41.36 | I74: =H74-C74 -> 41.36
B75: Wed 9-30 | D75: 0 | E75: FM | H75: 22.85 | I75: =H75-C75 -> 22.85
B76: Thu 10-1 | C76: 0 | D76: 0 | E76: CM | H76: 5.28 | I76: =H76-C76 -> 5.28
B77: Fri 10-2 | C77: 1275 | D77: 0 | E77: CM | F77: We paid change order received on 09/09/2026 | H77: 1314.46 | I77: =H77-C77 -> 39.46
B78: Sat 10-3 | D78: 0 | E78: CM | H78: -23.74 | I78: =H78-C78 -> -23.74
B79: Total Week | C79: =SUM(C72:C78) -> 1275 | D79: =SUM(D72:D78) -> 1370 | H79: =SUM(H72:H78) -> 1389 | I79: =SUM(I72:I78) -> 114
B80: Total Period | C80: =SUM(C79+C71+C63+C55) -> 2395 | D80: =SUM(D79+D71+D63+D55) -> 2645 | H80: =SUM(H79+H71+H63+H55) -> 2398.51 | I80: =SUM(I79+I71+I63+I55) -> 4
B81: Period Activity | C81: =D80+C80 -> 5040 | H81: =I80+H80 -> 2402.51 | I81: =J80+I80 -> 4
C82: Sun 10-4 | D82: After Period Close
B83: Ending Period Count of Amopunt on hand | C83: 1370 | E83: CM | F83: We will pay back this money as soon as we get our next delivery
B85: Number of Cash Drawers | C85: 2
B87: Amount of Each Drawer | C87: 200
B89: Amount of Petty Cash | C89: 300
B91: Period11
B92: Sun 10-4 | C92: 0 | D92: 0 | E92: FM | H92: -41.7 | I92: =H92-C92 -> -41.7
B93: Mon 10-5 | C93: 0 | D93: 0 | E93: FM | H93: 28.86 | I93: =H93-C93 -> 28.86
B94: Tue 10-6 | C94: 0 | D94: 0 | E94: FM | H94: 14.33 | I94: =H94-C94 -> 14.33
B95: Wed 10-7 | C95: 0 | D95: 0 | E95: FM | H95: -25.34 | I95: =H95-C95 -> -25.34
B96: Thu 10-8 | C96: 0 | D96: 0 | E96: CM | H96: 23.15 | I96: =H96-C96 -> 23.15
B97: Fri 10-9 | C97: 0 | D97: 0 | E97: CM | H97: -11.29 | I97: =H97-C97 -> -11.29
B98: Sat 10-10 | C98: 0 | D98: 0 | E98: FM | H98: -100.8 | I98: =H98-C98 -> -100.8
B99: Total Week | C99: =SUM(C92:C98) -> 0 | D99: =SUM(D92:D98) -> 0 | H99: =SUM(H92:H98) -> -112.79 | I99: =SUM(I92:I98) -> -112.79
B100: Sun 10-11 | C100: 0 | D100: 0 | H100: 0 | I100: =H100-C100 -> 0
B101: Mon 10-12 | C101: 0 | D101: 0 | H101: 0 | I101: =H101-C101 -> 0
B102: Tue 10-13 | C102: 0 | D102: 0 | H102: 0 | I102: =H102-C102 -> 0
B103: Wed 10-14 | C103: 0 | D103: 0 | H103: 0 | I103: =H103-C103 -> 0
B104: Thu 10-15 | C104: 0 | D104: 0 | H104: 0 | I104: =H104-C104 -> 0
B105: Fri 10-16 | C105: 0 | D105: 0 | H105: 0 | I105: =H105-C105 -> 0
B106: Sat 10-17 | C106: 0 | D106: 0 | H106: 0 | I106: =H106-C106 -> 0
B107: Total Week | C107: =SUM(C100:C106) -> 0 | D107: =SUM(D100:D106) -> 0 | H107: =SUM(H100:H106) -> 0 | I107: =SUM(I100:I106) -> 0
B108: Sun 10-18 | C108: 0 | D108: 0 | H108: 0 | I108: =H108-C108 -> 0
...

Sheet IG
C1: Inglewood
C2: Per Restaurant
C3: Chage Order Deposits | D3: Change Order Received | E3: Initials | F3: Comments | H3: Cash over/ (Short) per R365 Flash report | I3: True Over/ (Short)
B4: =Control!$B$3 -> 46243 | C4: 0 | D4: 4095 | E4: MH | F4: Bank Balance of $4095.00( no money was received on the week 08/09 | H4: =C4 -> 0 | I4: =H4-C4 -> 0
B5: =B4+1 -> 46244 | C5: 0 | D5: 0 | F5: till 08/15 see full report. | H5: =C5 -> 0 | I5: =H5-C5 -> 0
B6: =B5+1 -> 46245 | C6: 0 | D6: 0 | H6: =C6 -> 0 | I6: =H6-C6 -> 0
B7: =B6+1 -> 46246 | C7: 0 | D7: 0 | H7: =C7 -> 0 | I7: =H7-C7 -> 0
B8: =B7+1 -> 46247 | C8: 0 | D8: 0 | H8: =C8 -> 0 | I8: =H8-C8 -> 0
B9: =B8+1 -> 46248 | C9: 0 | D9: 0 | H9: =C9 -> 0 | I9: =H9-C9 -> 0
B10: =B9+1 -> 46249 | C10: 0 | D10: 0 | H10: =C10 -> 0 | I10: =H10-C10 -> 0
B11: Total Week | C11: =SUM(C4:C10) -> 0 | D11: =SUM(D4:D10) -> 4095 | H11: =SUM(H4:H10) -> 0 | I11: =SUM(I4:I10) -> 0
B12: =B10+1 -> 46250 | C12: 0 | D12: 0 | H12: =C12 -> 0 | I12: =H12-C12 -> 0
B13: =B12+1 -> 46251 | C13: 0 | D13: 0 | H13: =C13 -> 0 | I13: =H13-C13 -> 0
B14: =B13+1 -> 46252 | C14: 0 | D14: 0 | H14: =C14 -> 0 | I14: =H14-C14 -> 0
B15: =B14+1 -> 46253 | C15: 0 | D15: 0 | H15: =C15 -> 0 | I15: =H15-C15 -> 0
B16: =B15+1 -> 46254 | C16: 0 | D16: 0 | H16: =C16 -> 0 | I16: =H16-C16 -> 0
B17: =B16+1 -> 46255 | C17: 1695 | D17: 0 | E17: MH | H17: =C17 -> 1695 | I17: =H17-C17 -> 0
B18: =B17+1 -> 46256 | C18: 0 | D18: 0 | H18: =C18 -> 0 | I18: =H18-C18 -> 0
B19: Total Week | C19: =SUM(C12:C18) -> 1695 | D19: =SUM(D12:D18) -> 0 | H19: =SUM(H12:H18) -> 1695 | I19: =SUM(I12:I18) -> 0
B20: =B18+1 -> 46257 | C20: 0 | D20: 0 | H20: =C20 -> 0 | I20: =H20-C20 -> 0
B21: =B20+1 -> 46258 | C21: 0 | D21: 1500 | E21: GG | H21: =C21 -> 0 | I21: =H21-C21 -> 0
B22: =B21+1 -> 46259 | C22: 0 | D22: 0 | H22: =C22 -> 0 | I22: =H22-C22 -> 0
B23: =B22+1 -> 46260 | C23: 2000 | D23: 0 | H23: =C23 -> 2000 | I23: =H23-C23 -> 0
B24: =B23+1 -> 46261 | C24: 0 | D24: 0 | H24: =C24 -> 0 | I24: =H24-C24 -> 0
B25: =B24+1 -> 46262 | C25: 0 | D25: 0 | H25: =C25 -> 0 | I25: =H25-C25 -> 0
B26: =B25+1 -> 46263 | C26: 400 | D26: 0 | H26: =C26 -> 400 | I26: =H26-C26 -> 0
B27: Total Week | C27: =SUM(C20:C26) -> 2400 | D27: =SUM(D20:D26) -> 1500 | H27: =SUM(H20:H26) -> 2400 | I27: =SUM(I20:I26) -> 0
B28: =B26+1 -> 46264 | C28: 0 | D28: 0 | H28: =C28 -> 0 | I28: =H28-C28 -> 0
B29: =B28+1 -> 46265 | C29: 0 | D29: 0 | H29: =C29 -> 0 | I29: =H29-C29 -> 0
B30: =B29+1 -> 46266 | C30: 0 | D30: 2900 | E30: GG | H30: -35 | I30: =H30-C30 -> -35
B31: =B30+1 -> 46267 | C31: 0 | D31: 0 | H31: 109 | I31: =H31-C31 -> 109
B32: =B31+1 -> 46268 | C32: 0 | D32: 0 | H32: 2083 | I32: =H32-C32 -> 2083
B33: =B32+1 -> 46269 | C33: 0 | D33: 0 | H33: -21 | I33: =H33-C33 -> -21
B34: =B33+1 -> 46270 | C34: 0 | D34: 0 | H34: 71 | I34: =H34-C34 -> 71
B35: Total Week | C35: =SUM(C28:C34) -> 0 | D35: =SUM(D28:D34) -> 2900 | H35: =SUM(H28:H34) -> 2207 | I35: =SUM(I28:I34) -> 2207
B36: Total Period | C36: =SUM(C35+C27+C19+C11) -> 4095 | D36: =SUM(D35+D27+D19+D11) -> 8495 | H36: =SUM(H35+H27+H19+H11) -> 6302 | I36: =SUM(I35+I27+I19+I11) -> 2207
B37: Period Activity | C37: =D36+C36 -> 12590 | E37: MH | H37: =I36+H36 -> 8509 | I37: =J36+I36 -> 2207
C38: =B34+1 -> 46271 | D38: After Period Close
B39: Ending Period Count of Amount on hand | C39: 4400 | E39: MH
B41: Number of Cash Drawers | C41: 2
B43: Amount of Each Drawer | C43: 200
B45: Amount of Petty Cash | C45: 300
B47: Period10 | C47: 4400
B48: Sun 9-6 | C48: 0 | D48: 0 | E48: MH | I48: =H48-C48 -> 0
B49: Mon 9-7 | C49: 0 | D49: 0 | E49: SG | H49: -23.76 | I49: =H49-C49 -> -23.76
B50: Tue 9-8 | C50: 0 | D50: 0 | E50: SG | H50: -0.87 | I50: =H50-C50 -> -0.87
B51: Wed 9-9 | C51: 1500 | D51: 0 | E51: MH | H51: 1502 | I51: =H51-C51 -> 2
B52: Thu 9-10 | C52: 0 | D52: 0 | E52: MH | H52: 0.28 | I52: =H52-C52 -> 0.28
B53: Fri 9-11 | C53: 0 | D53: 2900 | E53: MH | F53: Received Change order | H53: 38.77 | I53: =H53-C53 -> 38.77
B54: Sat 9-12 | C54: 1000 | D54: 0 | E54: MH | H54: 1001 | I54: =H54-C54 -> 1
B55: Total Week | C55: =SUM(C48:C54) -> 2500 | D55: =SUM(D48:D54) -> 2900 | H55: =SUM(H48:H54) -> 2517.42 | I55: =SUM(I48:I54) -> 17.42
B56: Sun 9-13 | C56: 0 | D56: 0 | E56: SG | F56: Short $2.00 | H56: -2.49 | I56: =H56-C56 -> -2.49
B57: Mon 9-14 | C57: 0 | D57: 0 | E57: SG | F57: Short $4.00 | H57: -4 | I57: =H57-C57 -> -4
B58: Tue 9-15 | C58: 0 | D58: 0 | E58: SG | F58: Over $6.00 | H58: 5.71 | I58: =H58-C58 -> 5.71
B59: Wed 9-16 | C59: 800 | D59: 0 | E59: MH | F59: change order dropped $800 | H59: 806.77 | I59: =H59-C59 -> 6.77
B60: Thu 9-17 | C60: 0 | D60: 0 | E60: MH | F60: Short $ 15.00 | H60: -15.17 | I60: =H60-C60 -> -15.17
B61: Fri 9-18 | C61: 400 | D61: 0 | E61: MH | F61: change order dropped $400 | H61: 472 | I61: =H61-C61 -> 72
B62: Sat 9-19 | C62: 0 | D62: 0 | E62: MH | F62: Over $ 21.00 | H62: 21 | I62: =H62-C62 -> 21
B63: Total Week | C63: =SUM(C56:C62) -> 1200 | D63: =SUM(D56:D62) -> 0 | H63: =SUM(H56:H62) -> 1283.82 | I63: =SUM(I56:I62) -> 83.82
B64: Sun 9-20 | C64: 700 | D64: 0 | E64: SG | F64: Change order dropped. | H64: 684 | I64: =H64-C64 -> -16
B65: Mon 9-21 | C65: 0 | D65: 0 | E65: SG | F65: Short $ 11.00 | H65: -11.35 | I65: =H65-C65 -> -11.35
B66: Tue 9-22 | C66: 0 | D66: 0 | E66: MH | F66: Short $35.00 | H66: -34.5 | I66: =H66-C66 -> -34.5
B67: Wed 9-23 | C67: 0 | D67: 0 | E67: MH | F67: Over $ 25.00 | H67: 25.43 | I67: =H67-C67 -> 25.43
B68: Thu 9-24 | C68: 440 | D68: 440 | E68: MH | F68: The amount we received is the same amount we dropped.( Changer order) | H68: 440.54 | I68: =H68-C68 -> 0.54
B69: Fri 9-25 | C69: 0 | D69: 0 | E69: MH | F69: Over $30.00 | H69: 30.13 | I69: =H69-C69 -> 30.13
B70: Sat 9-26 | C70: 1150 | D70: 0 | E70: MH | F70: Change order dropped. | H70: 1155.85 | I70: =H70-C70 -> 5.85
B71: Total Week | C71: =SUM(C64:C70) -> 2290 | D71: =SUM(D64:D70) -> 440 | H71: =SUM(H64:H70) -> 2290.1 | I71: =SUM(I64:I70) -> 0.1
B72: Sun 9-27 | C72: 0 | D72: 0 | E72: SG | F72: short $24.00 | H72: -24.1 | I72: =H72-C72 -> -24.1
B73: Mon 9-28 | C73: 0 | D73: 0 | E73: SG | F73: Short $15.00 | H73: -15.31 | I73: =H73-C73 -> -15.31
B74: Tue 9-29 | C74: 0 | D74: 0 | E74: MH | F74: Over $7.00 | H74: 7.2 | I74: =H74-C74 -> 7.2
B75: Wed 9-30 | C75: 1000 | D75: 0 | E75: MH | F75: Change order dropped. $1000.00 | H75: 991.88 | I75: =H75-C75 -> -8.12
B76: Thu 10-1 | C76: 0 | D76: 2100 | E76: MH | F76: Change order Received $2100.00 | H76: 0.03 | I76: =H76-C76 -> 0.03
B77: Fri 10-2 | C77: 0 | D77: 0 | E77: MH | F77: Short by 19.3 | H77: -19 | I77: =H77-C77 -> -19
B78: Sat 10-3 | C78: 750 | D78: 0 | E78: MH | F78: Change order dropped.$750.00 | H78: 741.75 | I78: =H78-C78 -> -8.25
B79: Total Week | C79: =SUM(C72:C78) -> 1750 | D79: =SUM(D72:D78) -> 2100 | H79: =SUM(H72:H78) -> 1682.45 | I79: =SUM(I72:I78) -> -67.55
B80: Total Period | C80: =SUM(C79+C71+C63+C55) -> 7740 | D80: =SUM(D79+D71+D63+D55) -> 5440 | H80: =SUM(H79+H71+H63+H55) -> 7773.79 | I80: =SUM(I79+I71+I63+I55) -> 33.79
B81: Period Activity | C81: =D80+C80 -> 13180 | H81: =I80+H80 -> 7807.58 | I81: =J80+I80 -> 33.79
C82: Sun 10-4 | D82: After Period Close
B83: Ending Period Count of Amopunt on hand | C83: 2100 | E83: MH
B85: Number of Cash Drawers | C85: 2
B87: Amount of Each Drawer | C87: 200
B89: Amount of Petty Cash | C89: 300
B91: Period11
B92: Sun 10-4 | C92: 0 | D92: 0 | E92: SG | F92: Short for the day. | H92: -28 | I92: =H92-C92 -> -28
B93: Mon 10-5 | C93: 0 | D93: 0 | E93: SG | F93: Short $116.00 began to open at 6am | H93: -116.06 | I93: =H93-C93 -> -116.06
B94: Tue 10-6 | C94: 0 | D94: 0 | E94: SG | F94: Over $61.00 moving forward we are schedule to open at 6am. | H94: 61.33 | I94: =H94-C94 -> 61.33
B95: Wed 10-7 | C95: 1000 | D95: 0 | E95: MH | F95: Change order dropped $1000 | H95: 1014.34 | I95: =H95-C95 -> 14.34
B96: Thu 10-8 | D96: 0 | E96: MH | F96: over by $21.74 | H96: 21.74 | I96: =H96-C96 -> 21.74
B97: Fri 10-9 | C97: 700 | D97: 1790 | E97: MH | F97: Change Order recieved $1790.00& Change order dropped$700.00 | H97: 669.97 | I97: =H97-C97 -> -30.03
B98: Sat 10-10 | C98: 400 | D98: 0 | E98: MH | F98: Change order dropped $400 | H98: 495.78 | I98: =H98-C98 -> 95.78
B99: Total Week | C99: =SUM(C92:C98) -> 2100 | D99: =SUM(D92:D98) -> 1790 | H99: =SUM(H92:H98) -> 2119.1 | I99: =SUM(I92:I98) -> 19.1
B100: Sun 10-11 | C100: 0 | D100: 0 | H100: 0 | I100: =H100-C100 -> 0
B101: Mon 10-12 | C101: 0 | D101: 0 | H101: 0 | I101: =H101-C101 -> 0
B102: Tue 10-13 | C102: 0 | D102: 0 | H102: 0 | I102: =H102-C102 -> 0
B103: Wed 10-14 | C103: 0 | D103: 0 | H103: 0 | I103: =H103-C103 -> 0
B104: Thu 10-15 | C104: 0 | D104: 0 | H104: 0 | I104: =H104-C104 -> 0
B105: Fri 10-16 | C105: 0 | D105: 0 | H105: 0 | I105: =H105-C105 -> 0
B106: Sat 10-17 | C106: 0 | D106: 0 | H106: 0 | I106: =H106-C106 -> 0
B107: Total Week | C107: =SUM(C100:C106) -> 0 | D107: =SUM(D100:D106) -> 0 | H107: =SUM(H100:H106) -> 0 | I107: =SUM(I100:I106) -> 0
B108: Sun 10-18 | C108: 0 | D108: 0 | H108: 0 | I108: =H108-C108 -> 0
...

Sheet LC
C1: La Cienega
C2: Per Restaurant
C3: Chage Order Deposits | D3: Change Order Received | E3: Initials | F3: Comments | H3: Cash over/ (Short) per R365 Flash report | I3: True Over/ (Short)
B4: =Control!$B$3 -> 46243 | C4: 0 | D4: 0 | I4: =H4-C4 -> 0
B5: =B4+1 -> 46244 | C5: 0 | D5: 0 | I5: =H5-C5 -> 0
B6: =B5+1 -> 46245 | C6: 0 | D6: 0 | I6: =H6-C6 -> 0
B7: =B6+1 -> 46246 | C7: 0 | D7: 0 | I7: =H7-C7 -> 0
B8: =B7+1 -> 46247 | C8: 0 | D8: 0 | I8: =H8-C8 -> 0
B9: =B8+1 -> 46248 | C9: 2405 | D9: 2405 | E9: TS | F9: coin deposit recieved and drop | I9: =H9-C9 -> -2405
B10: =B9+1 -> 46249 | C10: 0 | D10: 0 | I10: =H10-C10 -> 0
B11: Total Week | C11: =SUM(C4:C10) -> 2405 | D11: =SUM(D4:D10) -> 2405 | E11: TS | H11: =SUM(H4:H10) -> 0 | I11: =SUM(I4:I10) -> -2405
B12: =B10+1 -> 46250 | C12: 0 | D12: 0 | E12: Tony S | I12: =H12-C12 -> 0
B13: =B12+1 -> 46251 | C13: 0 | D13: 0 | E13: Tony S | I13: =H13-C13 -> 0
B14: =B13+1 -> 46252 | C14: 0 | D14: 0 | E14: Tony S | I14: =H14-C14 -> 0
B15: =B14+1 -> 46253 | C15: 0 | D15: 0 | E15: Tony S | I15: =H15-C15 -> 0
B16: =B15+1 -> 46254 | C16: 1620 | D16: 1620 | E16: Tony S | F16: coin deposit recieved and drop | I16: =H16-C16 -> -1620
B17: =B16+1 -> 46255 | C17: 0 | D17: 0 | E17: Tony S | I17: =H17-C17 -> 0
B18: =B17+1 -> 46256 | C18: 0 | D18: 0 | E18: Tony S | I18: =H18-C18 -> 0
B19: Total Week | C19: =SUM(C12:C18) -> 1620 | D19: =SUM(D12:D18) -> 1620 | E19: Tony S | H19: =SUM(H12:H18) -> 0 | I19: =SUM(I12:I18) -> -1620
B20: =B18+1 -> 46257 | C20: 0 | D20: 0 | E20: Tony S | I20: =H20-C20 -> 0
B21: =B20+1 -> 46258 | C21: 0 | D21: 0 | E21: Tony S | I21: =H21-C21 -> 0
B22: =B21+1 -> 46259 | C22: 0 | D22: 0 | E22: Tony S | I22: =H22-C22 -> 0
B23: =B22+1 -> 46260 | C23: 0 | D23: 0 | E23: Tony S | I23: =H23-C23 -> 0
B24: =B23+1 -> 46261 | C24: 0 | D24: 0 | E24: Tony S | I24: =H24-C24 -> 0
B25: =B24+1 -> 46262 | C25: 0 | D25: 0 | E25: Tony S | I25: =H25-C25 -> 0
B26: =B25+1 -> 46263 | C26: 0 | D26: 0 | E26: Tony S | I26: =H26-C26 -> 0
B27: Total Week | C27: 0 | D27: 0 | E27: Tony S | H27: =SUM(H20:H26) -> 0 | I27: =SUM(I20:I26) -> 0
B28: =B26+1 -> 46264 | C28: 0 | D28: 0 | E28: Tony S | I28: =H28-C28 -> 0
B29: =B28+1 -> 46265 | C29: 2095 | D29: 2095 | E29: Tony S | F29: coin deposit recieved and drop | I29: =H29-C29 -> -2095
B30: =B29+1 -> 46266 | C30: 0 | D30: 0 | E30: Tony S | H30: -35 | I30: =H30-C30 -> -35
B31: =B30+1 -> 46267 | C31: 0 | D31: 0 | E31: Tony S | H31: 109 | I31: =H31-C31 -> 109
B32: =B31+1 -> 46268 | C32: 0 | D32: 0 | E32: Tony S | H32: 2083 | I32: =H32-C32 -> 2083
B33: =B32+1 -> 46269 | C33: 0 | D33: 0 | E33: Tony S | H33: -21 | I33: =H33-C33 -> -21
B34: =B33+1 -> 46270 | C34: 0 | D34: 0 | E34: Tony S | H34: 71 | I34: =H34-C34 -> 71
B35: Total Week | C35: =SUM(C28:C34) -> 2095 | D35: =SUM(D28:D34) -> 2095 | E35: Tony S | H35: =SUM(H28:H34) -> 2207 | I35: =SUM(I28:I34) -> 112
B36: Total Period | C36: =SUM(C35+C27+C19+C11) -> 6120 | D36: =SUM(D35+D27+D19+D11) -> 6120 | E36: Tony S | H36: =SUM(H35+H27+H19+H11) -> 2207 | I36: =SUM(I35+I27+I19+I11) -> -3913
B37: Period Activity | C37: =D36+C36 -> 12240 | E37: Tony S | H37: =I36+H36 -> -1706 | I37: =J36+I36 -> -3913
C38: =B34+1 -> 46271 | D38: After Period Close
B39: Ending Period Count of Amount on hand | C39: 2405 | E39: Tony D | F39: safe count recieved.
B41: Number of Cash Drawers | C41: 3
B43: Amount of Each Drawer | C43: 200
B45: Amount of Petty Cash | C45: 200
B47: Period10
B48: Sun 9-6 | C48: 2405 | D48: 2405 | E48: Tony S | F48: coin deposit recieved and drop | H48: -16 | I48: =H48-C48 -> -2421
B49: Mon 9-7 | C49: 0 | D49: 0 | E49: Tony S | H49: -15 | I49: =H49-C49 -> -15
B50: Tue 9-8 | C50: 0 | D50: 0 | E50: Tony S | H50: 16 | I50: =H50-C50 -> 16
B51: Wed 9-9 | C51: 0 | D51: 0 | E51: Tony S | H51: 21 | I51: =H51-C51 -> 21
B52: Thu 9-10 | C52: 2525 | D52: 2525 | E52: ym | F52: coin drop deposit recieved and drop | H52: 2433 | I52: =H52-C52 -> -92
B53: Fri 9-11 | C53: 0 | D53: 0 | E53: Tony S | H53: 60 | I53: =H53-C53 -> 60
B54: Sat 9-12 | C54: 0 | D54: 0 | E54: Tony S | H54: 207 | I54: =H54-C54 -> 207
B55: Total Week | C55: =SUM(C48:C54) -> 4930 | D55: =SUM(D48:D54) -> 4930 | E55: Tony S | H55: =SUM(H48:H54) -> 2706 | I55: =SUM(I48:I54) -> -2224
B56: Sun 9-13 | C56: 0 | D56: 0 | E56: Tony S | H56: -156 | I56: =H56-C56 -> -156
B57: Mon 9-14 | C57: 0 | D57: 0 | E57: Tony S | H57: -81 | I57: =H57-C57 -> -81
B58: Tue 9-15 | C58: 0 | D58: 0 | E58: Tony S | H58: 14 | I58: =H58-C58 -> 14
B59: Wed 9-16 | C59: 0 | D59: 0 | E59: Tony S | H59: 56 | I59: =H59-C59 -> 56
B60: Thu 9-17 | C60: 0 | D60: 0 | E60: Tony S | H60: 243 | I60: =H60-C60 -> 243
B61: Fri 9-18 | C61: 0 | D61: 0 | E61: Tony S | H61: 2439 | I61: =H61-C61 -> 2439
B62: Sat 9-19 | C62: 0 | D62: 0 | E62: Tony S | H62: -42 | I62: =H62-C62 -> -42
B63: Total Week | C63: =SUM(C56:C62) -> 0 | D63: =SUM(D56:D62) -> 0 | E63: TS | H63: =SUM(H56:H62) -> 2473 | I63: =SUM(I56:I62) -> 2473
B64: Sun 9-20 | C64: 0 | D64: 0 | E64: Tony S | H64: -13 | I64: =H64-C64 -> -13
B65: Mon 9-21 | C65: 0 | D65: 0 | E65: Tony S | H65: 0 | I65: =H65-C65 -> 0
B66: Tue 9-22 | C66: 0 | D66: 0 | E66: Tony S | H66: 15 | I66: =H66-C66 -> 15
B67: Wed 9-23 | C67: 2350 | D67: 2350 | E67: Tony S | F67: reveived and deposit | H67: 46 | I67: =H67-C67 -> -2304
B68: Thu 9-24 | C68: 0 | D68: 0 | E68: Tony S | H68: 2406.13 | I68: =H68-C68 -> 2406.13
B69: Fri 9-25 | C69: 0 | D69: 0 | E69: Tony S | F69: $100.00 drop got stock in the machine. actually $43.00 short | H69: -143 | I69: =H69-C69 -> -143
B70: Sat 9-26 | C70: 0 | D70: 0 | E70: Tony S | H70: 43 | I70: =H70-C70 -> 43
B71: Total Week | C71: =SUM(C64:C70) -> 2350 | D71: =SUM(D64:D70) -> 2350 | E71: Tony S | H71: =SUM(H64:H70) -> 2354.13 | I71: =SUM(I64:I70) -> 4.13
B72: Sun 9-27 | C72: 0 | D72: 0 | E72: Tony S | H72: -68 | I72: =H72-C72 -> -68
B73: Mon 9-28 | C73: 0 | D73: 0 | E73: Tony S | H73: 56 | I73: =H73-C73 -> 56
B74: Tue 9-29 | C74: 0 | D74: 0 | E74: Tony S | H74: -26 | I74: =H74-C74 -> -26
B75: Wed 9-30 | C75: 0 | D75: 0 | E75: Tony S | H75: 10 | I75: =H75-C75 -> 10
B76: Thu 10-1 | C76: 0 | D76: 0 | E76: Tony S | H76: 48 | I76: =H76-C76 -> 48
B77: Fri 10-2 | C77: 2150 | D77: 2150 | E77: Tony S | F77: coin order recieved and drop | H77: 2036 | I77: =H77-C77 -> -114
B78: Sat 10-3 | D78: 0 | E78: Tony S | H78: 161 | I78: =H78-C78 -> 161
B79: Total Week | C79: =SUM(C72:C78) -> 2150 | D79: =SUM(D72:D78) -> 2150 | E79: Tony S | H79: =SUM(H72:H78) -> 2217 | I79: =SUM(I72:I78) -> 67
B80: Total Period | C80: =SUM(C79+C71+C63+C55) -> 9430 | D80: =SUM(D79+D71+D63+D55) -> 9430 | E80: TS | H80: =SUM(H79+H71+H63+H55) -> 9750.13 | I80: =SUM(I79+I71+I63+I55) -> 320.13
B81: Period Activity | C81: =D80+C80 -> 18860 | H81: =I80+H80 -> 10070.26 | I81: =J80+I80 -> 320.13
C82: Sun 10-4 | D82: After Period Close
B83: Ending Period Count of Amopunt on hand | C83: 2170 | E83: TS | F83: safe money
B85: Number of Cash Drawers | C85: 3
B87: Amount of Each Drawer | C87: 200
B89: Amount of Petty Cash | C89: 200
B91: Period11
B92: Sun 10-4 | C92: 0 | D92: 0 | E92: Tony S | H92: -180 | I92: =H92-C92 -> -180
A93: -6 | B93: Mon 10-5 | C93: 0 | D93: 0 | E93: Tony S | H93: -6 | I93: =H93-C93 -> -6
B94: Tue 10-6 | C94: 0 | D94: 0 | E94: Tony S | H94: -8 | I94: =H94-C94 -> -8
B95: Wed 10-7 | C95: 0 | D95: 0 | E95: Tony S | H95: 36 | I95: =H95-C95 -> 36
B96: Thu 10-8 | C96: 2170 | D96: 2170 | E96: Tony S | F96: Coin order recieved and deposit | H96: 2185 | I96: =H96-C96 -> 15
B97: Fri 10-9 | C97: 0 | D97: 0 | E97: Tony s | H97: 36 | I97: =H97-C97 -> 36
B98: Sat 10-10 | C98: 0 | D98: 0 | E98: Ton y S | H98: -20.31 | I98: =H98-C98 -> -20.31
B99: Total Week | C99: =SUM(C92:C98) -> 2170 | D99: =SUM(D92:D98) -> 2170 | E99: Tony S | H99: =SUM(H92:H98) -> 2042.69 | I99: =SUM(I92:I98) -> -127.31
B100: Sun 10-11 | C100: 0 | D100: 0 | E100: Tony S | H100: -12.15 | I100: =H100-C100 -> -12.15
B101: Mon 10-12 | C101: 0 | D101: 0 | E101: Tony S | H101: 0 | I101: =H101-C101 -> 0
B102: Tue 10-13 | C102: 0 | D102: 0 | E102: Tony S | H102: 0 | I102: =H102-C102 -> 0
B103: Wed 10-14 | C103: 0 | D103: 0 | E103: Tony s | H103: 0 | I103: =H103-C103 -> 0
B104: Thu 10-15 | C104: 0 | D104: 0 | E104: Tony S | H104: 0 | I104: =H104-C104 -> 0
B105: Fri 10-16 | C105: 0 | D105: 0 | E105: Tony S | H105: 0 | I105: =H105-C105 -> 0
B106: Sat 10-17 | C106: 0 | D106: 0 | E106: Tony S | H106: 0 | I106: =H106-C106 -> 0
B107: Total Week | C107: =SUM(C100:C106) -> 0 | D107: =SUM(D100:D106) -> 0 | E107: Tony s | H107: =SUM(H100:H106) -> -12.15 | I107: =SUM(I100:I106) -> -12.15
B108: Sun 10-18 | C108: 0 | D108: 0 | E108: Tony S | H108: 0 | I108: =H108-C108 -> 0
...

Sheet LK
C1: Lakewood
C2: Per Restaurant
C3: Chage Order Deposits | D3: Change Order Received | E3: Initials | F3: Comments | H3: Cash over/ (Short) per R365 Flash report | I3: True Over/ (Short)
B4: =Control!$B$3 -> 46243 | C4: 0 | D4: 0 | E4: ER | H4: 27 | I4: =H4-C4 -> 27
B5: =B4+1 -> 46244 | C5: 0 | D5: 0 | E5: ER | H5: 0 | I5: =H5-C5 -> 0
B6: =B5+1 -> 46245 | C6: 0 | D6: 0 | E6: ER | H6: -85 | I6: =H6-C6 -> -85
B7: =B6+1 -> 46246 | C7: 0 | D7: 0 | E7: ER | H7: 1086 | I7: =H7-C7 -> 1086
B8: =B7+1 -> 46247 | C8: 0 | D8: 0 | E8: ER | H8: -31 | I8: =H8-C8 -> -31
B9: =B8+1 -> 46248 | C9: 0 | D9: 0 | E9: ER | H9: 141 | I9: =H9-C9 -> 141
B10: =B9+1 -> 46249 | C10: 1105 | D10: 1105 | E10: ER | H10: 50 | I10: =H10-C10 -> -1055
B11: Total Week | C11: =SUM(C4:C10) -> 1105 | D11: =SUM(D4:D10) -> 1105 | H11: =SUM(H4:H10) -> 1188 | I11: =SUM(I4:I10) -> 83
B12: =B10+1 -> 46250 | C12: 0 | D12: 0 | E12: ER | H12: 52 | I12: =H12-C12 -> 52
B13: =B12+1 -> 46251 | C13: 0 | D13: 0 | E13: ER | H13: 3 | I13: =H13-C13 -> 3
B14: =B13+1 -> 46252 | C14: 0 | E14: ER | H14: 66 | I14: =H14-C14 -> 66
B15: =B14+1 -> 46253 | C15: 0 | D15: 0 | E15: ER | H15: 2148 | I15: =H15-C15 -> 2148
B16: =B15+1 -> 46254 | C16: 0 | D16: 0 | E16: ER | H16: 0 | I16: =H16-C16 -> 0
B17: =B16+1 -> 46255 | C17: 0 | D17: 0 | E17: ER | H17: 15 | I17: =H17-C17 -> 15
B18: =B17+1 -> 46256 | C18: 0 | D18: 0 | E18: ER | H18: -12 | I18: =H18-C18 -> -12
B19: Total Week | C19: =SUM(C12:C18) -> 0 | D19: =SUM(D12:D18) -> 0 | H19: =SUM(H12:H18) -> 2272 | I19: =SUM(I12:I18) -> 2272
B20: =B18+1 -> 46257 | C20: 0 | D20: 0 | H20: -15 | I20: =H20-C20 -> -15
B21: =B20+1 -> 46258 | C21: 0 | D21: 0 | H21: 3 | I21: =H21-C21 -> 3
B22: =B21+1 -> 46259 | C22: 0 | D22: 0 | H22: 17 | I22: =H22-C22 -> 17
B23: =B22+1 -> 46260 | C23: 1350 | D23: 1350 | H23: 947 | I23: =H23-C23 -> -403
B24: =B23+1 -> 46261 | C24: 0 | D24: 0 | H24: 38 | I24: =H24-C24 -> 38
B25: =B24+1 -> 46262 | C25: 0 | D25: 0 | H25: 92 | I25: =H25-C25 -> 92
B26: =B25+1 -> 46263 | C26: 0 | D26: 0 | H26: 285 | I26: =H26-C26 -> 285
B27: Total Week | C27: =SUM(C20:C26) -> 1350 | D27: =SUM(D20:D26) -> 1350 | H27: =SUM(H20:H26) -> 1367 | I27: =SUM(I20:I26) -> 17
B28: =B26+1 -> 46264 | C28: 0 | D28: 0 | E28: ER | H28: 3 | I28: =H28-C28 -> 3
B29: =B28+1 -> 46265 | C29: 0 | D29: 0 | E29: ER | H29: 4 | I29: =H29-C29 -> 4
B30: =B29+1 -> 46266 | C30: 0 | D30: 0 | E30: ER | H30: 37 | I30: =H30-C30 -> 37
B31: =B30+1 -> 46267 | C31: 0 | D31: 0 | E31: ER | H31: 990 | I31: =H31-C31 -> 990
B32: =B31+1 -> 46268 | C32: 0 | D32: 1225 | E32: ER | F32: Received change order | H32: 104 | I32: =H32-C32 -> 104
B33: =B32+1 -> 46269 | C33: 0 | E33: ER | H33: 24 | I33: =H33-C33 -> 24
B34: =B33+1 -> 46270 | D34: 0 | E34: ER | H34: 47 | I34: =H34-C34 -> 47
B35: Total Week | C35: =SUM(C28:C34) -> 0 | D35: =SUM(D28:D34) -> 1225 | H35: =SUM(H28:H34) -> 1209 | I35: =SUM(I28:I34) -> 1209
B36: Total Period | C36: =SUM(C35+C27+C19+C11) -> 2455 | D36: =SUM(D35+D27+D19+D11) -> 3680 | H36: =SUM(H35+H27+H19+H11) -> 6036 | I36: =SUM(I35+I27+I19+I11) -> 3581
B37: Period Activity | C37: =D36+C36 -> 6135 | H37: =I36+H36 -> 9617 | I37: =J36+I36 -> 3581
C38: =B34+1 -> 46271 | D38: After Period Close
B39: Ending Period Count of Amount on hand | C39: 1525
B41: Number of Cash Drawers | C41: 2
B43: Amount of Each Drawer | C43: 200
B45: Amount of Petty Cash | C45: 300
B47: Period10
B48: Sun 9-6 | C48: 0 | D48: 0 | E48: ER | H48: -3 | I48: =H48-C48 -> -3
B49: Mon 9-7 | C49: 0 | D49: 0 | E49: Er | H49: -5 | I49: =H49-C49 -> -5
B50: Tue 9-8 | C50: 1225 | D50: 0 | E50: Er | H50: 429 | I50: =H50-C50 -> -796
B51: Wed 9-9 | D51: 1205 | E51: SP | H51: 818 | I51: =H51-C51 -> 818
B52: Thu 9-10 | D52: 0 | E52: ER | H52: 21 | I52: =H52-C52 -> 21
B53: Fri 9-11 | C53: 600 | D53: 0 | E53: ER | F53: $600.00 dropped | H53: -41 | I53: =H53-C53 -> -641
B54: Sat 9-12 | D54: 0 | E54: ER | H54: 659 | I54: =H54-C54 -> 659
B55: Total Week | C55: =SUM(C48:C54) -> 1825 | D55: =SUM(D48:D54) -> 1205 | H55: =SUM(H48:H54) -> 1878 | I55: =SUM(I48:I54) -> 53
B56: Sun 9-13 | D56: 0 | E56: SP | H56: 42 | I56: =H56-C56 -> 42
B57: Mon 9-14 | C57: 0 | D57: 0 | E57: SP | H57: -31 | I57: =H57-C57 -> -31
B58: Tue 9-15 | D58: 0 | E58: SP | H58: -107 | I58: =H58-C58 -> -107
B59: Wed 9-16 | C59: 605 | D59: 0 | E59: ER | F59: Dropped $605 by Lalo | H59: 583 | I59: =H59-C59 -> -22
B60: Thu 9-17 | C60: 0 | D60: 1200 | E60: ER | F60: Change order received | H60: 52 | I60: =H60-C60 -> 52
B61: Fri 9-18 | C61: 650 | D61: 0 | E61: ER | F61: $650.00 Change order deposit | H61: -76 | I61: =H61-C61 -> -726
B62: Sat 9-19 | D62: 0 | E62: ER | H62: 680 | I62: =H62-C62 -> 680
B63: Total Week | C63: =SUM(C56:C62) -> 1255 | D63: =SUM(D56:D62) -> 1200 | H63: =SUM(H56:H62) -> 1143 | I63: =SUM(I56:I62) -> -112
B64: Sun 9-20 | C64: 0 | D64: 0 | E64: SP | H64: 4 | I64: =H64-C64 -> 4
B65: Mon 9-21 | C65: 0 | D65: 0 | E65: SP | H65: 50 | I65: =H65-C65 -> 50
B66: Tue 9-22 | C66: 0 | D66: 0 | E66: SP | H66: 0 | I66: 0
B67: Wed 9-23 | C67: 550 | D67: 0 | E67: ER | F67: Change order Deposit | H67: 553 | I67: =H67-C67 -> 3
B68: Thu 9-24 | D68: 1220 | E68: ER | F68: Change order received | H68: -125 | I68: =H68-C68 -> -125
B69: Fri 9-25 | C69: 490 | D69: 0 | E69: ER | F69: $490 Change order deposited | H69: 458 | I69: =H69-C69 -> -32
B70: Sat 9-26 | C70: 0 | D70: 0 | E70: ER | H70: -4 | I70: =H70-C70 -> -4
B71: Total Week | C71: =SUM(C64:C70) -> 1040 | D71: =SUM(D64:D70) -> 1220 | H71: =SUM(H64:H70) -> 936 | I71: =SUM(I64:I70) -> -104
B72: Sun 9-27 | C72: 0 | D72: 0 | E72: SP | H72: 58 | I72: =H72-C72 -> 58
B73: Mon 9-28 | C73: 0 | D73: 0 | E73: JG | H73: 4 | I73: =H73-C73 -> 4
B74: Tue 9-29 | C74: 0 | D74: 0 | E74: SP | H74: 11 | I74: =H74-C74 -> 11
B75: Wed 9-30 | C75: 730 | D75: 0 | E75: SP | F75: Dropped $730 by Lalo | H75: 745 | I75: =H75-C75 -> 15
B76: Thu 10-1 | D76: 1350 | E76: ER | F76: Change Order Received | H76: -27 | I76: =H76-C76 -> -27
B77: Fri 10-2 | C77: 550 | D77: 0 | E77: ER | F77: Change order Deposited By lalo Deposit was made after 7am | H77: 591 | I77: =H77-C77 -> 41
B78: Sat 10-3 | D78: 0 | E78: ER | H78: -51 | I78: =H78-C78 -> -51
B79: Total Week | C79: =SUM(C72:C78) -> 1280 | D79: =SUM(D72:D78) -> 1350 | H79: =SUM(H72:H78) -> 1331 | I79: =SUM(I72:I78) -> 51
B80: Total Period | C80: =SUM(C79+C71+C63+C55) -> 5400 | D80: =SUM(D79+D71+D63+D55) -> 4975 | H80: =SUM(H79+H71+H63+H55) -> 5288 | I80: =SUM(I79+I71+I63+I55) -> -112
B81: Period Activity | C81: =D80+C80 -> 10375 | H81: =I80+H80 -> 5176 | I81: =J80+I80 -> -112
C82: Sun 10-4 | D82: After Period Close
B83: Ending Period Count of Amopunt on hand | C83: 800 | E83: ER
B85: Number of Cash Drawers | C85: 2
B87: Amount of Each Drawer | C87: 200
B89: Amount of Petty Cash | C89: 300
B91: Period11
B92: Sun 10-4 | C92: 700 | D92: 0 | E92: SP | F92: Change order dropped | H92: 645 | I92: =H92-C92 -> -55
B93: Mon 10-5 | C93: 0 | D93: 0 | E93: SP | H93: -64 | I93: =H93-C93 -> -64
B94: Tue 10-6 | C94: 0 | D94: 0 | E94: SP | H94: -5 | I94: =H94-C94 -> -5
B95: Wed 10-7 | C95: 0 | D95: 0 | E95: SP | H95: -7 | I95: =H95-C95 -> -7
B96: Thu 10-8 | C96: 0 | D96: 0 | E96: SP | H96: 113 | I96: =H96-C96 -> 113
B97: Fri 10-9 | C97: 100 | D97: 1180 | E97: ER | F97: Change order received & Lalo forgot to put the deposit to Aloha | H97: -2431 | I97: =H97-C97 -> -2531
B98: Sat 10-10 | C98: 780 | D98: 0 | E98: ER | H98: 796 | I98: =H98-C98 -> 16
B99: Total Week | C99: =SUM(C92:C98) -> 1580 | D99: =SUM(D92:D98) -> 1180 | H99: =SUM(H92:H98) -> -953 | I99: =SUM(I92:I98) -> -2533
B100: Sun 10-11 | C100: 0 | D100: 0 | E100: SP | H100: 0 | I100: =H100-C100 -> 0
B101: Mon 10-12 | C101: 0 | D101: 0 | E101: SP | H101: 0 | I101: =H101-C101 -> 0
B102: Tue 10-13 | C102: 0 | D102: 0 | E102: SP | H102: 0 | I102: =H102-C102 -> 0
B103: Wed 10-14 | C103: 0 | D103: 0 | E103: SP | H103: 0 | I103: =H103-C103 -> 0
B104: Thu 10-15 | C104: 0 | D104: 0 | H104: 0 | I104: =H104-C104 -> 0
B105: Fri 10-16 | C105: 0 | D105: 0 | H105: 0 | I105: =H105-C105 -> 0
B106: Sat 10-17 | C106: 0 | D106: 0 | H106: 0 | I106: =H106-C106 -> 0
B107: Total Week | C107: =SUM(C100:C106) -> 0 | D107: =SUM(D100:D106) -> 0 | H107: =SUM(H100:H106) -> 0 | I107: =SUM(I100:I106) -> 0
B108: Sun 10-18 | C108: 0 | D108: 0 | H108: 0 | I108: =H108-C108 -> 0
...

Sheet LV
C1: Las Vegas
C2: Per Restaurant
C3: Chage Order Deposits | D3: Change Order Received | E3: Initials | F3: Comments | H3: Cash over/ (Short) per R365 Flash report | I3: True Over/ (Short)
B4: =Control!$B$3 -> 46243 | C4: 0 | D4: 0 | I4: =H4-C4 -> 0
B5: =B4+1 -> 46244 | C5: 0 | D5: 0 | I5: =H5-C5 -> 0
B6: =B5+1 -> 46245 | C6: 0 | D6: 0 | I6: =H6-C6 -> 0
B7: =B6+1 -> 46246 | C7: 0 | D7: 0 | I7: =H7-C7 -> 0
B8: =B7+1 -> 46247 | C8: 0 | D8: 0 | I8: =H8-C8 -> 0
B9: =B8+1 -> 46248 | C9: 0 | D9: 0 | I9: =H9-C9 -> 0
B10: =B9+1 -> 46249 | C10: 700 | D10: 0 | E10: ADC HT | I10: =H10-C10 -> -700
B11: Total Week | C11: =SUM(C4:C10) -> 700 | D11: =SUM(D4:D10) -> 0 | E11: ADC HT | H11: =SUM(H4:H10) -> 0 | I11: =SUM(I4:I10) -> -700
B12: =B10+1 -> 46250 | C12: 0 | D12: 0 | I12: =H12-C12 -> 0
B13: =B12+1 -> 46251 | C13: 0 | D13: 0 | I13: =H13-C13 -> 0
B14: =B13+1 -> 46252 | C14: 0 | D14: 1570 | E14: ADC HT | I14: =H14-C14 -> 0
B15: =B14+1 -> 46253 | C15: 0 | D15: 0 | I15: =H15-C15 -> 0
B16: =B15+1 -> 46254 | C16: 800 | D16: 0 | E16: ADC HT | I16: =H16-C16 -> -800
B17: =B16+1 -> 46255 | C17: 0 | D17: 0 | I17: =H17-C17 -> 0
B18: =B17+1 -> 46256 | C18: 0 | D18: 0 | I18: =H18-C18 -> 0
B19: Total Week | C19: =SUM(C12:C18) -> 800 | D19: =SUM(D12:D18) -> 1570 | E19: ADC HT | H19: =SUM(H12:H18) -> 0 | I19: =SUM(I12:I18) -> -800
B20: =B18+1 -> 46257 | C20: 0 | D20: 0 | I20: =H20-C20 -> 0
B21: =B20+1 -> 46258 | C21: 0 | D21: 0 | I21: =H21-C21 -> 0
B22: =B21+1 -> 46259 | C22: 0 | D22: 0 | I22: =H22-C22 -> 0
B23: =B22+1 -> 46260 | C23: 0 | D23: 0 | I23: =H23-C23 -> 0
B24: =B23+1 -> 46261 | C24: 0 | D24: 0 | I24: =H24-C24 -> 0
B25: =B24+1 -> 46262 | C25: 0 | D25: 0 | I25: =H25-C25 -> 0
B26: =B25+1 -> 46263 | C26: 0 | D26: 0 | I26: =H26-C26 -> 0
B27: Total Week | C27: =SUM(C20:C26) -> 0 | D27: =SUM(D20:D26) -> 0 | H27: =SUM(H20:H26) -> 0 | I27: =SUM(I20:I26) -> 0
B28: =B26+1 -> 46264 | C28: 0 | D28: 0 | I28: =H28-C28 -> 0
B29: =B28+1 -> 46265 | C29: 0 | D29: 0 | I29: =H29-C29 -> 0
B30: =B29+1 -> 46266 | C30: 0 | D30: 0 | I30: =H30-C30 -> 0
B31: =B30+1 -> 46267 | C31: 0 | D31: 0 | I31: =H31-C31 -> 0
B32: =B31+1 -> 46268 | D32: 6850 | E32: ADC HT | F32: 5000 Prize Pool For Cash Grab A Cox | I32: =H32-C32 -> 0
B33: =B32+1 -> 46269 | C33: 870 | D33: 0 | E33: ADC HT | I33: =H33-C33 -> -870
B34: =B33+1 -> 46270 | C34: 0 | D34: 0 | I34: =H34-C34 -> 0
B35: Total Week | C35: =SUM(C28:C34) -> 870 | D35: =SUM(D28:D34) -> 6850 | E35: ADC HT | H35: =SUM(H28:H34) -> 0 | I35: =SUM(I28:I34) -> -870
B36: Total Period | C36: =SUM(C35+C27+C19+C11) -> 2370 | D36: =SUM(D35+D27+D19+D11) -> 8420 | E36: ADC HT | H36: =SUM(H35+H27+H19+H11) -> 0 | I36: =SUM(I35+I27+I19+I11) -> -2370
B37: Period Activity | C37: =D36+C36 -> 10790 | H37: =I36+H36 -> -2370 | I37: =J36+I36 -> -2370
C38: =B34+1 -> 46271 | D38: After Period Close
B39: Ending Period Count of Amount on hand | C39: 7550 | F39: ADC HT CG Verified by all managers
B41: Number of Cash Drawers | C41: 2
B43: Amount of Each Drawer | C43: 200
B45: Amount of Petty Cash | C45: 300
B47: Period10
B48: Sun 9-6 | C48: 0 | D48: 0 | H48: 19 | I48: =H48-C48 -> 19
B49: Mon 9-7 | C49: 0 | D49: 0 | H49: -2 | I49: =H49-C49 -> -2
B50: Tue 9-8 | C50: 0 | D50: 0 | H50: 28 | I50: =H50-C50 -> 28
B51: Wed 9-9 | C51: 0 | D51: 0 | H51: 38 | I51: =H51-C51 -> 38
B52: Thu 9-10 | C52: 0 | D52: 0 | H52: -11 | I52: =H52-C52 -> -11
B53: Fri 9-11 | C53: 0 | D53: 0 | H53: -14 | I53: =H53-C53 -> -14
B54: Sat 9-12 | C54: 5000 | D54: 0 | E54: AC | F54: $5000 Prize Fund - Paid $3277 OUT- Drop $1723 Samantha/ Hugo | H54: -707 | I54: =H54-C54 -> -5707
B55: Total Week | C55: =SUM(C48:C54) -> 5000 | D55: =SUM(D48:D54) -> 0 | H55: =SUM(H48:H54) -> -649 | I55: =SUM(I48:I54) -> -5649
B56: Sun 9-13 | C56: 800 | D56: 0 | E56: AC | F56: 2 Bags. $700 (last Period) $100 This period | H56: 803 | I56: =H56-C56 -> 3
B57: Mon 9-14 | C57: 0 | D57: 0 | E57: AC | F57: Short $4 | H57: -4 | I57: =H57-C57 -> -4
B58: Tue 9-15 | D58: 900 | E58: HT | F58: RECEIVED 2 BAGS OF $100 AND 1 BAG OF $700 IN CHANGE FUND | H58: 12 | I58: =H58-C58 -> 12
B59: Wed 9-16 | C59: 0 | D59: 0 | E59: AC | F59: Zero for over/short | I59: 0
B60: Thu 9-17 | C60: 0 | D60: 0 | E60: AC | F60: Over $10 | H60: 10 | I60: =H60-C60 -> 10
B61: Fri 9-18 | C61: 0 | D61: 0 | E61: AC | F61: Over$36 | H61: 36 | I61: =H61-C61 -> 36
B62: Sat 9-19 | C62: 950 | D62: 0 | E62: AC | F62: Change bought Bag $950 - A Cox | H62: 895 | I62: =H62-C62 -> -55
B63: Total Week | C63: =SUM(C56:C62) -> 1750 | D63: =SUM(D56:D62) -> 900 | H63: =SUM(H56:H62) -> 1752 | I63: =SUM(I56:I62) -> 2
B64: Sun 9-20 | C64: 0 | D64: 0 | E64: HT | F64: Over $32 | H64: 32 | I64: =H64-C64 -> 32
B65: Mon 9-21 | C65: 0 | D65: 0 | E65: HT | F65: Over$34 | H65: 34 | I65: =H65-C65 -> 34
B66: Tue 9-22 | C66: 0 | D66: 0 | E66: AC | F66: Over $17 | H66: 17 | I66: =H66-C66 -> 17
B67: Wed 9-23 | C67: 0 | D67: 0 | E67: AC | F67: Short $4 | H67: -8 | I67: =H67-C67 -> -8
B68: Thu 9-24 | C68: 0 | D68: 0 | E68: AC | F68: Short$11 | H68: -11 | I68: =H68-C68 -> -11
B69: Fri 9-25 | C69: 0 | D69: 0 | E69: AC | F69: Short $19 | H69: -19 | I69: =H69-C69 -> -19
B70: Sat 9-26 | C70: 0 | D70: 0 | E70: AC | F70: Over $15 | H70: 15 | I70: =H70-C70 -> 15
B71: Total Week | C71: =SUM(C64:C70) -> 0 | D71: =SUM(D64:D70) -> 0 | H71: =SUM(H64:H70) -> 60 | I71: =SUM(I64:I70) -> 60
B72: Sun 9-27 | C72: 900 | D72: 1600 | E72: AC | F72: Change Order Received $1600 (2x $100 & 2x $700) // Change buy drop $900 (2x$100 & 1x $700) | H72: -7 | I72: =H72-C72 -> -907
B73: Mon 9-28 | C73: 0 | D73: 0 | E73: AC | F73: Bounce from prior day | H73: 67 | I73: =H73-C73 -> 67
B74: Tue 9-29 | C74: 0 | D74: 0 | E74: AC | F74: Over $16 | H74: 16 | I74: =H74-C74 -> 16
B75: Wed 9-30 | C75: 0 | D75: 0 | E75: AC | F75: Deposit of 347 enetered was imcorrect. Deposit was $505 for 10/1/26. This created a $6 overage. | H75: 6 | I75: =H75-C75 -> 6
B76: Thu 10-1 | C76: 0 | D76: 0 | E76: HT | F76: over 6$ | H76: 6 | I76: =H76-C76 -> 6
B77: Fri 10-2 | C77: 0 | D77: 0 | E77: HT | F77: over $10 | H77: 10 | I77: =H77-C77 -> 10
B78: Sat 10-3 | C78: 800 | D78: 0 | E78: HT | F78: Change bought - Bag of $700 and Bag of $100 - A Cox | H78: 830 | I78: =H78-C78 -> 30
B79: Total Week | C79: =SUM(C72:C78) -> 1700 | D79: =SUM(D72:D78) -> 1600 | H79: =SUM(H72:H78) -> 928 | I79: =SUM(I72:I78) -> -772
B80: Total Period | C80: =SUM(C79+C71+C63+C55) -> 8450 | D80: =SUM(D79+D71+D63+D55) -> 2500 | H80: =SUM(H79+H71+H63+H55) -> 2091 | I80: =SUM(I79+I71+I63+I55) -> -6359
B81: Period Activity | C81: =D80+C80 -> 10950 | H81: =I80+H80 -> -4268 | I81: =J80+I80 -> -6359
C82: Sun 10-4 | D82: After Period Close
B83: Ending Period Count of Amount on hand | C83: 1600 | E83: AC/HT
B85: Number of Cash Drawers | C85: 2
B87: Amount of Each Drawer | C87: 200
B89: Amount of Petty Cash | C89: 300
B91: Period11
B92: Sun 10-4 | C92: 0 | E92: HT | F92: Short $2 | H92: -2 | I92: =H92-C92 -> -2
B93: Mon 10-5 | C93: 0 | D93: 0 | E93: HT | F93: Over $7 | H93: 7 | I93: =H93-C93 -> 7
B94: Tue 10-6 | C94: 0 | D94: 0 | E94: AC | F94: Over $45 | H94: 45 | I94: =H94-C94 -> 45
B95: Wed 10-7 | C95: 0 | D95: 1490 | E95: AC | F95: C/O Received (1 x $90 & 2 x $700) // Short$20 | H95: -20 | I95: =H95-C95 -> -20
B96: Thu 10-8 | C96: 0 | D96: 0 | E96: AC | F96: Over $4 | H96: 4 | I96: =H96-C96 -> 4
B97: Fri 10-9 | C97: 0 | D97: 0 | E97: AC | F97: Over $24 | H97: 24 | I97: =H97-C97 -> 24
B98: Sat 10-10 | C98: 0 | D98: 0 | H98: 0 | I98: =H98-C98 -> 0
B99: Total Week | C99: =SUM(C92:C98) -> 0 | D99: =SUM(D92:D98) -> 1490 | H99: =SUM(H92:H98) -> 58 | I99: =SUM(I92:I98) -> 58
B100: Sun 10-11 | C100: 0 | D100: 0 | H100: 0 | I100: =H100-C100 -> 0
B101: Mon 10-12 | C101: 0 | D101: 0 | H101: 0 | I101: =H101-C101 -> 0
B102: Tue 10-13 | C102: 0 | D102: 0 | H102: 0 | I102: =H102-C102 -> 0
B103: Wed 10-14 | C103: 0 | D103: 0 | H103: 0 | I103: =H103-C103 -> 0
B104: Thu 10-15 | C104: 0 | D104: 0 | H104: 0 | I104: =H104-C104 -> 0
B105: Fri 10-16 | C105: 0 | D105: 0 | H105: 0 | I105: =H105-C105 -> 0
B106: Sat 10-17 | C106: 0 | D106: 0 | H106: 0 | I106: =H106-C106 -> 0
B107: Total Week | C107: =SUM(C100:C106) -> 0 | D107: =SUM(D100:D106) -> 0 | H107: =SUM(H100:H106) -> 0 | I107: =SUM(I100:I106) -> 0
B108: Sun 10-18 | C108: 0 | D108: 0 | H108: 0 | I108: =H108-C108 -> 0
...

Sheet ON
C1: Ontario
C2: Per Restaurant
C3: Chage Order Deposits | D3: Change Order Received | E3: Initials | F3: Comments | H3: Cash over/ (Short) per R365 Flash report | I3: True Over/ (Short)
B4: =Control!$B$3 -> 46243 | C4: 0 | D4: 0 | I4: =H4-C4 -> 0
B5: =B4+1 -> 46244 | C5: -700 | F5: The payment in column c pays the outstanding balance at the end of Per08 | I5: =H5-C5 -> 700
B6: =B5+1 -> 46245 | C6: 0 | D6: 700 | I6: =H6-C6 -> 0
B7: =B6+1 -> 46246 | C7: 0 | D7: 0 | I7: =H7-C7 -> 0
B8: =B7+1 -> 46247 | C8: 0 | D8: 0 | I8: =H8-C8 -> 0
B9: =B8+1 -> 46248 | C9: 0 | D9: 0 | I9: =H9-C9 -> 0
B10: =B9+1 -> 46249 | C10: 0 | D10: 0 | I10: =H10-C10 -> 0
B11: Total Week | C11: =SUM(C4:C10) -> -700 | D11: =SUM(D4:D10) -> 700 | H11: =SUM(H4:H10) -> 0 | I11: =SUM(I4:I10) -> 700
B12: =B10+1 -> 46250 | C12: 0 | D12: 0 | I12: =H12-C12 -> 0
B13: =B12+1 -> 46251 | C13: 0 | D13: 0 | I13: =H13-C13 -> 0
B14: =B13+1 -> 46252 | C14: 0 | D14: 0 | I14: =H14-C14 -> 0
B15: =B14+1 -> 46253 | C15: 0 | D15: 0 | I15: =H15-C15 -> 0
B16: =B15+1 -> 46254 | C16: 0 | D16: 0 | I16: =H16-C16 -> 0
B17: =B16+1 -> 46255 | C17: 0 | D17: 0 | I17: =H17-C17 -> 0
B18: =B17+1 -> 46256 | C18: 0 | D18: 0 | I18: =H18-C18 -> 0
B19: Total Week | C19: =SUM(C12:C18) -> 0 | D19: =SUM(D12:D18) -> 0 | H19: =SUM(H12:H18) -> 0 | I19: =SUM(I12:I18) -> 0
B20: =B18+1 -> 46257 | C20: -700 | D20: 0 | I20: =H20-C20 -> 700
B21: =B20+1 -> 46258 | C21: 0 | D21: 0 | I21: =H21-C21 -> 0
B22: =B21+1 -> 46259 | C22: 0 | D22: 700 | I22: =H22-C22 -> 0
B23: =B22+1 -> 46260 | C23: 0 | D23: 0 | I23: =H23-C23 -> 0
B24: =B23+1 -> 46261 | C24: 0 | D24: 0 | I24: =H24-C24 -> 0
B25: =B24+1 -> 46262 | C25: 0 | D25: 0 | I25: =H25-C25 -> 0
B26: =B25+1 -> 46263 | C26: 0 | D26: 0 | I26: =H26-C26 -> 0
B27: Total Week | C27: =SUM(C20:C26) -> -700 | D27: =SUM(D20:D26) -> 700 | E27: LV | H27: =SUM(H20:H26) -> 0 | I27: =SUM(I20:I26) -> 700
B28: =B26+1 -> 46264 | C28: 0 | D28: 0 | I28: =H28-C28 -> 0
B29: =B28+1 -> 46265 | C29: 0 | D29: 0 | I29: =H29-C29 -> 0
B30: =B29+1 -> 46266 | C30: 0 | D30: 700 | E30: LV | I30: =H30-C30 -> 0
B31: =B30+1 -> 46267 | C31: 0 | D31: 0 | I31: =H31-C31 -> 0
B32: =B31+1 -> 46268 | C32: 0 | D32: 0 | I32: =H32-C32 -> 0
B33: =B32+1 -> 46269 | C33: 0 | D33: 0 | I33: =H33-C33 -> 0
B34: =B33+1 -> 46270 | C34: 0 | D34: 0 | I34: =H34-C34 -> 0
B35: Total Week | C35: =SUM(C28:C34) -> 0 | D35: =SUM(D28:D34) -> 700 | H35: =SUM(H28:H34) -> 0 | I35: =SUM(I28:I34) -> 0
B36: Total Period | C36: =SUM(C35+C27+C19+C11) -> -1400 | D36: =SUM(D35+D27+D19+D11) -> 2100 | H36: =SUM(H35+H27+H19+H11) -> 0 | I36: =SUM(I35+I27+I19+I11) -> 1400
B37: Period Activity | C37: =D36+C36 -> 700 | H37: =I36+H36 -> 1400 | I37: =J36+I36 -> 1400
C38: =B34+1 -> 46271 | D38: After Period Close
B39: Ending Period Count of Amount on hand | C39: 1400 | E39: LV
B41: Number of Cash Drawers | C41: 2
B43: Amount of Each Drawer | C43: 200
B45: Amount of Petty Cash | C45: 300
B47: Period10
B48: Sun 9-6 | C48: 0 | D48: 0 | E48: CG | H48: 27 | I48: =H48-C48 -> 27
B49: Mon 9-7 | C49: 0 | D49: 0 | E49: CG | H49: -75 | I49: =H49-C49 -> -75
B50: Tue 9-8 | C50: 0 | D50: 700 | E50: LV | F50: Change ord recvd | H50: 12 | I50: =H50-C50 -> 12
B51: Wed 9-9 | C51: 0 | D51: 0 | E51: LV | H51: -673 | I51: =H51-C51 -> -673
B52: Thu 9-10 | C52: 0 | D52: 0 | E52: LV | H52: -36 | I52: =H52-C52 -> -36
B53: Fri 9-11 | C53: 700 | E53: LV | F53: Pay change order | H53: 1358 | I53: =H53-C53 -> 658
B54: Sat 9-12 | C54: 0 | D54: 0 | E54: CG | H54: -120 | I54: =H54-C54 -> -120
B55: Total Week | C55: =SUM(C48:C54) -> 700 | D55: =SUM(D48:D54) -> 700 | H55: =SUM(H48:H54) -> 493 | I55: =SUM(I48:I54) -> -207
B56: Sun 9-13 | C56: 0 | D56: 0 | E56: CG | H56: -9 | I56: =H56-C56 -> -9
B57: Mon 9-14 | C57: 0 | D57: 0 | E57: LV | H57: 8 | I57: =H57-C57 -> 8
B58: Tue 9-15 | C58: 0 | D58: 700 | E58: LV | F58: Change ord recvd | H58: 25 | I58: =H58-C58 -> 25
B59: Wed 9-16 | C59: 0 | D59: 0 | E59: LV | H59: 21 | I59: =H59-C59 -> 21
B60: Thu 9-17 | C60: 0 | D60: 0 | E60: CG | H60: -85.9 | I60: =H60-C60 -> -85.9
B61: Fri 9-18 | C61: 0 | D61: 0 | E61: CG | H61: -0.24 | I61: =H61-C61 -> -0.24
B62: Sat 9-19 | C62: 0 | D62: 0 | E62: CG | H62: -78.17 | I62: =H62-C62 -> -78.17
B63: Total Week | C63: =SUM(C56:C62) -> 0 | D63: =SUM(D56:D62) -> 700 | H63: =SUM(H56:H62) -> -119.31 | I63: =SUM(I56:I62) -> -119.31
B64: Sun 9-20 | C64: 0 | D64: 0 | E64: LV | F64: Pay tips | H64: 1355 | I64: =H64-C64 -> 1355
B65: Mon 9-21 | C65: 700 | D65: 0 | E65: LV | F65: Pay change order | H65: 40 | I65: =H65-C65 -> -660
B66: Tue 9-22 | C66: 0 | D66: 700 | E66: LV | F66: Change ord recvd | H66: 128 | I66: =H66-C66 -> 128
B67: Wed 9-23 | C67: 0 | D67: 0 | E67: CG | H67: 65 | I67: =H67-C67 -> 65
B68: Thu 9-24 | C68: 0 | D68: 0 | E68: CG | H68: 66 | I68: =H68-C68 -> 66
B69: Fri 9-25 | C69: 0 | D69: 0 | E69: CG | H69: 215 | I69: =H69-C69 -> 215
B70: Sat 9-26 | C70: 0 | D70: 0 | E70: CG | H70: 1384 | I70: =H70-C70 -> 1384
B71: Total Week | C71: =SUM(C64:C70) -> 700 | D71: =SUM(D64:D70) -> 700 | H71: =SUM(H64:H70) -> 3253 | I71: =SUM(I64:I70) -> 2553
B72: Sun 9-27 | C72: 700 | D72: 0 | E72: LV | F72: Pay change order / was short not over -SH | H72: -112 | I72: =H72-C72 -> -812
B73: Mon 9-28 | D73: 700 | E73: LV/CG | F73: Change ord recvd by CG | H73: 28 | I73: =H73-C73 -> 28
B74: Tue 9-29 | C74: 0 | D74: 0 | E74: LV | F74: Short $759 -SH | H74: -759 | I74: =H74-C74 -> -759
B75: Wed 9-30 | C75: 0 | D75: 0 | E75: LV | F75: Over/Short was (0) | H75: 0 | I75: =H75-C75 -> 0
B76: Thu 10-1 | C76: 700 | D76: 0 | E76: CG | F76: Over $561 -CG | H76: 561 | I76: =H76-C76 -> -139
B77: Fri 10-2 | C77: 0 | D77: 0 | E77: CG | F77: Short $524 not over -SH | H77: -524 | I77: =H77-C77 -> -524
B78: Sat 10-3 | D78: 0 | E78: CG | F78: Short $40 | H78: -40 | I78: =H78-C78 -> -40
B79: Total Week | C79: =SUM(C72:C78) -> 1400 | D79: =SUM(D72:D78) -> 700 | H79: =SUM(H72:H78) -> -846 | I79: =SUM(I72:I78) -> -2246
B80: Total Period | C80: =SUM(C79+C71+C63+C55) -> 2800 | D80: =SUM(D79+D71+D63+D55) -> 2800 | H80: =SUM(H79+H71+H63+H55) -> 2780.69 | I80: =SUM(I79+I71+I63+I55) -> -19.31
B81: Period Activity | C81: =D80+C80 -> 5600 | H81: =I80+H80 -> 2761.38 | I81: =J80+I80 -> -19.31
C82: Sun 10-4 | D82: After Period Close
B83: Ending Period Count of Amopunt on hand | C83: 700 | E83: LV/CG
B85: Number of Cash Drawers | C85: 200
B87: Amount of Each Drawer | C87: 200
B89: Amount of Petty Cash | C89: 300
B91: Period11
B92: Sun 10-4 | C92: 0 | D92: 0 | E92: LV | F92: Over $49 | H92: 49 | I92: =H92-C92 -> 49
B93: Mon 10-5 | C93: 0 | D93: 0 | E93: LV | F93: Short -$60 but is only 11 over for the week | H93: -60 | I93: =H93-C93 -> -60
B94: Tue 10-6 | C94: 0 | D94: 700 | E94: LV | F94: Change ord recvd by LV | H94: 578 | I94: =H94-C94 -> 578
B95: Wed 10-7 | C95: 700 | D95: 0 | E95: LV | F95: Change ord deposit $700 by LV | H95: 745 | I95: =H95-C95 -> 45
B96: Thu 10-8 | C96: 300 | D96: 0 | E96: SH | F96: Change Order Deposit $300 by SH | H96: -245 | I96: =H96-C96 -> -545
A97: ( | B97: Fri 10-9 | D97: 0 | E97: SH | F97: Short -$50 - tip out | H97: -50 | I97: =H97-C97 -> -50
B98: Sat 10-10 | C98: 0 | D98: 0 | E98: SH | F98: Short $44-tip out | H98: -44 | I98: =H98-C98 -> -44
B99: Total Week | C99: =SUM(C92:C98) -> 1000 | D99: =SUM(D92:D98) -> 700 | H99: =SUM(H92:H98) -> 973 | I99: =SUM(I92:I98) -> -27
B100: Sun 10-11 | C100: 0 | D100: 0 | E100: LV | F100: In the Report of the 365 is (0) | H100: 0 | I100: 0
B101: Mon 10-12 | C101: 0 | D101: 0 | H101: 0 | I101: =H101-C101 -> 0
B102: Tue 10-13 | C102: 0 | D102: 0 | H102: 0 | I102: =H102-C102 -> 0
B103: Wed 10-14 | C103: 0 | D103: 0 | H103: 0 | I103: =H103-C103 -> 0
B104: Thu 10-15 | C104: 0 | D104: 0 | H104: 0 | I104: =H104-C104 -> 0
B105: Fri 10-16 | C105: 0 | D105: 0 | H105: 0 | I105: =H105-C105 -> 0
B106: Sat 10-17 | C106: 0 | D106: 0 | H106: 0 | I106: =H106-C106 -> 0
B107: Total Week | C107: =SUM(C100:C106) -> 0 | D107: =SUM(D100:D106) -> 0 | H107: =SUM(H100:H106) -> 0 | I107: =SUM(I100:I106) -> 0
B108: Sun 10-18 | C108: 0 | D108: 0 | H108: 0 | I108: =H108-C108 -> 0
...

Sheet OR
C1: Orange
C2: Per Restaurant
C3: Chage Order Deposits | D3: Change Order Received | E3: Initials | F3: Comments | H3: Cash over/ (Short) per R365 Flash report | I3: True Over/ (Short)
B4: =Control!$B$3 -> 46243 | C4: 0 | D4: 0 | H4: -7.38 | I4: =H4-C4 -> -7.38
B5: =B4+1 -> 46244 | C5: 0 | D5: 0 | H5: -13.6 | I5: =H5-C5 -> -13.6
B6: =B5+1 -> 46245 | C6: 0 | D6: 0 | H6: 11.7 | I6: =H6-C6 -> 11.7
B7: =B6+1 -> 46246 | C7: 0 | D7: 0 | H7: 6.26 | I7: =H7-C7 -> 6.26
B8: =B7+1 -> 46247 | C8: 0 | D8: 0 | H8: -2.34 | I8: =H8-C8 -> -2.34
B9: =B8+1 -> 46248 | C9: 0 | D9: 0 | H9: 3.97 | I9: =H9-C9 -> 3.97
B10: =B9+1 -> 46249 | C10: 0 | D10: 0 | H10: 12.03 | I10: =H10-C10 -> 12.03
B11: Total Week | C11: =SUM(C4:C10) -> 0 | D11: =SUM(D4:D10) -> 0 | H11: -51.56 | I11: =SUM(I4:I10) -> 10.64
B12: =B10+1 -> 46250 | C12: 0 | D12: 0 | H12: -6.43 | I12: =H12-C12 -> -6.43
B13: =B12+1 -> 46251 | C13: 0 | D13: 0 | H13: 34.12 | I13: =H13-C13 -> 34.12
B14: =B13+1 -> 46252 | C14: 0 | D14: 0 | H14: -51.56 | I14: =H14-C14 -> -51.56
B15: =B14+1 -> 46253 | C15: 0 | D15: 0 | H15: -8.88 | I15: =H15-C15 -> -8.88
B16: =B15+1 -> 46254 | C16: 0 | D16: 0 | H16: 1.84 | I16: =H16-C16 -> 1.84
B17: =B16+1 -> 46255 | C17: 0 | D17: 0 | H17: 129.78 | I17: =H17-C17 -> 129.78
B18: =B17+1 -> 46256 | C18: 0 | D18: 0 | H18: -250.03 | I18: =H18-C18 -> -250.03
B19: Total Week | C19: =SUM(C12:C18) -> 0 | D19: =SUM(D12:D18) -> 0 | H19: -9.26 | I19: =SUM(I12:I18) -> -151.16
B20: =B18+1 -> 46257 | C20: 0 | D20: 0 | H20: 23 | I20: =H20-C20 -> 23
B21: =B20+1 -> 46258 | C21: 0 | D21: 0 | H21: -11 | I21: =H21-C21 -> -11
B22: =B21+1 -> 46259 | C22: 0 | D22: 0 | H22: -9.38 | I22: =H22-C22 -> -9.38
B23: =B22+1 -> 46260 | C23: 0 | D23: 0 | H23: 127 | I23: =H23-C23 -> 127
B24: =B23+1 -> 46261 | C24: 0 | D24: 0 | H24: -9 | I24: =H24-C24 -> -9
B25: =B24+1 -> 46262 | C25: 0 | D25: 0 | H25: 13 | I25: =H25-C25 -> 13
B26: =B25+1 -> 46263 | C26: 0 | D26: 0 | H26: 9 | I26: =H26-C26 -> 9
B27: Total Week | C27: =SUM(C20:C26) -> 0 | D27: =SUM(D20:D26) -> 0 | H27: =SUM(H20:H26) -> 142.62 | I27: =SUM(I20:I26) -> 142.62
B28: =B26+1 -> 46264 | C28: 0 | D28: 0 | H28: -13.17 | I28: =H28-C28 -> -13.17
B29: =B28+1 -> 46265 | C29: 0 | D29: 0 | H29: -19.54 | I29: =H29-C29 -> -19.54
B30: =B29+1 -> 46266 | C30: 0 | D30: 0 | H30: -23.01 | I30: =H30-C30 -> -23.01
B31: =B30+1 -> 46267 | C31: 0 | D31: 0 | H31: 5.39 | I31: =H31-C31 -> 5.39
B32: =B31+1 -> 46268 | C32: 0 | D32: 0 | H32: 50.3 | I32: =H32-C32 -> 50.3
B33: =B32+1 -> 46269 | C33: 0 | D33: 0 | H33: 9 | I33: =H33-C33 -> 9
B34: =B33+1 -> 46270 | C34: 0 | D34: 0 | H34: 21 | I34: =H34-C34 -> 21
B35: Total Week | C35: =SUM(C28:C34) -> 0 | D35: =SUM(D28:D34) -> 0 | H35: =SUM(H28:H34) -> 29.97 | I35: =SUM(I28:I34) -> 29.97
B36: Total Period | C36: =SUM(C35+C27+C19+C11) -> 0 | D36: =SUM(D35+D27+D19+D11) -> 0 | H36: =SUM(H35+H27+H19+H11) -> 111.77 | I36: =SUM(I35+I27+I19+I11) -> 32.07
B37: Period Activity | C37: =D36+C36 -> 0 | H37: =I36+H36 -> 143.84 | I37: =J36+I36 -> 32.07
C38: =B34+1 -> 46271 | D38: After Period Close
B39: Ending Period Count of Amount on hand | C39: 900 | E39: BL
B41: Number of Cash Drawers | C41: 1
B43: Amount of Each Drawer | C43: 200
B45: Amount of Petty Cash | C45: 300
B47: Period10
B48: Sun 9-6 | C48: 0 | D48: 0 | E48: BL | H48: -20.05 | I48: =H48-C48 -> -20.05
B49: Mon 9-7 | C49: 0 | D49: 0 | E49: BL | H49: 36.8 | I49: =H49-C49 -> 36.8
B50: Tue 9-8 | C50: 0 | D50: 0 | E50: BL | H50: -25.65 | I50: =H50-C50 -> -25.65
B51: Wed 9-9 | D51: 0 | E51: BL | H51: -23.39 | I51: =H51-C51 -> -23.39
B52: Thu 9-10 | C52: 0 | D52: 0 | E52: BL | H52: -2.7 | I52: =H52-C52 -> -2.7
B53: Fri 9-11 | C53: 0 | D53: 0 | E53: BL | H53: -8 | I53: =H53-C53 -> -8
B54: Sat 9-12 | C54: 0 | D54: 0 | E54: BL | H54: 16.62 | I54: =H54-C54 -> 16.62
B55: Total Week | C55: =SUM(C48:C54) -> 0 | D55: =SUM(D48:D54) -> 0 | E55: BL | H55: =SUM(H48:H54) -> -26.37 | I55: =SUM(I48:I54) -> -26.37
B56: Sun 9-13 | C56: 0 | D56: 0 | E56: BR | F56: short 0 | H56: 0.21 | I56: =H56-C56 -> 0.21
B57: Mon 9-14 | C57: 0 | D57: 0 | E57: BR | H57: -88 | I57: 0.21
B58: Tue 9-15 | C58: 0 | D58: 0 | E58: BR | H58: 26 | I58: =H58-C58 -> 26
B59: Wed 9-16 | C59: 0 | D59: 0 | E59: AR | H59: 107 | I59: =H59-C59 -> 107
B60: Thu 9-17 | C60: 0 | D60: 695 | E60: AR | H60: -36 | I60: =H60-C60 -> -36
B61: Fri 9-18 | C61: 0 | D61: 0 | E61: AR | H61: 6.36 | I61: =H61-C61 -> 6.36
B62: Sat 9-19 | C62: 0 | D62: 0 | E62: AR | H62: 22.4 | I62: =H62-C62 -> 22.4
B63: Total Week | C63: =SUM(C56:C62) -> 0 | D63: =SUM(D56:D62) -> 695 | H63: =SUM(H56:H62) -> 37.97 | I63: =SUM(I56:I62) -> 126.18
B64: Sun 9-20 | C64: 695 | D64: 0 | E64: BR | F64: Coin order was paid today | H64: -1278 | I64: =H64-C64 -> -1973
B65: Mon 9-21 | C65: 0 | D65: 0 | E65: BR | H65: -8.01 | I65: =H65-C65 -> -8.01
B66: Tue 9-22 | C66: 0 | D66: 0 | E66: BR | H66: -22.24 | I66: =H66-C66 -> -22.24
B67: Wed 9-23 | C67: 0 | D67: 0 | E67: AR | H67: 72.04 | I67: =H67-C67 -> 72.04
B68: Thu 9-24 | C68: 0 | D68: 0 | H68: -29.94 | I68: =H68-C68 -> -29.94
B69: Fri 9-25 | C69: 0 | D69: 0 | E69: AR | H69: 28.54 | I69: =H69-C69 -> 28.54
B70: Sat 9-26 | C70: 0 | D70: 0 | E70: TB | H70: 15 | I70: =H70-C70 -> 15
B71: Total Week | C71: =SUM(C64:C70) -> 695 | D71: =SUM(D64:D70) -> 0 | H71: =SUM(H64:H70) -> -1222.61 | I71: =SUM(I64:I70) -> -1917.61
B72: Sun 9-27 | D72: 0 | E72: TB | H72: -1 | I72: =H72-C72 -> -1
B73: Mon 9-28 | D73: 0 | E73: TB | H73: 31 | I73: =H73-C73 -> 31
B74: Tue 9-29 | C74: 0 | D74: 0 | E74: TB | H74: -66 | I74: =H74-C74 -> -66
B75: Wed 9-30 | C75: 0 | D75: 0 | E75: TB | H75: 11 | I75: =H75-C75 -> 11
B76: Thu 10-1 | C76: 0 | D76: 0 | E76: TB | H76: 14 | I76: =H76-C76 -> 14
B77: Fri 10-2 | C77: 0 | D77: 0 | E77: TB | H77: 15 | I77: =H77-C77 -> 15
B78: Sat 10-3 | D78: 0 | H78: 10.88 | I78: =H78-C78 -> 10.88
B79: Total Week | C79: =SUM(C72:C78) -> 0 | D79: =SUM(D72:D78) -> 0 | H79: =SUM(H72:H78) -> 14.88 | I79: =SUM(I72:I78) -> 14.88
B80: Total Period | C80: =SUM(C79+C71+C63+C55) -> 695 | D80: =SUM(D79+D71+D63+D55) -> 695 | H80: =SUM(H79+H71+H63+H55) -> -1196.13 | I80: =SUM(I79+I71+I63+I55) -> -1802.92
B81: Period Activity | C81: =D80+C80 -> 1390 | H81: ...................... | I81: =J80+I80 -> -1802.92
C82: Sun 10-4 | D82: After Period Close | H82: .
B83: Ending Period Count of Amopunt on hand | C83: 1400 | E83: TB | F83: petty shows should be 1300, only at 1200.
E84: =
B85: Number of Cash Drawers | C85: 1 | E85: 1 | F85: `
B87: Amount of Each Drawer | C87: 200
B89: Amount of Petty Cash | C89: 1200
B91: Period11
B92: Sun 10-4 | C92: 0 | D92: 0 | E92: TB | H92: 53.21 | I92: =H92-C92 -> 53.21
B93: Mon 10-5 | C93: 0 | D93: 0 | E93: AR | F93: Coin order was placed this day by AR not over or short | H93: 0.26 | I93: =H93-C93 -> 0.26
B94: Tue 10-6 | C94: 0 | D94: 0 | E94: TB | H94: -10 | I94: =H94-C94 -> -10
B95: Wed 10-7 | D95: 875 | E95: TB | F95: change order received $875 | H95: -21 | I95: =H95-C95 -> -21
B96: Thu 10-8 | C96: 0 | D96: 0 | E96: TB | F96: $0 over/short | H96: 0 | I96: =H96-C96 -> 0
B97: Fri 10-9 | C97: 0 | D97: 0 | E97: TB | G97: -*C8743 | H97: 15 | I97: =H97-C97 -> 15
B98: Sat 10-10 | C98: 0 | D98: 0 | E98: TB | H98: -37 | I98: =H98-C98 -> -37
B99: Total Week | C99: =SUM(C92:C98) -> 0 | D99: =SUM(D92:D98) -> 875 | H99: =SUM(H92:H98) -> 0.47 | I99: =SUM(I92:I98) -> 0.47
B100: Sun 10-11 | C100: 0 | D100: 0 | H100: 0 | I100: =H100-C100 -> 0
B101: Mon 10-12 | C101: 0 | D101: 0 | H101: 0 | I101: =H101-C101 -> 0
B102: Tue 10-13 | C102: 0 | D102: 0 | H102: 0 | I102: =H102-C102 -> 0
B103: Wed 10-14 | C103: 0 | D103: 0 | H103: 0 | I103: =H103-C103 -> 0
B104: Thu 10-15 | C104: 0 | D104: 0 | H104: 0 | I104: =H104-C104 -> 0
B105: Fri 10-16 | C105: 0 | D105: 0 | H105: 0 | I105: =H105-C105 -> 0
B106: Sat 10-17 | C106: 0 | D106: 0 | H106: 0 | I106: =H106-C106 -> 0
B107: Total Week | C107: =SUM(C100:C106) -> 0 | D107: =SUM(D100:D106) -> 0 | H107: =SUM(H100:H106) -> 0 | I107: =SUM(I100:I106) -> 0
...

Sheet PR
C1: Pico Rivera
C2: Per Restaurant
C3: Chage Order Deposits | D3: Change Order Received | E3: Initials | F3: Comments | H3: Cash over/ (Short) per R365 Flash report | I3: True Over/ (Short)
B4: =Control!$B$3 -> 46243 | C4: 0 | D4: 0 | I4: =H4-C4 -> 0
B5: =B4+1 -> 46244 | C5: 0 | D5: 0 | I5: =H5-C5 -> 0
B6: =B5+1 -> 46245 | C6: 500 | D6: 0 | E6: HF | I6: =H6-C6 -> -500
B7: =B6+1 -> 46246 | C7: 0 | D7: 2000 | E7: VM | I7: =H7-C7 -> 0
B8: =B7+1 -> 46247 | C8: 0 | D8: 0 | I8: =H8-C8 -> 0
B9: =B8+1 -> 46248 | C9: 500 | D9: 0 | E9: HF | I9: =H9-C9 -> -500
B10: =B9+1 -> 46249 | C10: 500 | D10: 0 | E10: HF | I10: =H10-C10 -> -500
B11: Total Week | C11: =SUM(C4:C10) -> 1500 | D11: =SUM(D4:D10) -> 2000 | H11: =SUM(H4:H10) -> 0 | I11: =SUM(I4:I10) -> -1500
B12: =B10+1 -> 46250 | C12: 0 | D12: 0 | I12: =H12-C12 -> 0
B13: =B12+1 -> 46251 | C13: 500 | D13: 0 | E13: HF | I13: =H13-C13 -> -500
B14: =B13+1 -> 46252 | C14: 0 | D14: 0 | I14: =H14-C14 -> 0
B15: =B14+1 -> 46253 | C15: 0 | D15: 0 | I15: =H15-C15 -> 0
B16: =B15+1 -> 46254 | C16: 500 | D16: 0 | E16: VM | I16: =H16-C16 -> -500
B17: =B16+1 -> 46255 | C17: 0 | D17: 0 | I17: =H17-C17 -> 0
B18: =B17+1 -> 46256 | C18: 0 | D18: 0 | I18: =H18-C18 -> 0
B19: Total Week | C19: =SUM(C12:C18) -> 1000 | D19: =SUM(D12:D18) -> 0 | H19: =SUM(H12:H18) -> 0 | I19: =SUM(I12:I18) -> -1000
B20: =B18+1 -> 46257 | C20: 0 | D20: 0 | I20: =H20-C20 -> 0
B21: =B20+1 -> 46258 | C21: 500 | D21: 0 | E21: HF | I21: =H21-C21 -> -500
B22: =B21+1 -> 46259 | C22: 0 | D22: 4000 | E22: VM | F22: didnt recieve bag the week before got double 2 bags this week | I22: =H22-C22 -> 0
B23: =B22+1 -> 46260 | C23: 0 | D23: 0 | I23: =H23-C23 -> 0
B24: =B23+1 -> 46261 | C24: 1500 | D24: 0 | E24: VM | I24: =H24-C24 -> -1500
B25: =B24+1 -> 46262 | C25: 0 | D25: 0 | I25: =H25-C25 -> 0
B26: =B25+1 -> 46263 | C26: 0 | D26: 0 | I26: =H26-C26 -> 0
B27: Total Week | C27: =SUM(C20:C26) -> 2000 | D27: =SUM(D20:D26) -> 4000 | H27: =SUM(H20:H26) -> 0 | I27: =SUM(I20:I26) -> -2000
B28: =B26+1 -> 46264 | C28: 0 | D28: 0 | I28: =H28-C28 -> 0
B29: =B28+1 -> 46265 | C29: 1000 | D29: 0 | E29: HF | I29: =H29-C29 -> -1000
B30: =B29+1 -> 46266 | C30: 0 | D30: 0 | I30: =H30-C30 -> 0
B31: =B30+1 -> 46267 | C31: 0 | D31: 0 | I31: =H31-C31 -> 0
B32: =B31+1 -> 46268 | C32: 500 | D32: 0 | E32: VM | I32: =H32-C32 -> -500
B33: =B32+1 -> 46269 | C33: 500 | D33: 0 | I33: =H33-C33 -> -500
B34: =B33+1 -> 46270 | C34: 500 | D34: 0 | H34: 509 | I34: =H34-C34 -> 9
B35: Total Week | C35: =SUM(C28:C34) -> 2500 | D35: =SUM(D28:D34) -> 0 | H35: =SUM(H28:H34) -> 509 | I35: =SUM(I28:I34) -> -1991
B36: Total Period | C36: =SUM(C35+C27+C19+C11) -> 7000 | D36: =SUM(D35+D27+D19+D11) -> 6000 | H36: =SUM(H35+H27+H19+H11) -> 509 | I36: =SUM(I35+I27+I19+I11) -> -6491
B37: Period Activity | C37: =D36+C36 -> 13000 | H37: =I36+H36 -> -5982 | I37: =J36+I36 -> -6491
C38: =B34+1 -> 46271 | D38: After Period Close
B39: Ending Period Count of Amount on hand | C39: 500 | E39: VM PP
B41: Number of Cash Drawers | C41: 2
B43: Amount of Each Drawer | C43: 200
B45: Amount of Petty Cash | C45: 300
B47: Period10
B48: Sun 9-6 | C48: 0 | D48: 0 | E48: HF | H48: 68 | I48: =H48-C48 -> 68
B49: Mon 9-7 | C49: 0 | D49: 0 | E49: HF | H49: -10 | I49: =H49-C49 -> -10
B50: Tue 9-8 | C50: 0 | D50: 0 | E50: HF | H50: 4 | I50: =H50-C50 -> 4
B51: Wed 9-9 | C51: 500 | D51: 2000 | E51: VM | F51: change order drop / change order recived | H51: 482 | I51: =H51-C51 -> -18
B52: Thu 9-10 | C52: 0 | D52: 0 | E52: HF | H52: 21 | I52: =H52-C52 -> 21
B53: Fri 9-11 | C53: 0 | D53: 0 | E53: HF | H53: -55 | I53: =H53-C53 -> -55
B54: Sat 9-12 | C54: 1000 | D54: 0 | E54: HF | H54: 1015 | I54: =H54-C54 -> 15
B55: Total Week | C55: =SUM(C48:C54) -> 1500 | D55: =SUM(D48:D54) -> 2000 | E55: HF | H55: =SUM(H48:H54) -> 1525 | I55: =SUM(I48:I54) -> 25
B56: Sun 9-13 | C56: 0 | D56: 0 | E56: HF | H56: 9 | I56: =H56-C56 -> 9
B57: Mon 9-14 | C57: 0 | D57: 0 | E57: HF | H57: 6 | I57: =H57-C57 -> 6
B58: Tue 9-15 | C58: 500 | D58: 2000 | E58: HF | F58: change order drop / change order recived | H58: 555.44 | I58: =H58-C58 -> 55.44
B59: Wed 9-16 | C59: 0 | D59: 0 | E59: pp | H59: -34.03 | I59: =H59-C59 -> -34.03
B60: Thu 9-17 | C60: 500 | D60: 0 | E60: HF | F60: change order drop | H60: 585 | I60: =H60-C60 -> 85
B61: Fri 9-18 | C61: 0 | D61: 0 | E61: HF | H61: 27 | I61: =H61-C61 -> 27
B62: Sat 9-19 | C62: 1000 | D62: 0 | E62: HF | F62: change order drop | H62: 857 | I62: =H62-C62 -> -143
B63: Total Week | C63: =SUM(C56:C62) -> 2000 | D63: =SUM(D56:D62) -> 2000 | H63: =SUM(H56:H62) -> 2005.41 | I63: =SUM(I56:I62) -> 5.41
B64: Sun 9-20 | C64: 0 | D64: 0 | E64: VM | F64: Order placed | H64: -70 | I64: =H64-C64 -> -70
B65: Mon 9-21 | C65: 500 | D65: 0 | E65: HF | F65: change order drop | H65: 594 | I65: =H65-C65 -> 94
B66: Tue 9-22 | C66: 0 | D66: 2000 | E66: HF | F66: received bank order | H66: 4.95 | I66: =H66-C66 -> 4.95
B67: Wed 9-23 | C67: 0 | D67: 0 | E67: VM | H67: 65 | I67: =H67-C67 -> 65
B68: Thu 9-24 | C68: 500 | D68: 0 | E68: VM | F68: change order drop | H68: 465 | I68: =H68-C68 -> -35
B69: Fri 9-25 | C69: 500 | D69: 0 | E69: VM | F69: change order drop | H69: 519 | I69: =H69-C69 -> 19
B70: Sat 9-26 | C70: 500 | D70: 0 | E70: VM | F70: change order drop | H70: 548 | I70: =H70-C70 -> 48
B71: Total Week | C71: =SUM(C64:C70) -> 2000 | D71: =SUM(D64:D70) -> 2000 | H71: =SUM(H64:H70) -> 2125.95 | I71: =SUM(I64:I70) -> 125.95
B72: Sun 9-27 | C72: 500 | D72: 0 | E72: HF | F72: Order placed / change order drop | H72: 521 | I72: =H72-C72 -> 21
B73: Mon 9-28 | C73: 500 | D73: 0 | E73: HF | F73: Change order drop | H73: 497 | I73: =H73-C73 -> -3
B74: Tue 9-29 | C74: 0 | D74: 2000 | E74: HF | F74: received bank order | H74: 25.97 | I74: =H74-C74 -> 25.97
B75: Wed 9-30 | C75: 500 | D75: 0 | E75: VM | F75: Change order drop | H75: 507 | I75: =H75-C75 -> 7
B76: Thu 10-1 | C76: 0 | D76: 0 | E76: VM | H76: 43.79 | I76: =H76-C76 -> 43.79
B77: Fri 10-2 | C77: 500 | D77: 0 | E77: VM | F77: Change order drop | H77: 469 | I77: =H77-C77 -> -31
B78: Sat 10-3 | D78: 0 | E78: VM | H78: 5 | I78: =H78-C78 -> 5
B79: Total Week | C79: =SUM(C72:C78) -> 2000 | D79: =SUM(D72:D78) -> 2000 | H79: =SUM(H72:H78) -> 2068.76 | I79: =SUM(I72:I78) -> 68.76
B80: Total Period | C80: =SUM(C79+C71+C63+C55) -> 7500 | D80: =SUM(D79+D71+D63+D55) -> 8000 | H80: =SUM(H79+H71+H63+H55) -> 7725.12 | I80: =SUM(I79+I71+I63+I55) -> 225.12
B81: Period Activity | C81: =D80+C80 -> 15500 | H81: =I80+H80 -> 7950.24 | I81: =J80+I80 -> 225.12
C82: Sun 10-4 | D82: After Period Close
B83: Ending Period Count of Amopunt on hand | C83: 1000 | E83: VM PP | F83: All counts verified
B85: Number of Cash Drawers | C85: 2
B87: Amount of Each Drawer | C87: 200
B89: Amount of Petty Cash | C89: 300
B91: Period11
B92: Sun 10-4 | C92: 500 | D92: 0 | E92: vm | F92: Order placed /change order drop | H92: 501 | I92: =H92-C92 -> 1
B93: Mon 10-5 | C93: 0 | D93: 0 | E93: PP | H93: 45 | I93: =H93-C93 -> 45
B94: Tue 10-6 | C94: 500 | D94: 2000 | E94: HF | F94: received bank order /change order drop | H94: 508 | I94: =H94-C94 -> 8
B95: Wed 10-7 | C95: 0 | D95: 0 | E95: VM | H95: 18 | I95: =H95-C95 -> 18
B96: Thu 10-8 | C96: 500 | D96: 0 | E96: VM | F96: Change order drop | H96: 496 | I96: =H96-C96 -> -4
B97: Fri 10-9 | C97: 0 | D97: 0 | E97: VM | H97: 2 | I97: =H97-C97 -> 2
B98: Sat 10-10 | C98: 500 | D98: 0 | E98: VM | H98: 468 | I98: =H98-C98 -> -32
B99: Total Week | C99: =SUM(C92:C98) -> 2000 | D99: =SUM(D92:D98) -> 2000 | H99: =SUM(H92:H98) -> 2038 | I99: =SUM(I92:I98) -> 38
B100: Sun 10-11 | C100: 0 | D100: 0 | E100: VM | F100: Order placed | H100: 61 | I100: =H100-C100 -> 61
B101: Mon 10-12 | C101: 0 | D101: 0 | H101: 0 | I101: =H101-C101 -> 0
B102: Tue 10-13 | C102: 0 | D102: 0 | H102: 0 | I102: =H102-C102 -> 0
B103: Wed 10-14 | C103: 0 | D103: 0 | H103: 0 | I103: =H103-C103 -> 0
B104: Thu 10-15 | C104: 0 | D104: 0 | H104: 0 | I104: =H104-C104 -> 0
B105: Fri 10-16 | C105: 0 | D105: 0 | H105: 0 | I105: =H105-C105 -> 0
B106: Sat 10-17 | C106: 0 | D106: 0 | H106: 0 | I106: =H106-C106 -> 0
B107: Total Week | C107: =SUM(C100:C106) -> 0 | D107: =SUM(D100:D106) -> 0 | H107: =SUM(H100:H106) -> 61 | I107: =SUM(I100:I106) -> 61
B108: Sun 10-18 | C108: 0 | D108: 0 | H108: 0 | I108: =H108-C108 -> 0
...

Sheet RL
C1: Rialto
C2: Per Restaurant
C3: Chage Order Deposits | D3: Change Order Received | E3: Initials | F3: Comments | H3: Cash over/ (Short) per R365 Flash report | I3: True Over/ (Short)
B4: =Control!$B$3 -> 46243 | C4: 0 | D4: 0 | I4: =H4-C4 -> 0
B5: =B4+1 -> 46244 | C5: 0 | D5: 0 | I5: =H5-C5 -> 0
B6: =B5+1 -> 46245 | C6: 0 | D6: 0 | I6: =H6-C6 -> 0
B7: =B6+1 -> 46246 | C7: 0 | D7: 0 | I7: =H7-C7 -> 0
B8: =B7+1 -> 46247 | C8: 0 | D8: 805 | E8: BR | I8: =H8-C8 -> 0
B9: =B8+1 -> 46248 | C9: -805 | D9: 0 | E9: BR | I9: =H9-C9 -> 805
B10: =B9+1 -> 46249 | C10: 0 | D10: 0 | I10: =H10-C10 -> 0
B11: Total Week | C11: =SUM(C4:C10) -> -805 | D11: =SUM(D4:D10) -> 805 | H11: =SUM(H4:H10) -> 0 | I11: =SUM(I4:I10) -> 805
B12: =B10+1 -> 46250 | C12: 0 | D12: 0 | I12: =H12-C12 -> 0
B13: =B12+1 -> 46251 | C13: 0 | D13: 0 | I13: =H13-C13 -> 0
B14: =B13+1 -> 46252 | C14: 0 | D14: 0 | I14: =H14-C14 -> 0
B15: =B14+1 -> 46253 | C15: 0 | D15: 0 | I15: =H15-C15 -> 0
B16: =B15+1 -> 46254 | C16: 0 | D16: 800 | E16: BR | I16: =H16-C16 -> 0
B17: =B16+1 -> 46255 | C17: 0 | D17: 0 | I17: =H17-C17 -> 0
B18: =B17+1 -> 46256 | C18: -800 | D18: 0 | E18: BR | I18: =H18-C18 -> 800
B19: Total Week | C19: =SUM(C12:C18) -> -800 | D19: =SUM(D12:D18) -> 800 | H19: =SUM(H12:H18) -> 0 | I19: =SUM(I12:I18) -> 800
B20: =B18+1 -> 46257 | C20: 0 | D20: 0 | I20: =H20-C20 -> 0
B21: =B20+1 -> 46258 | C21: 0 | D21: 0 | I21: =H21-C21 -> 0
B22: =B21+1 -> 46259 | C22: 0 | D22: 0 | I22: =H22-C22 -> 0
B23: =B22+1 -> 46260 | C23: 0 | D23: 0 | I23: =H23-C23 -> 0
B24: =B23+1 -> 46261 | C24: 0 | D24: 800 | E24: BR | I24: =H24-C24 -> 0
B25: =B24+1 -> 46262 | C25: 0 | D25: 0 | I25: =H25-C25 -> 0
B26: =B25+1 -> 46263 | C26: 800 | D26: 0 | E26: BR | I26: =H26-C26 -> -800
B27: Total Week | C27: =SUM(C20:C26) -> 800 | D27: =SUM(D20:D26) -> 800 | H27: =SUM(H20:H26) -> 0 | I27: =SUM(I20:I26) -> -800
B28: =B26+1 -> 46264 | C28: 0 | D28: 0 | I28: =H28-C28 -> 0
B29: =B28+1 -> 46265 | C29: 0 | D29: 0 | I29: =H29-C29 -> 0
B30: =B29+1 -> 46266 | C30: 0 | D30: 0 | I30: =H30-C30 -> 0
B31: =B30+1 -> 46267 | C31: 0 | D31: 0 | I31: =H31-C31 -> 0
B32: =B31+1 -> 46268 | C32: 0 | D32: 855 | E32: BR | I32: =H32-C32 -> 0
B33: =B32+1 -> 46269 | C33: 0 | D33: 0 | I33: =H33-C33 -> 0
B34: =B33+1 -> 46270 | C34: 855 | D34: 0 | E34: BR | I34: =H34-C34 -> -855
B35: Total Week | C35: =SUM(C28:C34) -> 855 | D35: =SUM(D28:D34) -> 855 | H35: =SUM(H28:H34) -> 0 | I35: =SUM(I28:I34) -> -855
B36: Total Period | C36: =SUM(C35+C27+C19+C11) -> 50 | D36: =SUM(D35+D27+D19+D11) -> 3260 | H36: =SUM(H35+H27+H19+H11) -> 0 | I36: =SUM(I35+I27+I19+I11) -> -50
B37: Period Activity | C37: =D36+C36 -> 3310 | H37: =I36+H36 -> -50 | I37: =J36+I36 -> -50
C38: =B34+1 -> 46271 | D38: After Period Close
B39: Ending Period Count of Amount on hand | C39: 0
B41: Number of Cash Drawers | C41: 3
B43: Amount of Each Drawer | C43: 200
B45: Amount of Petty Cash | C45: 300
B47: Period10
B48: Sun 9-6 | C48: 0 | D48: 0 | E48: JA | F48: OVER 19 | H48: 19 | I48: =H48-C48 -> 19
B49: Mon 9-7 | C49: 0 | D49: 0 | E49: JA | F49: Short 46 | H49: -46 | I49: =H49-C49 -> -46
B50: Tue 9-8 | C50: 0 | D50: 0 | E50: JA | F50: Short 11 | H50: -11 | I50: =H50-C50 -> -11
B51: Wed 9-9 | C51: 0 | D51: 0 | E51: AJ | F51: Short 21 | H51: -21 | I51: =H51-C51 -> -21
B52: Thu 9-10 | C52: 0 | D52: 875 | E52: BR/JA/OM | F52: Change order received over 43 | H52: 43 | I52: =H52-C52 -> 43
B53: Fri 9-11 | C53: 0 | D53: 0 | E53: BR/JA/OM | F53: Over 24 | H53: 24 | I53: =H53-C53 -> 24
B54: Sat 9-12 | C54: 875 | D54: 0 | E54: BR/JA/OM | F54: Change Paid | H54: 848 | I54: =H54-C54 -> -27
B55: Total Week | C55: =SUM(C48:C54) -> 875 | D55: =SUM(D48:D54) -> 875 | E55: BR/JA/OM | H55: =SUM(H48:H54) -> 856 | I55: =SUM(I48:I54) -> -19
B56: Sun 9-13 | C56: 0 | D56: 0 | E56: JA | F56: over 20 | H56: 20 | I56: =H56-C56 -> 20
B57: Mon 9-14 | C57: 0 | D57: 0 | E57: JA | F57: Shoort 4 | H57: -4 | I57: =H57-C57 -> -4
B58: Tue 9-15 | C58: 0 | D58: 0 | E58: OM | F58: DROP DIDNT GO THRUE FOR $460 | H58: -478 | I58: =H58-C58 -> -478
B59: Wed 9-16 | C59: 0 | D59: 0 | E59: JA | F59: short 47 | H59: -46.59 | I59: =H59-C59 -> -46.59
B60: Thu 9-17 | C60: 0 | D60: 850 | E60: BR/JA/OM | F60: Change order received over 52 | H60: 52 | I60: =H60-C60 -> 52
B61: Fri 9-18 | C61: 0 | D61: 0 | E61: BR/JA/OM | F61: over 52 | H61: 52.24 | I61: =H61-C61 -> 52.24
B62: Sat 9-19 | C62: 850 | D62: 0 | E62: BR/JA/OM | F62: over 18 | H62: 868 | I62: =H62-C62 -> 18
B63: Total Week | C63: =SUM(C56:C62) -> 850 | D63: =SUM(D56:D62) -> 850 | H63: =SUM(H56:H62) -> 463.65 | I63: =SUM(I56:I62) -> -386.35
B64: Sun 9-20 | C64: 0 | D64: 0 | E64: JA | F64: short 1 | H64: -1 | I64: =H64-C64 -> -1
B65: Mon 9-21 | C65: 0 | D65: 0 | E65: JA | F65: short 53 | H65: -53 | I65: =H65-C65 -> -53
B66: Tue 9-22 | C66: 0 | D66: 0 | E66: JA | F66: short 15 | H66: -15 | I66: =H66-C66 -> -15
B67: Wed 9-23 | C67: 0 | D67: 0 | E67: AJ | F67: over 22 | H67: 22 | I67: =H67-C67 -> 22
B68: Thu 9-24 | C68: 0 | D68: 0 | E68: BR | F68: OVER 59 No change order this week | H68: 59 | I68: =H68-C68 -> 59
B69: Fri 9-25 | C69: 0 | D69: 0 | E69: BR/JA/OM | F69: Short 22 | H69: -22 | I69: =H69-C69 -> -22
B70: Sat 9-26 | C70: 0 | D70: 0 | E70: BR/JA/OM | F70: Short 20 | H70: -20 | I70: =H70-C70 -> -20
B71: Total Week | C71: =SUM(C64:C70) -> 0 | D71: =SUM(D64:D70) -> 0 | H71: =SUM(H64:H70) -> -30 | I71: =SUM(I64:I70) -> -30
B72: Sun 9-27 | C72: 0 | D72: 0 | E72: BR/JA/OM | F72: OVER 32 | H72: 32 | I72: =H72-C72 -> 32
B73: Mon 9-28 | C73: 0 | D73: 0 | E73: BR | F73: Short 5 | H73: -5 | I73: =H73-C73 -> -5
B74: Tue 9-29 | C74: 0 | D74: 0 | E74: BR | F74: Short 22 | H74: -22 | I74: =H74-C74 -> -22
B75: Wed 9-30 | C75: 0 | D75: 0 | E75: JA | F75: Short 14 | H75: -14 | I75: =H75-C75 -> -14
B76: Thu 10-1 | C76: 0 | D76: 1820 | E76: JA | F76: Change order received over 7 | H76: 7 | I76: 7
B77: Fri 10-2 | C77: 900 | D77: 0 | E77: JA | F77: Short | H77: 866 | I77: =H77-C77 -> -34
B78: Sat 10-3 | D78: 0 | E78: JA | F78: Short 46 | H78: -46 | I78: =H78-C78 -> -46
B79: Total Week | C79: =SUM(C72:C78) -> 900 | D79: =SUM(D72:D78) -> 1820 | H79: =SUM(H72:H78) -> 818 | I79: =SUM(I72:I78) -> -82
B80: Total Period | C80: =SUM(C79+C71+C63+C55) -> 2625 | D80: =SUM(D79+D71+D63+D55) -> 3545 | H80: =SUM(H79+H71+H63+H55) -> 2107.65 | I80: =SUM(I79+I71+I63+I55) -> -517.35
B81: Period Activity | C81: =D80+C80 -> 6170 | H81: =I80+H80 -> 1590.3 | I81: =J80+I80 -> -517.35
C82: Sun 10-4 | D82: After Period Close
B83: Ending Period Count of Amopunt on hand | C83: 920 | E83: JA | F83: still have one bag of 920
B85: Number of Cash Drawers | C85: 3
B87: Amount of Each Drawer | C87: 200
B89: Amount of Petty Cash | C89: 300
B91: Period11
B92: Sun 10-4 | C92: 0 | D92: 0 | E92: OM | F92: short 20 | H92: -20 | I92: =H92-C92 -> -20
B93: Mon 10-5 | C93: 0 | D93: 0 | E93: JA | F93: Over 10 | H93: 10 | I93: =H93-C93 -> 10
B94: Tue 10-6 | C94: 0 | D94: 0 | E94: JA | F94: Over 26 | H94: 25.72 | I94: =H94-C94 -> 25.72
B95: Wed 10-7 | C95: 0 | D95: 0 | E95: JA | F95: Short 15 | H95: -15 | I95: =H95-C95 -> -15
B96: Thu 10-8 | C96: 920 | D96: 0 | E96: JA | F96: Change order deposit | H96: 902 | I96: =H96-C96 -> -18
B97: Fri 10-9 | C97: 0 | D97: 0 | E97: JA | F97: Short 12 | H97: -12 | I97: =H97-C97 -> -12
B98: Sat 10-10 | C98: 0 | D98: 0 | E98: JA | F98: Short 22 | H98: -22 | I98: =H98-C98 -> -22
B99: Total Week | C99: =SUM(C92:C98) -> 920 | D99: =SUM(D92:D98) -> 0 | H99: =SUM(H92:H98) -> 868.72 | I99: =SUM(I92:I98) -> -51.28
B100: Sun 10-11 | C100: 0 | D100: 0 | E100: JA | F100: Over 8 | H100: 8 | I100: =H100-C100 -> 8
B101: Mon 10-12 | C101: 0 | D101: 0 | H101: 0 | I101: =H101-C101 -> 0
B102: Tue 10-13 | C102: 0 | D102: 0 | H102: 0 | I102: =H102-C102 -> 0
B103: Wed 10-14 | C103: 0 | D103: 0 | H103: 0 | I103: =H103-C103 -> 0
B104: Thu 10-15 | C104: 0 | D104: 0 | H104: 0 | I104: =H104-C104 -> 0
B105: Fri 10-16 | C105: 0 | D105: 0 | H105: 0 | I105: =H105-C105 -> 0
B106: Sat 10-17 | C106: 0 | D106: 0 | H106: 0 | I106: =H106-C106 -> 0
B107: Total Week | C107: =SUM(C100:C106) -> 0 | D107: =SUM(D100:D106) -> 0 | H107: =SUM(H100:H106) -> 8 | I107: =SUM(I100:I106) -> 8
B108: Sun 10-18 | C108: 0 | D108: 0 | H108: 0 | I108: =H108-C108 -> 0
...

Sheet RV
C1: Riverside
C2: Per Restaurant
C3: Chage Order Deposits | D3: Change Order Received | E3: Initials | F3: Comments | H3: Cash over/ (Short) per R365 Flash report | I3: True Over/ (Short)
B4: =Control!$B$3 -> 46243 | C4: 0 | D4: 0 | I4: =H4-C4 -> 0
B5: =B4+1 -> 46244 | C5: 0 | D5: 0 | I5: =H5-C5 -> 0
B6: =B5+1 -> 46245 | C6: 1225 | D6: 1270 | I6: =H6-C6 -> -1225
B7: =B6+1 -> 46246 | C7: 0 | D7: 0 | I7: =H7-C7 -> 0
B8: =B7+1 -> 46247 | C8: 0 | D8: 0 | I8: =H8-C8 -> 0
B9: =B8+1 -> 46248 | C9: 0 | D9: 0 | I9: =H9-C9 -> 0
B10: =B9+1 -> 46249 | C10: 0 | D10: 0 | I10: =H10-C10 -> 0
B11: Total Week | C11: =SUM(C4:C10) -> 1225 | D11: =SUM(D4:D10) -> 1270 | H11: =SUM(H4:H10) -> 0 | I11: =SUM(I4:I10) -> -1225
B12: =B10+1 -> 46250 | C12: 0 | D12: 0 | I12: =H12-C12 -> 0
B13: =B12+1 -> 46251 | C13: 0 | D13: 0 | I13: =H13-C13 -> 0
B14: =B13+1 -> 46252 | C14: 1270 | D14: 1100 | E14: JP | I14: =H14-C14 -> -1270
B15: =B14+1 -> 46253 | C15: 0 | D15: 0 | I15: =H15-C15 -> 0
B16: =B15+1 -> 46254 | C16: 0 | D16: 0 | I16: =H16-C16 -> 0
B17: =B16+1 -> 46255 | C17: 0 | D17: 0 | I17: =H17-C17 -> 0
B18: =B17+1 -> 46256 | C18: 0 | D18: 0 | I18: =H18-C18 -> 0
B19: Total Week | C19: =SUM(C12:C18) -> 1270 | D19: =SUM(D12:D18) -> 1100 | H19: =SUM(H12:H18) -> 0 | I19: =SUM(I12:I18) -> -1270
B20: =B18+1 -> 46257 | C20: 0 | D20: 0 | I20: =H20-C20 -> 0
B21: =B20+1 -> 46258 | C21: 0 | D21: 0 | I21: =H21-C21 -> 0
B22: =B21+1 -> 46259 | C22: 0 | D22: 0 | I22: =H22-C22 -> 0
B23: =B22+1 -> 46260 | C23: 0 | D23: 0 | H23: 0 | I23: =H23-C23 -> 0
B24: =B23+1 -> 46261 | C24: 0 | D24: 0 | I24: =H24-C24 -> 0
B25: =B24+1 -> 46262 | C25: 0 | D25: 0 | I25: =H25-C25 -> 0
B26: =B25+1 -> 46263 | C26: 0 | D26: 0 | I26: =H26-C26 -> 0
B27: Total Week | C27: =SUM(C20:C26) -> 0 | D27: =SUM(D20:D26) -> 0 | H27: =SUM(H20:H26) -> 0 | I27: =SUM(I20:I26) -> 0
B28: =B26+1 -> 46264 | C28: 0 | D28: 0 | I28: =H28-C28 -> 0
B29: =B28+1 -> 46265 | C29: 0 | D29: 0 | I29: =H29-C29 -> 0
B30: =B29+1 -> 46266 | C30: 0 | D30: 1150 | E30: CA | I30: =H30-C30 -> 0
B31: =B30+1 -> 46267 | C31: 0 | D31: 0 | I31: =H31-C31 -> 0
B32: =B31+1 -> 46268 | C32: 0 | D32: 0 | I32: =H32-C32 -> 0
B33: =B32+1 -> 46269 | C33: 0 | D33: 0 | I33: =H33-C33 -> 0
B34: =B33+1 -> 46270 | C34: 1100 | D34: 0 | E34: JP | I34: =H34-C34 -> -1100
B35: Total Week | C35: =SUM(C28:C34) -> 1100 | D35: =SUM(D28:D34) -> 1150 | H35: =SUM(H28:H34) -> 0 | I35: =SUM(I28:I34) -> -1100
B36: Total Period | C36: =SUM(C35+C27+C19+C11) -> 3595 | D36: =SUM(D35+D27+D19+D11) -> 3520 | H36: =SUM(H35+H27+H19+H11) -> 0 | I36: =SUM(I35+I27+I19+I11) -> -3595
B37: Period Activity | C37: =D36+C36 -> 7115 | H37: =I36+H36 -> -3595 | I37: =J36+I36 -> -3595
C38: =B34+1 -> 46271 | D38: After Period Close
B39: Ending Period Count of Amount on hand | C39: 1150 | E39: JP
B41: Number of Cash Drawers | C41: 2
B43: Amount of Each Drawer | C43: 200
B45: Amount of Petty Cash | C45: 300
B47: Period10
B48: Sun 9-6 | C48: 0 | D48: 0 | E48: CA | H48: 21 | I48: =H48-C48 -> 21
B49: Mon 9-7 | C49: 0 | D49: 0 | E49: CA | F49: LABOR DAY | H49: 13 | I49: =H49-C49 -> 13
B50: Tue 9-8 | C50: 0 | D50: 0 | E50: CA | H50: 12 | I50: =H50-C50 -> 12
B51: Wed 9-9 | C51: 0 | D51: 1220 | E51: CA | H51: 10 | I51: =H51-C51 -> 10
B52: Thu 9-10 | C52: 1150 | D52: 0 | E52: JP | F52: Change deposit | H52: 1152 | I52: =H52-C52 -> 2
B53: Fri 9-11 | D53: 0 | E53: JP | H53: 23 | I53: =H53-C53 -> 23
B54: Sat 9-12 | C54: 0 | D54: 0 | E54: CA | H54: 22 | I54: =H54-C54 -> 22
B55: Total Week | C55: =SUM(C48:C54) -> 1150 | D55: =SUM(D48:D54) -> 1220 | H55: =SUM(H48:H54) -> 1253 | I55: =SUM(I48:I54) -> 103
B56: Sun 9-13 | C56: 0 | D56: 0 | E56: CA | H56: 2 | I56: =H56-C56 -> 2
B57: Mon 9-14 | C57: 0 | D57: 0 | E57: CA | H57: 3 | I57: =H57-C57 -> 3
B58: Tue 9-15 | C58: 0 | D58: 1200 | E58: CA | H58: 7 | I58: =H58-C58 -> 7
B59: Wed 9-16 | C59: 0 | D59: 0 | E59: CA | H59: 7 | I59: =H59-C59 -> 7
B60: Thu 9-17 | C60: 0 | D60: 0 | E60: CA | H60: -0.32 | I60: =H60-C60 -> -0.32
B61: Fri 9-18 | C61: 1220 | D61: 0 | E61: CA | H61: 1222 | I61: =H61-C61 -> 2
B62: Sat 9-19 | C62: 0 | D62: 0 | E62: CA | H62: -2 | I62: =H62-C62 -> -2
B63: Total Week | C63: =SUM(C56:C62) -> 1220 | D63: =SUM(D56:D62) -> 1200 | H63: =SUM(H56:H62) -> 1238.68 | I63: =SUM(I56:I62) -> 18.68
B64: Sun 9-20 | C64: 0 | D64: 0 | E64: MR | H64: 2 | I64: =H64-C64 -> 2
B65: Mon 9-21 | C65: 0 | D65: 0 | E65: CA | H65: 6 | I65: =H65-C65 -> 6
B66: Tue 9-22 | C66: 0 | D66: 0 | E66: CA | H66: -19 | I66: =H66-C66 -> -19
B67: Wed 9-23 | C67: 0 | D67: 0 | E67: JP | H67: 10 | I67: 10
B68: Thu 9-24 | C68: 0 | D68: 0 | E68: JP | H68: -38 | I68: =H68-C68 -> -38
B69: Fri 9-25 | C69: 0 | D69: 0 | E69: dd | H69: 19 | I69: =H69-C69 -> 19
B70: Sat 9-26 | C70: 0 | D70: 0 | E70: dd | H70: 13 | I70: =H70-C70 -> 13
B71: Total Week | C71: =SUM(C64:C70) -> 0 | D71: =SUM(D64:D70) -> 0 | I71: =SUM(I64:I70) -> -7
B72: Sun 9-27 | C72: 0 | D72: 0 | E72: dd | H72: 3 | I72: =H72-C72 -> 3
B73: Mon 9-28 | C73: 0 | D73: 0 | E73: CA | H73: 5 | I73: =H73-C73 -> 5
B74: Tue 9-29 | C74: 1200 | D74: 1220 | E74: CA | H74: 1196 | I74: =H74-C74 -> -4
B75: Wed 9-30 | C75: 0 | D75: 0 | E75: CA | H75: -7 | I75: =H75-C75 -> -7
B76: Thu 10-1 | C76: 0 | D76: 0 | E76: JP | H76: -22 | I76: =H76-C76 -> -22
B77: Fri 10-2 | C77: 0 | D77: 0 | E77: JP | H77: -5 | I77: =H77-C77 -> -5
B78: Sat 10-3 | D78: 0 | E78: JP | H78: -29 | I78: =H78-C78 -> -29
B79: Total Week | C79: =SUM(C72:C78) -> 1200 | D79: =SUM(D72:D78) -> 1220 | H79: =SUM(H72:H78) -> 1141 | I79: =SUM(I72:I78) -> -59
B80: Total Period | C80: =SUM(C79+C71+C63+C55) -> 3570 | D80: =SUM(D79+D71+D63+D55) -> 3640 | H80: =SUM(H79+H71+H63+H55) -> 3632.68 | I80: =SUM(I79+I71+I63+I55) -> 55.68
B81: Period Activity | C81: =D80+C80 -> 7210 | H81: =I80+H80 -> 3688.36 | I81: =J80+I80 -> 55.68
C82: Sun 10-4 | D82: After Period Close
B83: Ending Period Count of Amopunt on hand | C83: 1220 | E83: JP
B85: Number of Cash Drawers | C85: 2
B87: Amount of Each Drawer | C87: 200
B89: Amount of Petty Cash | C89: 300
B91: Period11
B92: Sun 10-4 | C92: 0 | D92: 0 | E92: dd | F92: we are over $16.00 | H92: 16 | I92: =H92-C92 -> 16
B93: Mon 10-5 | C93: 0 | D93: 0 | E93: dd | F93: we are over $27 | H93: 27 | I93: =H93-C93 -> 27
B94: Tue 10-6 | C94: 0 | D94: 0 | E94: CA | H94: -3 | I94: =H94-C94 -> -3
B95: Wed 10-7 | C95: 0 | D95: 0 | E95: CA | H95: 50 | I95: =H95-C95 -> 50
B96: Thu 10-8 | C96: 1220 | D96: 1200 | E96: JP | F96: Change order received & deposits | H96: 1176 | I96: =H96-C96 -> -44
B97: Fri 10-9 | C97: 0 | D97: 0 | E97: CA | H97: 4 | I97: =H97-C97 -> 4
B98: Sat 10-10 | C98: 0 | D98: 0 | E98: CA | H98: 26 | I98: =H98-C98 -> 26
B99: Total Week | C99: =SUM(C92:C98) -> 1220 | D99: =SUM(D92:D98) -> 1200 | H99: =SUM(H92:H98) -> 1296 | I99: =SUM(I92:I98) -> 76
B100: Sun 10-11 | C100: 0 | D100: 0 | H100: 0 | I100: =H100-C100 -> 0
B101: Mon 10-12 | C101: 0 | D101: 0 | H101: 0 | I101: =H101-C101 -> 0
B102: Tue 10-13 | C102: 0 | D102: 0 | H102: 0 | I102: =H102-C102 -> 0
B103: Wed 10-14 | C103: 0 | D103: 0 | H103: 0 | I103: =H103-C103 -> 0
B104: Thu 10-15 | C104: 0 | D104: 0 | H104: 0 | I104: =H104-C104 -> 0
B105: Fri 10-16 | C105: 0 | D105: 0 | H105: 0 | I105: =H105-C105 -> 0
B106: Sat 10-17 | C106: 0 | D106: 0 | H106: 0 | I106: =H106-C106 -> 0
B107: Total Week | C107: =SUM(C100:C106) -> 0 | D107: =SUM(D100:D106) -> 0 | H107: =SUM(H100:H106) -> 0 | I107: =SUM(I100:I106) -> 0
B108: Sun 10-18 | C108: 0 | D108: 0 | H108: 0 | I108: =H108-C108 -> 0
...

Sheet SA
C1: Santa Ana
C2: Per Restaurant
C3: Chage Order Deposits | D3: Change Order Received | E3: Initials | F3: Comments | H3: Cash over/ (Short) per R365 Flash report | I3: True Over/ (Short)
B4: =Control!$B$3 -> 46243 | C4: 0 | D4: 499 | F4: 499 change order left unpaid from previous period. | H4: 273 | I4: =H4-C4 -> 273
B5: =B4+1 -> 46244 | C5: 251 | D5: 0 | H5: 201 | I5: =H5-C5 -> -50
B6: =B5+1 -> 46245 | C6: 0 | D6: 0 | H6: 537 | I6: =H6-C6 -> 537
B7: =B6+1 -> 46246 | C7: 245 | D7: 905 | H7: -871 | I7: =H7-C7 -> -1116
B8: =B7+1 -> 46247 | C8: 300 | D8: 0 | H8: 552 | I8: =H8-C8 -> 252
B9: =B8+1 -> 46248 | C9: 0 | D9: 0 | H9: 18 | I9: =H9-C9 -> 18
B10: =B9+1 -> 46249 | C10: 0 | D10: 0 | H10: 22 | I10: =H10-C10 -> 22
B11: Total Week | C11: =SUM(C4:C10) -> 796 | D11: =SUM(D4:D10) -> 1404 | H11: =SUM(H4:H10) -> 732 | I11: =SUM(I4:I10) -> -64
B12: =B10+1 -> 46250 | C12: 300 | D12: 0 | H12: 569 | I12: =H12-C12 -> 269
B13: =B12+1 -> 46251 | C13: 0 | D13: 0 | H13: 24 | I13: =H13-C13 -> 24
B14: =B13+1 -> 46252 | C14: 200 | D14: 830 | E14: ema | H14: -434 | I14: =H14-C14 -> -634
B15: =B14+1 -> 46253 | C15: 200 | D15: 0 | H15: 430 | I15: =H15-C15 -> 230
B16: =B15+1 -> 46254 | C16: 0 | D16: 0 | H16: 111 | I16: =H16-C16 -> 111
B17: =B16+1 -> 46255 | C17: 0 | D17: 0 | H17: 106 | I17: =H17-C17 -> 106
B18: =B17+1 -> 46256 | C18: 300 | D18: 0 | H18: 625 | I18: =H18-C18 -> 325
B19: Total Week | C19: =SUM(C12:C18) -> 1000 | D19: =SUM(D12:D18) -> 830 | H19: =SUM(H12:H18) -> 1431 | I19: =SUM(I12:I18) -> 431
B20: =B18+1 -> 46257 | C20: 150 | D20: 0 | H20: -42 | I20: =H20-C20 -> -192
B21: =B20+1 -> 46258 | C21: 335 | D21: 0 | H21: 590 | I21: =H21-C21 -> 255
B22: =B21+1 -> 46259 | C22: 0 | D22: 900 | E22: ema | H22: -812 | I22: =H22-C22 -> -812
B23: =B22+1 -> 46260 | C23: 105 | D23: 0 | H23: 112 | I23: =H23-C23 -> 7
B24: =B23+1 -> 46261 | C24: 500 | D24: 0 | H24: 473 | I24: =H24-C24 -> -27
B25: =B24+1 -> 46262 | C25: 300 | D25: 755 | E25: ema | H25: 309 | I25: =H25-C25 -> 9
B26: =B25+1 -> 46263 | C26: 420 | D26: 0 | H26: 459 | I26: =H26-C26 -> 39
B27: Total Week | C27: =SUM(C20:C26) -> 1810 | D27: =SUM(D20:D26) -> 1655 | H27: =SUM(H20:H26) -> 1089 | I27: =SUM(I20:I26) -> -721
B28: =B26+1 -> 46264 | C28: 0 | D28: 0 | H28: 8 | I28: =H28-C28 -> 8
B29: =B28+1 -> 46265 | C29: 0 | D29: 0 | H29: 10 | I29: =H29-C29 -> 10
B30: =B29+1 -> 46266 | C30: 0 | D30: 0 | H30: 13 | I30: =H30-C30 -> 13
B31: =B30+1 -> 46267 | C31: 0 | D31: 0 | H31: 15 | I31: =H31-C31 -> 15
B32: =B31+1 -> 46268 | C32: 435 | D32: 980 | E32: ema | H32: 425 | I32: =H32-C32 -> -10
B33: =B32+1 -> 46269 | C33: 250 | D33: 0 | H33: 116 | I33: =H33-C33 -> -134
B34: =B33+1 -> 46270 | C34: 0 | D34: 0 | H34: -30 | I34: =H34-C34 -> -30
B35: Total Week | C35: =SUM(C28:C34) -> 685 | D35: =SUM(D28:D34) -> 980 | H35: =SUM(H28:H34) -> 557 | I35: =SUM(I28:I34) -> -128
B36: Total Period | C36: =SUM(C35+C27+C19+C11) -> 4291 | D36: =SUM(D35+D27+D19+D11) -> 4869 | F36: 0 | H36: =SUM(H35+H27+H19+H11) -> 3809 | I36: =SUM(I35+I27+I19+I11) -> -482
B37: Period Activity | C37: =D36+C36 -> 9160 | H37: =I36+H36 -> 3327 | I37: =J36+I36 -> -482
C38: =B34+1 -> 46271 | D38: After Period Close
B39: Ending Period Count of Amount on hand | C39: 805 | E39: ema
B41: Number of Cash Drawers | C41: 2
B43: Amount of Each Drawer | C43: 200
B45: Amount of Petty Cash | C45: 300
B47: Period10
B48: Sun 9-6 | C48: 300 | D48: 0 | E48: ema | H48: -157 | I48: =H48-C48 -> -457
B49: Mon 9-7 | C49: 0 | D49: 0 | F49: morning drop 450 didn't go in until after 7:30, today short 450 | H49: 482 | I49: =H49-C49 -> 482
B50: Tue 9-8 | C50: 0 | D50: 0 | F50: Tuesday will be over 450$ | H50: -58 | I50: =H50-C50 -> -58
B51: Wed 9-9 | D51: 1075 | E51: ema | H51: -30 | I51: =H51-C51 -> -30
B52: Thu 9-10 | C52: 250 | D52: 0 | E52: ema | H52: 303 | I52: =H52-C52 -> 53
B53: Fri 9-11 | C53: 180 | D53: 0 | E53: ema | H53: 193 | I53: =H53-C53 -> 13
B54: Sat 9-12 | C54: 475 | D54: 0 | E54: ema | H54: 489 | I54: =H54-C54 -> 14
B55: Total Week | C55: =SUM(C48:C54) -> 1205 | D55: =SUM(D48:D54) -> 1075 | H55: =SUM(H48:H54) -> 1222 | I55: =SUM(I48:I54) -> 17
B56: Sun 9-13 | C56: 0 | D56: 0 | H56: 489 | I56: =H56-C56 -> 489
B57: Mon 9-14 | C57: 0 | D57: 0 | H57: -8 | I57: =H57-C57 -> -8
B58: Tue 9-15 | C58: 300 | D58: 905 | E58: st | F58: Paid in for $905 and paidout for $300 accidently added in pos | H58: -341 | I58: =H58-C58 -> -641
B59: Wed 9-16 | C59: 0 | D59: 0 | H59: 18 | I59: =H59-C59 -> 18
B60: Thu 9-17 | C60: 400 | D60: 0 | E60: ema | F60: paid out for $605 added to correct accident from TUE | H60: 1020 | I60: =H60-C60 -> 620
B61: Fri 9-18 | C61: 0 | D61: 0 | H61: 6 | I61: =H61-C61 -> 6
B62: Sat 9-19 | C62: 370 | D62: 0 | E62: ema | H62: 259 | I62: =H62-C62 -> -111
B63: Total Week | C63: =SUM(C56:C62) -> 1070 | D63: =SUM(D56:D62) -> 905 | H63: =SUM(H56:H62) -> 1443 | I63: =SUM(I56:I62) -> 373
B64: Sun 9-20 | C64: 0 | D64: 0 | H64: 92 | I64: =H64-C64 -> 92
B65: Mon 9-21 | C65: 100 | D65: 0 | H65: 81 | I65: =H65-C65 -> -19
B66: Tue 9-22 | C66: 0 | D66: 800 | E66: ST | H66: 89 | I66: =H66-C66 -> 89
B67: Wed 9-23 | C67: 480 | D67: 0 | E67: ema | H67: 490 | I67: =H67-C67 -> 10
B68: Thu 9-24 | C68: 100 | D68: 0 | E68: ea | H68: -41 | I68: =H68-C68 -> -141
B69: Fri 9-25 | C69: 336 | D69: 1000 | E69: ST | F69: Change order recived $1000.00 | H69: 261 | I69: =H69-C69 -> -75
B70: Sat 9-26 | C70: 500 | D70: 0 | E70: ema | H70: 594 | I70: =H70-C70 -> 94
B71: Total Week | C71: =SUM(C64:C70) -> 1516 | D71: =SUM(D64:D70) -> 1800 | H71: =SUM(H64:H70) -> 1566 | I71: =SUM(I64:I70) -> 50
B72: Sun 9-27 | C72: 300 | D72: 0 | E72: ema | H72: 320 | I72: =H72-C72 -> 20
B73: Mon 9-28 | C73: 0 | D73: 975 | E73: ST | F73: Change order recived $975.00 | H73: 9 | I73: =H73-C73 -> 9
B74: Tue 9-29 | C74: 400 | D74: 0 | E74: ema | H74: 350 | I74: =H74-C74 -> -50
B75: Wed 9-30 | C75: 0 | D75: 0 | H75: 10 | I75: =H75-C75 -> 10
B76: Thu 10-1 | C76: 604 | D76: 0 | E76: ema | F76: forgot to add daily deposit by 8am tot dep. 3416 | H76: 630 | I76: =H76-C76 -> 26
B77: Fri 10-2 | C77: 0 | D77: 0 | H77: -496 | I77: =H77-C77 -> -496
B78: Sat 10-3 | D78: 0 | E78: St | F78: Forgot to add daily deposit by 8AM tot deposit $2533.00 | H78: -34 | I78: =H78-C78 -> -34
B79: Total Week | C79: =SUM(C72:C78) -> 1304 | D79: =SUM(D72:D78) -> 975 | H79: =SUM(H72:H78) -> 789 | I79: =SUM(I72:I78) -> -515
B80: Total Period | C80: =SUM(C79+C71+C63+C55) -> 5095 | D80: =SUM(D79+D71+D63+D55) -> 4755 | H80: =SUM(H79+H71+H63+H55) -> 5020 | I80: =SUM(I79+I71+I63+I55) -> -75
B81: Period Activity | C81: =D80+C80 -> 9850 | H81: =I80+H80 -> 4945 | I81: =J80+I80 -> -75
C82: Sun 10-4 | D82: After Period Close
B83: Ending Period Count of Amopunt on hand | C83: 512 | E83: EA
B85: Number of Cash Drawers | C85: 2
B87: Amount of Each Drawer | C87: 200
B89: Amount of Petty Cash | C89: 300
B91: Period11
B92: Sun 10-4 | C92: 350 | D92: 900 | E92: ST | H92: 9 | I92: =H92-C92 -> -341
B93: Mon 10-5 | C93: 0 | D93: 0 | H93: 373 | I93: =H93-C93 -> 373
B94: Tue 10-6 | C94: 0 | D94: 0 | H94: -1 | I94: =H94-C94 -> -1
B95: Wed 10-7 | D95: 0 | H95: 89 | I95: =H95-C95 -> 89
B96: Thu 10-8 | C96: 300 | D96: 0 | E96: ema | H96: 315 | I96: =H96-C96 -> 15
B97: Fri 10-9 | C97: 0 | D97: 0 | H97: 7 | I97: =H97-C97 -> 7
B98: Sat 10-10 | C98: 400 | D98: 0 | E98: ema | H98: 430 | I98: =H98-C98 -> 30
B99: Total Week | C99: =SUM(C92:C98) -> 1050 | D99: =SUM(D92:D98) -> 900 | H99: =SUM(H92:H98) -> 1222 | I99: =SUM(I92:I98) -> 172
B100: Sun 10-11 | C100: 0 | D100: 0 | H100: 0 | I100: =H100-C100 -> 0
B101: Mon 10-12 | C101: 0 | D101: 0 | H101: 0 | I101: =H101-C101 -> 0
B102: Tue 10-13 | C102: 0 | D102: 0 | H102: 0 | I102: =H102-C102 -> 0
B103: Wed 10-14 | C103: 0 | D103: 0 | H103: 0 | I103: =H103-C103 -> 0
B104: Thu 10-15 | C104: 0 | D104: 0 | H104: 0 | I104: =H104-C104 -> 0
B105: Fri 10-16 | C105: 0 | D105: 0 | H105: 0 | I105: =H105-C105 -> 0
B106: Sat 10-17 | C106: 0 | D106: 0 | H106: 0 | I106: =H106-C106 -> 0
B107: Total Week | C107: =SUM(C100:C106) -> 0 | D107: =SUM(D100:D106) -> 0 | H107: =SUM(H100:H106) -> 0 | I107: =SUM(I100:I106) -> 0
B108: Sun 10-18 | C108: 0 | D108: 0 | H108: 0 | I108: =H108-C108 -> 0
...

Sheet SL
C1: Slauson
C2: Per Restaurant
C3: Chage Order Deposits | D3: Change Order Received | E3: Initials | F3: Comments | H3: Cash over/ (Short) per R365 Flash report | I3: True Over/ (Short)
B4: =Control!$B$3 -> 46243 | C4: 0 | D4: 2376 | E4: RG | F4: Prior Period 8 owed $2376 | H4: -123.83 | I4: =H4-C4 -> -123.83
B5: =B4+1 -> 46244 | C5: 0 | D5: 0 | H5: 39.51 | I5: =H5-C5 -> 39.51
B6: =B5+1 -> 46245 | C6: 0 | D6: 0 | H6: -9.21 | I6: =H6-C6 -> -9.21
B7: =B6+1 -> 46246 | C7: 0 | D7: 0 | H7: 267.36 | I7: =H7-C7 -> 267.36
B8: =B7+1 -> 46247 | C8: 0 | D8: 0 | H8: 289.63 | I8: =H8-C8 -> 289.63
B9: =B8+1 -> 46248 | C9: 0 | D9: 0 | H9: 499.01 | I9: =H9-C9 -> 499.01
B10: =B9+1 -> 46249 | C10: 0 | D10: 0 | H10: -646.65 | I10: =H10-C10 -> -646.65
B11: Total Week | C11: =SUM(C4:C10) -> 0 | D11: =SUM(D4:D10) -> 2376 | H11: =SUM(H4:H10) -> 315.82 | I11: =SUM(I4:I10) -> 315.82
B12: =B10+1 -> 46250 | C12: 0 | D12: 0 | H12: -35.05 | I12: =H12-C12 -> -35.05
B13: =B12+1 -> 46251 | C13: 0 | D13: 0 | H13: -105.15 | I13: =H13-C13 -> -105.15
B14: =B13+1 -> 46252 | C14: 0 | D14: 0 | H14: -202.16 | I14: =H14-C14 -> -202.16
B15: =B14+1 -> 46253 | C15: 0 | D15: 0 | E15: RG | H15: 276.95 | I15: =H15-C15 -> 276.95
B16: =B15+1 -> 46254 | C16: 0 | D16: 0 | E16: RG | H16: 144.49 | I16: =H16-C16 -> 144.49
B17: =B16+1 -> 46255 | C17: 0 | D17: 0 | H17: -213.92 | I17: =H17-C17 -> -213.92
B18: =B17+1 -> 46256 | C18: 0 | D18: 0 | H18: 12.82 | I18: =H18-C18 -> 12.82
B19: Total Week | C19: =SUM(C12:C18) -> 0 | D19: =SUM(D12:D18) -> 0 | H19: =SUM(H12:H18) -> -122.02 | I19: =SUM(I12:I18) -> -122.02
B20: =B18+1 -> 46257 | C20: 0 | D20: 0 | H20: -112.87 | I20: =H20-C20 -> -112.87
B21: =B20+1 -> 46258 | C21: 0 | D21: 0 | H21: -311.29 | I21: =H21-C21 -> -311.29
B22: =B21+1 -> 46259 | C22: 0 | D22: 2990 | E22: Rg | H22: 289.37 | I22: =H22-C22 -> 289.37
B23: =B22+1 -> 46260 | C23: 0 | D23: 0 | H23: -53.52 | I23: =H23-C23 -> -53.52
B24: =B23+1 -> 46261 | C24: 0 | D24: 0 | H24: 45.06 | I24: =H24-C24 -> 45.06
B25: =B24+1 -> 46262 | C25: 0 | D25: 0 | H25: -41.33 | I25: =H25-C25 -> -41.33
B26: =B25+1 -> 46263 | C26: 0 | D26: 0 | H26: -471.97 | I26: =H26-C26 -> -471.97
B27: Total Week | C27: =SUM(C20:C26) -> 0 | D27: =SUM(D20:D26) -> 2990 | H27: =SUM(H20:H26) -> -656.55 | I27: =SUM(I20:I26) -> -656.55
B28: =B26+1 -> 46264 | C28: 0 | D28: 0 | H28: 444.88 | I28: =H28-C28 -> 444.88
B29: =B28+1 -> 46265 | C29: 0 | D29: 0 | H29: -17.92 | I29: =H29-C29 -> -17.92
B30: =B29+1 -> 46266 | C30: 0 | D30: 0 | H30: -4.1 | I30: =H30-C30 -> -4.1
B31: =B30+1 -> 46267 | C31: 0 | D31: 0 | H31: 73.38 | I31: =H31-C31 -> 73.38
B32: =B31+1 -> 46268 | C32: 0 | D32: 0 | H32: -717.37 | I32: =H32-C32 -> -717.37
B33: =B32+1 -> 46269 | C33: 0 | D33: 0 | H33: 827.41 | I33: =H33-C33 -> 827.41
B34: =B33+1 -> 46270 | C34: 0 | D34: 0 | H34: -112.1 | I34: =H34-C34 -> -112.1
B35: Total Week | C35: =SUM(C28:C34) -> 0 | D35: =SUM(D28:D34) -> 0 | H35: =SUM(H28:H34) -> 494.18 | I35: =SUM(I28:I34) -> 494.18
B36: Total Period | C36: =SUM(C35+C27+C19+C11) -> 0 | D36: =SUM(D35+D27+D19+D11) -> 5366 | H36: =SUM(H35+H27+H19+H11) -> 31.43 | I36: =SUM(I35+I27+I19+I11) -> 31.43
B37: Period Activity | C37: =D36+C36 -> 5366 | H37: =I36+H36 -> 62.86 | I37: =J36+I36 -> 31.43
C38: =B34+1 -> 46271 | D38: After Period Close
B39: Ending Period Count of Amount on hand | C39: 5366 | F39: owed 5366
B41: Number of Cash Drawers | C41: 2
B43: Amount of Each Drawer | C43: 200
B45: Amount of Petty Cash | C45: 300
B47: Period10
B48: Sun 9-6 | C48: 0 | D48: 5366 | F48: Period 9 OWED Total 5366 | H48: -59.05 | I48: =H48-C48 -> -59.05
B49: Mon 9-7 | C49: 0 | D49: 0 | E49: RG | H49: -55.79 | I49: =H49-C49 -> -55.79
B50: Tue 9-8 | C50: 0 | D50: 0 | E50: Rg | H50: 13.39 | I50: =H50-C50 -> 13.39
B51: Wed 9-9 | C51: 0 | D51: 0 | E51: Rg | H51: -0.58 | I51: =H51-C51 -> -0.58
B52: Thu 9-10 | C52: 0 | D52: 0 | E52: Rg | H52: 129.33 | I52: =H52-C52 -> 129.33
B53: Fri 9-11 | C53: 100 | D53: 0 | E53: Rg | H53: 260.38 | I53: =H53-C53 -> 160.38
B54: Sat 9-12 | C54: 0 | D54: 0 | E54: Rg | H54: -199.33 | I54: =H54-C54 -> -199.33
B55: Total Week | C55: =SUM(C48:C54) -> 100 | D55: =SUM(D48:D54) -> 5366 | E55: Rg | H55: =SUM(H48:H54) -> 88.35 | I55: =SUM(I48:I54) -> -11.65
B56: Sun 9-13 | C56: 0 | D56: 0 | E56: Rg | H56: 35.63 | I56: =H56-C56 -> 35.63
B57: Mon 9-14 | C57: 0 | D57: 0 | E57: Rg | H57: -21.39 | I57: =H57-C57 -> -21.39
B58: Tue 9-15 | C58: 230 | D58: 0 | E58: Rg | H58: 230.89 | I58: =H58-C58 -> 0.89
B59: Wed 9-16 | C59: 0 | D59: 0 | E59: Rg | H59: 12.3 | I59: =H59-C59 -> 12.3
B60: Thu 9-17 | C60: 100 | D60: 0 | E60: Rg | H60: 88.86 | I60: =H60-C60 -> -11.14
B61: Fri 9-18 | C61: 0 | D61: 0 | E61: Rg | H61: 31.93 | I61: =H61-C61 -> 31.93
B62: Sat 9-19 | C62: 0 | D62: 0 | E62: Rg | H62: -45.18 | I62: =H62-C62 -> -45.18
B63: Total Week | C63: =SUM(C56:C62) -> 330 | D63: =SUM(D56:D62) -> 0 | E63: Rg | H63: =SUM(H56:H62) -> 333.04 | I63: =SUM(I56:I62) -> 3.04
B64: Sun 9-20 | C64: 0 | D64: 0 | E64: Rg | H64: -111.16 | I64: =H64-C64 -> -111.16
B65: Mon 9-21 | C65: 0 | D65: 0 | E65: Rg | H65: -7.86 | I65: =H65-C65 -> -7.86
B66: Tue 9-22 | C66: 0 | D66: 0 | E66: Rg | H66: 85.6 | I66: =H66-C66 -> 85.6
B67: Wed 9-23 | C67: 0 | D67: 0 | E67: Rg | H67: 114.77 | I67: =H67-C67 -> 114.77
B68: Thu 9-24 | C68: 0 | D68: 0 | E68: RG | H68: 118.89 | I68: =H68-C68 -> 118.89
B69: Fri 9-25 | C69: 0 | D69: 0 | E69: Rg | H69: -10.13 | I69: =H69-C69 -> -10.13
B70: Sat 9-26 | C70: 0 | D70: 0 | E70: Rg | H70: -417.36 | I70: =H70-C70 -> -417.36
B71: Total Week | C71: =SUM(C64:C70) -> 0 | D71: =SUM(D64:D70) -> 0 | H71: =SUM(H64:H70) -> -227.25 | I71: =SUM(I64:I70) -> -227.25
B72: Sun 9-27 | C72: 0 | D72: 0 | E72: fn | H72: 209.7 | I72: =H72-C72 -> 209.7
B73: Mon 9-28 | C73: 0 | D73: 0 | E73: fn | H73: -50.25 | I73: =H73-C73 -> -50.25
B74: Tue 9-29 | C74: 142 | D74: 0 | E74: fn | H74: 192.05 | I74: =H74-C74 -> 50.05
B75: Wed 9-30 | C75: 0 | D75: 0 | E75: RG | H75: -19.55 | I75: =H75-C75 -> -19.55
B76: Thu 10-1 | C76: 0 | D76: 0 | E76: RG | H76: 10.57 | I76: =H76-C76 -> 10.57
B77: Fri 10-2 | C77: 0 | D77: 0 | E77: Rg | H77: 17 | I77: =H77-C77 -> 17
B78: Sat 10-3 | C78: 2020 | D78: 0 | E78: Rg | H78: 2020.26 | I78: =H78-C78 -> 0.26
B79: Total Week | C79: =SUM(C72:C78) -> 2162 | D79: =SUM(D72:D78) -> 0 | E79: RG | H79: =SUM(H72:H78) -> 2379.78 | I79: =SUM(I72:I78) -> 217.78
B80: Total Period | C80: =SUM(C79+C71+C63+C55) -> 2592 | D80: =SUM(D79+D71+D63+D55) -> 5366 | E80: Rg | H80: =SUM(H79+H71+H63+H55) -> 2573.92 | I80: =SUM(I79+I71+I63+I55) -> -18.08
B81: Period Activity | C81: =D80-C80 -> 2774 | E81: Rg | H81: =I80+H80 -> 2555.84 | I81: =J80+I80 -> -18.08
C82: Sun 10-4 | D82: After Period Close
B83: Ending Period Count of Amopunt on hand | C83: 2774 | E83: Rg | F83: P 10 We owed 2774 + Pc300 = 3074
B85: Number of Cash Drawers | C85: 2
B87: Amount of Each Drawer | C87: 200
B89: Amount of Petty Cash | C89: 300
B91: Period11
B92: Sun 10-4 | C92: 120 | D92: 2774 | E92: Rg | F92: we owed p10 $2774 | H92: 117.78 | I92: =H92-C92 -> -2.22
B93: Mon 10-5 | C93: 100 | D93: 0 | E93: Rg | H93: 99.76 | I93: =H93-C93 -> -0.24
B94: Tue 10-6 | C94: 120 | D94: 0 | E94: rg | H94: 116.87 | I94: =H94-C94 -> -3.13
B95: Wed 10-7 | C95: 80 | D95: 0 | E95: Rg | H95: 76.49 | I95: =H95-C95 -> -3.51
B96: Thu 10-8 | C96: 0 | D96: 0 | E96: Rg. | H96: 2.42 | I96: =H96-C96 -> 2.42
B97: Fri 10-9 | C97: 0 | D97: 0 | E97: Rg | H97: 67.71 | I97: =H97-C97 -> 67.71
B98: Sat 10-10 | C98: 100 | D98: 0 | E98: Rg | H98: 33.72 | I98: =H98-C98 -> -66.28
B99: Total Week | C99: =SUM(C92:C98) -> 520 | D99: =SUM(D92:D98) -> 2774 | H99: =SUM(H92:H98) -> 514.75 | I99: =SUM(I92:I98) -> -5.25
B100: Sun 10-11 | C100: 0 | D100: 0 | H100: 0 | I100: =H100-C100 -> 0
B101: Mon 10-12 | C101: 0 | D101: 0 | H101: 0 | I101: =H101-C101 -> 0
B102: Tue 10-13 | C102: 0 | D102: 0 | H102: 0 | I102: =H102-C102 -> 0
B103: Wed 10-14 | C103: 0 | D103: 0 | H103: 0 | I103: =H103-C103 -> 0
B104: Thu 10-15 | C104: 0 | D104: 0 | H104: 0 | I104: =H104-C104 -> 0
B105: Fri 10-16 | C105: 0 | D105: 0 | H105: 0 | I105: =H105-C105 -> 0
B106: Sat 10-17 | C106: 0 | D106: 0 | H106: 0 | I106: =H106-C106 -> 0
B107: Total Week | C107: =SUM(C100:C106) -> 0 | D107: =SUM(D100:D106) -> 0 | H107: =SUM(H100:H106) -> 0 | I107: =SUM(I100:I106) -> 0
B108: Sun 10-18 | C108: 0 | D108: 0 | H108: 0 | I108: =H108-C108 -> 0
...

Sheet ST
C1: South Torrance
C3: Chage Order Deposits | D3: Change Order Received | E3: Initials | F3: Comments | H3: Cash over/ (Short) per R365 Flash report | I3: True Over/ (Short)
B4: =Control!$B$3 -> 46243 | C4: 0 | D4: 0 | I4: =H4-C4 -> 0
B5: =B4+1 -> 46244 | C5: 675 | D5: 0 | I5: =H5-C5 -> -675
B6: =B5+1 -> 46245 | C6: 0 | D6: 580 | I6: =H6-C6 -> 0
B7: =B6+1 -> 46246 | C7: 0 | D7: 0 | I7: =H7-C7 -> 0
B8: =B7+1 -> 46247 | C8: 0 | D8: 0 | I8: =H8-C8 -> 0
B9: =B8+1 -> 46248 | C9: 0 | D9: 0 | I9: =H9-C9 -> 0
B10: =B9+1 -> 46249 | C10: 0 | D10: 0 | I10: =H10-C10 -> 0
B11: Total Week | C11: =SUM(C4:C10) -> 675 | D11: =SUM(D4:D10) -> 580 | H11: =SUM(H4:H10) -> 0 | I11: =SUM(I4:I10) -> -675
B12: =B10+1 -> 46250 | C12: 0 | D12: 0 | I12: =H12-C12 -> 0
B13: =B12+1 -> 46251 | C13: 0 | D13: 0 | I13: =H13-C13 -> 0
B14: =B13+1 -> 46252 | C14: 0 | D14: 0 | I14: =H14-C14 -> 0
B15: =B14+1 -> 46253 | C15: 0 | D15: 600 | I15: =H15-C15 -> 0
B16: =B15+1 -> 46254 | C16: 580 | D16: 0 | I16: =H16-C16 -> -580
B17: =B16+1 -> 46255 | C17: 450 | D17: 0 | I17: =H17-C17 -> -450
B18: =B17+1 -> 46256 | C18: 0 | D18: 705 | I18: =H18-C18 -> 0
B19: Total Week | C19: =SUM(C12:C18) -> 1030 | D19: =SUM(D12:D18) -> 1305 | H19: =SUM(H12:H18) -> 0 | I19: =SUM(I12:I18) -> -1030
B20: =B18+1 -> 46257 | C20: 150 | D20: 0 | I20: =H20-C20 -> -150
B21: =B20+1 -> 46258 | C21: 0 | D21: 0 | H21: 6 | I21: 6.08
B22: =B21+1 -> 46259 | C22: 0 | D22: 0 | H22: -4 | I22: -4.32
B23: =B22+1 -> 46260 | C23: 0 | D23: 0 | H23: -5 | I23: -5.06
B24: =B23+1 -> 46261 | C24: 0 | D24: 0 | H24: 15 | I24: 15.463
B25: =B24+1 -> 46262 | C25: 0 | D25: 0 | H25: 7 | I25: =7.26 -> 7.26
B26: =B25+1 -> 46263 | C26: 0 | D26: 0 | E26: jp | H26: -27 | I26: -27
B27: Total Week | C27: =SUM(C20:C26) -> 150 | D27: =SUM(D20:D26) -> 0 | E27: jp | H27: =SUM(H20:H26) -> -8 | I27: =SUM(I20:I26) -> -157.577
B28: =B26+1 -> 46264 | C28: 0 | D28: 0 | E28: jp | H28: -16 | I28: -15.99
B29: =B28+1 -> 46265 | C29: 0 | D29: 0 | E29: jp | H29: -3 | I29: -2.7
B30: =B29+1 -> 46266 | C30: 0 | D30: 800 | E30: jp | H30: -9 | I30: -9
B31: =B30+1 -> 46267 | C31: 705 | D31: 0 | E31: jp | H31: 9 | I31: =H31-C31 -> -696
B32: =B31+1 -> 46268 | C32: 0 | D32: 0 | E32: jp | H32: -13 | I32: -12.94
B33: =B32+1 -> 46269 | C33: 0 | D33: 0 | E33: jp | H33: -24 | I33: -23.99
H34: 25 | I34: 24.99
B35: =B33+1 -> 46270 | C35: 0 | D35: 0 | E35: jp | H35: -24 | I35: =H35-C35 -> -24
B36: Total Week | C36: =SUM(C28:C35) -> 705 | D36: =SUM(D28:D35) -> 800 | H36: =SUM(H28:H35) -> -55 | I36: =SUM(I28:I35) -> -759.63
B37: Total Period | C37: =SUM(C36+C27+C19+C11) -> 2560 | D37: =SUM(D36+D27+D19+D11) -> 2685 | H37: =SUM(H36+H27+H19+H11) -> -63 | I37: =SUM(I36+I27+I19+I11) -> -2622.207
B38: Period Activity | C38: =D37+C37 -> 5245 | H38: =I37+H37 -> -2685.207 | I38: =J37+I37 -> -2622.207
C39: =B35+1 -> 46271 | D39: After Period Close
B40: Ending Period Count of Amount on hand | C40: 800 | E40: IA
B42: Number of Cash Drawers | C42: 2
B44: Amount of Each Drawer | C44: 200
B46: Amount of Petty Cash | C46: 300
B48: Period10
B49: Sun 9-6 | C49: 0 | D49: 0 | E49: jp | H49: 2 | I49: =H49-C49 -> 2
B50: Mon 9-7 | C50: 0 | D50: 0 | E50: jp | H50: -12 | I50: =H50-C50 -> -12
B51: Tue 9-8 | C51: 0 | D51: 0 | E51: jp | H51: 1 | I51: =H51-C51 -> 1
B52: Wed 9-9 | C52: 0 | D52: 400 | E52: ia | F52: Money recieved Wed ordered Sun 9/6 | H52: 7 | I52: =H52-C52 -> 7
B53: Thu 9-10 | C53: 800 | D53: 0 | E53: ia | F53: Paid Change order back | H53: 805 | I53: =H53-C53 -> 5
B54: Fri 9-11 | C54: 0 | D54: 0 | E54: ia | H54: 3 | I54: =H54-C54 -> 3
B55: Sat 9-12 | C55: 0 | D55: 0 | E55: ia | H55: 2 | I55: =H55-C55 -> 2
B56: Total Week | C56: =SUM(C49:C55) -> 800 | D56: =SUM(D49:D55) -> 400 | H56: =SUM(H49:H55) -> 808 | I56: =SUM(I49:I55) -> 8
B57: Sun 9-13 | C57: 0 | D57: 0 | E57: jp | H57: -14 | I57: =H57-C57 -> -14
B58: Mon 9-14 | C58: 0 | D58: 0 | E58: jp | H58: -18 | I58: =H58-C58 -> -18
B59: Tue 9-15 | C59: 0 | D59: 700 | E59: jp | F59: Hipo did not pick up tips. Money Recieved on tuesday ordered 9/13 | H59: 96 | I59: =H59-C59 -> 96
B60: Wed 9-16 | C60: 400 | D60: 0 | E60: ia | F60: Money short from yesterday Paid Hippo | H60: 305 | I60: =H60-C60 -> -95
B61: Thu 9-17 | C61: 0 | D61: 0 | E61: ia | H61: -8 | I61: =H61-C61 -> -8
B62: Fri 9-18 | C62: 0 | D62: 0 | E62: ia | H62: -13 | I62: =H62-C62 -> -13
B63: Sat 9-19 | C63: 0 | D63: 0 | E63: ia | F63: Over 35 | H63: 35 | I63: =H63-C63 -> 35
B64: Total Week | C64: =SUM(C57:C63) -> 400 | D64: =SUM(D57:D63) -> 700 | H64: =SUM(H57:H63) -> 383 | I64: =SUM(I57:I63) -> -17
B65: Sun 9-20 | C65: 0 | D65: 0 | E65: ia | F65: Short 37 from yestday real is $2+ | H65: -37 | I65: =H65-C65 -> -37
B66: Mon 9-21 | C66: 0 | D66: 0 | E66: JP | H66: 3 | I66: =H66-C66 -> 3
B67: Tue 9-22 | C67: 0 | D67: 0 | E67: JP | H67: 31 | I67: =H67-C67 -> 31
B68: Wed 9-23 | C68: 0 | D68: 0 | E68: jp | F68: Zero Cash Over Short. | H68: 0 | I68: =H68-C68 -> 0
B69: Thu 9-24 | C69: 0 | D69: 0 | E69: ia | F69: Under investigation | H69: -95 | I69: =H69-C69 -> -95
B70: Fri 9-25 | C70: 0 | D70: 700 | E70: ia | F70: Ripped 20$ actual short | H70: -22 | I70: =H70-C70 -> -22
B71: Sat 9-26 | C71: 700 | D71: 0 | E71: ia | F71: Dropped change order | H71: 745 | I71: =H71-C71 -> 45
B72: Total Week | C72: =SUM(C65:C71) -> 700 | D72: =SUM(D65:D71) -> 700 | H72: =SUM(H65:H71) -> 625 | I72: =SUM(I65:I71) -> -75
B73: Sun 9-27 | C73: 0 | D73: 0 | E73: jp | H73: -30.47 | I73: =H73-C73 -> -30.47
B74: Mon 9-28 | C74: 0 | D74: 0 | E74: jp | H74: -13 | I74: =H74-C74 -> -13
B75: Tue 9-29 | C75: 0 | D75: 0 | E75: jp | H75: -38 | I75: =H75-C752 -> -38
B76: Wed 9-30 | C76: 0 | D76: 0 | E76: ia | H76: 18 | I76: =H76-C76 -> 18
B77: Thu 10-1 | C77: 0 | D77: 0 | E77: ia | H77: 44.32 | I77: =H77-C77 -> 44.32
B78: Fri 10-2 | C78: 0 | D78: 0 | E78: ia | H78: -39 | I78: =H78-C78 -> -39
B79: Sat 10-3 | D79: 0 | E79: jp | H79: 1 | I79: =H79-C79 -> 1
B80: Total Week | C80: =SUM(C73:C79) -> 0 | D80: =SUM(D73:D79) -> 0 | H80: =SUM(H73:H79) -> -57.15 | I80: =SUM(I73:I79) -> -57.15
B81: Total Period | C81: =SUM(C80+C72+C64+C56) -> 1900 | D81: =SUM(D80+D72+D64+D56) -> 1800 | H81: =SUM(H80+H72+H64+H56) -> 1758.85 | I81: =SUM(I80+I72+I64+I56) -> -141.15
B82: Period Activity | C82: =D81+C81 -> 3700 | H82: =I81+H81 -> 1617.7 | I82: =J81+I81 -> -141.15
C83: Sun 10-4 | D83: After Period Close
B84: Ending Period Count of Amopunt on hand | C84: 700 | E84: IA
B86: Number of Cash Drawers | C86: 2
B88: Amount of Each Drawer | C88: 200
B90: Amount of Petty Cash | C90: 300
B92: Period11
B93: Sun 10-4 | C93: 0 | D93: 0 | E93: jp | F93: R365 not pulling from Aloha manuelly calculated | H93: 129.4 | I93: =H93-C93 -> 129.4
B94: Mon 10-5 | C94: 0 | D94: 0 | E94: jp | F94: R365 not pulling from Aloha manuelly calculated | H94: 5.3 | I94: =H94-C94 -> 5.3
B95: Tue 10-6 | C95: 0 | D95: 725 | E95: jp | F95: Change order recieved during PM Shift | H95: -1.17 | I95: =H95-C95 -> -1.17
B96: Wed 10-7 | C96: 700 | D96: 0 | E96: jp | F96: Change order paid back (left blank, inputed on 10/09 | H96: 691 | I96: =H96-C96 -> -9
B97: Thu 10-8 | C97: 0 | D97: 0 | E97: ia | F97: Under investigation over on sunday (manuelly calculted waiting on r365 | H97: -82 | I97: =H97-C97 -> -82
B98: Fri 10-9 | C98: 0 | D98: 0 | E98: ia | F98: Over 10 | H98: 10 | I98: =H98-C98 -> 10 | L98: 6+5+654
B99: Sat 10-10 | C99: 0 | D99: 0 | E99: jp | H99: 3.53 | I99: =H99-C99 -> 3.53
B100: Total Week | C100: =SUM(C93:C99) -> 700 | D100: =SUM(D93:D99) -> 725 | H100: =SUM(H93:H99) -> 756.06 | I100: =SUM(I93:I99) -> 56.06
B101: Sun 10-11 | C101: 0 | D101: 0 | E101: jp | H101: 45.34 | I101: =H101-C101 -> 45.34
B102: Mon 10-12 | C102: 0 | D102: 0 | H102: 0 | I102: =H102-C102 -> 0
B103: Tue 10-13 | C103: 0 | D103: 0 | H103: 0 | I103: =H103-C103 -> 0
B104: Wed 10-14 | C104: 0 | D104: 0 | H104: 0 | I104: =H104-C104 -> 0
B105: Thu 10-15 | C105: 0 | D105: 0 | H105: 0 | I105: =H105-C105 -> 0
B106: Fri 10-16 | C106: 0 | D106: 0 | H106: 0 | I106: =H106-C106 -> 0
B107: Sat 10-17 | C107: 0 | D107: 0 | H107: 0 | I107: =H107-C107 -> 0
B108: Total Week | C108: =SUM(C101:C107) -> 0 | D108: =SUM(D101:D107) -> 0 | H108: =SUM(H101:H107) -> 45.34 | I108: =SUM(I101:I107) -> 45.34
B109: Sun 10-18 | C109: 0 | D109: 0 | H109: 0 | I109: =H109-C109 -> 0
...

Sheet TO
C1: North Torrance
C2: Per Restaurant
C3: Chage Order Deposits | D3: Change Order Received | E3: Initials | F3: Comments | H3: Cash over/ (Short) per R365 Flash report | I3: True Over/ (Short)
B4: =Control!$B$3 -> 46243 | C4: -500 | D4: 0 | E4: JA | I4: =H4-C4 -> 500
B5: =B4+1 -> 46244 | C5: 0 | D5: 0 | I5: =H5-C5 -> 0
B6: =B5+1 -> 46245 | C6: 0 | D6: 0 | I6: =H6-C6 -> 0
B7: =B6+1 -> 46246 | C7: -1070 | D7: 2570 | E7: JA | I7: =H7-C7 -> 1070
B8: =B7+1 -> 46247 | C8: 0 | D8: 0 | I8: =H8-C8 -> 0
B9: =B8+1 -> 46248 | C9: -500 | D9: 0 | E9: JA | I9: =H9-C9 -> 500
B10: =B9+1 -> 46249 | C10: -500 | D10: 0 | E10: KG | I10: =H10-C10 -> 500
B11: Total Week | C11: =SUM(C4:C10) -> -2570 | D11: =SUM(D4:D10) -> 2570 | H11: =SUM(H4:H10) -> 0 | I11: =SUM(I4:I10) -> 2570
B12: =B10+1 -> 46250 | C12: -500 | D12: 0 | E12: JA | I12: =H12-C12 -> 500
B13: =B12+1 -> 46251 | C13: 0 | D13: 0 | I13: =H13-C13 -> 0
B14: =B13+1 -> 46252 | C14: 0 | D14: 2550 | E14: KG | I14: =H14-C14 -> 0
B15: =B14+1 -> 46253 | C15: -500 | D15: 0 | E15: JA | I15: =H15-C15 -> 500
B16: =B15+1 -> 46254 | C16: 0 | D16: 0 | I16: =H16-C16 -> 0
B17: =B16+1 -> 46255 | C17: -500 | D17: 0 | E17: JA | I17: =H17-C17 -> 500
B18: =B17+1 -> 46256 | C18: -500 | D18: 0 | E18: KG | I18: =H18-C18 -> 500
B19: Total Week | C19: =SUM(C12:C18) -> -2000 | D19: =SUM(D12:D18) -> 2550 | H19: =SUM(H12:H18) -> 0 | I19: =SUM(I12:I18) -> 2000
B20: =B18+1 -> 46257 | C20: 0 | D20: 0 | I20: =H20-C20 -> 0
B21: =B20+1 -> 46258 | C21: -500 | D21: 0 | E21: KG | I21: =H21-C21 -> 500
B22: =B21+1 -> 46259 | C22: 0 | D22: 2570 | E22: KG | I22: =H22-C22 -> 0
B23: =B22+1 -> 46260 | C23: 0 | D23: 0 | I23: =H23-C23 -> 0
B24: =B23+1 -> 46261 | C24: -145 | D24: 0 | E24: JA | I24: =H24-C24 -> 145
B25: =B24+1 -> 46262 | C25: 0 | D25: 0 | I25: =H25-C25 -> 0
B26: =B25+1 -> 46263 | C26: 0 | D26: 0 | I26: =H26-C26 -> 0
B27: Total Week | C27: =SUM(C20:C26) -> -645 | D27: =SUM(D20:D26) -> 2570 | H27: =SUM(H20:H26) -> 0 | I27: =SUM(I20:I26) -> 645
B28: =B26+1 -> 46264 | C28: -500 | D28: 0 | E28: KG | I28: =H28-C28 -> 500
B29: =B28+1 -> 46265 | C29: -500 | D29: 0 | E29: KG | I29: =H29-C29 -> 500
B30: =B29+1 -> 46266 | C30: 0 | D30: 0 | I30: =H30-C30 -> 0
B31: =B30+1 -> 46267 | C31: 0 | D31: 0 | I31: =H31-C31 -> 0
B32: =B31+1 -> 46268 | C32: 0 | D32: 0 | I32: =H32-C32 -> 0
B33: =B32+1 -> 46269 | C33: 0 | D33: 0 | I33: =H33-C33 -> 0
B34: =B33+1 -> 46270 | C34: -500 | D34: 0 | E34: JA | I34: =H34-C34 -> 500
B35: Total Week | C35: =SUM(C28:C34) -> -1500 | D35: =SUM(D28:D34) -> 0 | H35: =SUM(H28:H34) -> 0 | I35: =SUM(I28:I34) -> 1500
B36: Total Period | C36: =SUM(C35+C27+C19+C11) -> -6715 | D36: =SUM(D35+D27+D19+D11) -> 7690 | H36: =SUM(H35+H27+H19+H11) -> 0 | I36: =SUM(I35+I27+I19+I11) -> 6715
B37: Period Activity | C37: =D36+C36 -> 975 | H37: =I36+H36 -> 6715 | I37: =J36+I36 -> 6715
C38: =B34+1 -> 46271 | D38: After Period Close
B39: Ending Period Count of Amount on hand | C39: 2000 | E39: JA
B41: Number of Cash Drawers | C41: 2
B43: Amount of Each Drawer | C43: 200
B45: Amount of Petty Cash | C45: 300
B47: Period10
B48: Sun 9-6 | C48: 500 | D48: 0 | E48: JA | F48: $500 change order | H48: 693 | I48: =H48-C48 -> 193
B49: Mon 9-7 | C49: 0 | D49: 0 | E49: KG | F49: $121 tips pulled from dinner after register count | H49: -154 | I49: =H49-C49 -> -154
B50: Tue 9-8 | C50: 500 | D50: 0 | E50: KG | F50: $500 change order | H50: 479 | I50: =H50-C50 -> -21
B51: Wed 9-9 | C51: 0 | D51: 0 | E51: JA | H51: 47 | I51: =H51-C51 -> 47
B52: Thu 9-10 | C52: 0 | D52: 0 | E52: JA | H52: 7 | I52: =H52-C52 -> 7
B53: Fri 9-11 | C53: 0 | D53: 0 | E53: JA | H53: -170 | I53: =H53-C53 -> -170
B54: Sat 9-12 | C54: 500 | D54: 0 | E54: KG | F54: $500 change order | H54: 718 | I54: =H54-C54 -> 218
B55: Total Week | C55: =SUM(C48:C54) -> 1500 | D55: =SUM(D48:D54) -> 0 | H55: =SUM(H48:H54) -> 1620 | I55: =SUM(I48:I54) -> 120
B56: Sun 9-13 | C56: 0 | D56: 0 | E56: JA | H56: 46 | I56: =H56-C56 -> 46
B57: Mon 9-14 | C57: 0 | D57: 0 | E57: KG | H57: 37 | I57: =H57-C57 -> 37
B58: Tue 9-15 | C58: 0 | D58: 0 | E58: KG | H58: 19 | I58: =H58-C58 -> 19
B59: Wed 9-16 | C59: 0 | D59: 0 | E59: JA | H59: 13 | I59: =H59-C59 -> 13
B60: Thu 9-17 | C60: 0 | D60: 0 | E60: JA | H60: 28 | I60: =H60-C60 -> 28
B61: Fri 9-18 | C61: 0 | D61: 2945 | E61: JA | F61: Brinks Delivery | H61: -17 | I61: =H61-C61 -> -17
B62: Sat 9-19 | C62: 0 | D62: 0 | E62: JA | F62: GY tips left drawer with $150 in total plus olo tips $17 not paid | H62: 63 | I62: =H62-C62 -> 63
B63: Total Week | C63: =SUM(C56:C62) -> 0 | D63: =SUM(D56:D62) -> 2945 | H63: =SUM(H56:H62) -> 189 | I63: =SUM(I56:I62) -> 189
B64: Sun 9-20 | C64: 500 | E64: KG | F64: $500 change order | H64: 520 | I64: =H64-C64 -> 20
B65: Mon 9-21 | C65: 0 | D65: 0 | E65: KG | H65: 2 | I65: =H65-C65 -> 2
B66: Tue 9-22 | C66: 500 | D66: 0 | E66: KG | F66: $257 dropped at 7:45am 9/23 goes to 9/22/2026 $500 change | H66: 108 | I66: =H66-C66 -> -392
B67: Wed 9-23 | C67: 0 | D67: 0 | E67: JA | H67: 259 | I67: =H67-C67 -> 259
B68: Thu 9-24 | C68: 500 | D68: 0 | E68: JA | F68: $500 change order | H68: 503 | I68: =H68-C68 -> 3
B69: Fri 9-25 | C69: 0 | D69: 0 | H69: 23 | I69: =H69-C69 -> 23
B70: Sat 9-26 | C70: 500 | D70: 0 | E70: JA | F70: $500 change order | H70: 478 | I70: =H70-C70 -> -22
B71: Total Week | C71: =SUM(C64:C70) -> 2000 | D71: =SUM(D64:D70) -> 0 | H71: =SUM(H64:H70) -> 1893 | I71: =SUM(I64:I70) -> -107
B72: Sun 9-27 | C72: 500 | D72: 0 | E72: KG | F72: Change order | H72: 452 | I72: =H72-C72 -> -48
B73: Mon 9-28 | C73: 0 | D73: 0 | E73: kg | H73: -9 | I73: =H73-C73 -> -9
B74: Tue 9-29 | C74: 0 | D74: 0 | E74: kg | H74: 3 | I74: =H74-C74 -> 3
B75: Wed 9-30 | C75: 0 | D75: 0 | E75: kg | H75: 15 | I75: =H75-C75 -> 15
B76: Thu 10-1 | C76: 0 | D76: 0 | E76: kg | H76: -397 | I76: =H76-C76 -> -397
B77: Fri 10-2 | C77: 1000 | D77: 2500 | E77: KG | F77: $1000.00 dropped/ $2500.00 rec. | H77: 1015 | I77: =H77-C77 -> 15
B78: Sat 10-3 | D78: 0 | E78: KG | H78: 28 | I78: =H78-C78 -> 28
B79: Total Week | C79: =SUM(C72:C78) -> 1500 | D79: =SUM(D72:D78) -> 2500 | H79: =SUM(H72:H78) -> 1107 | I79: =SUM(I72:I78) -> -393
B80: Total Period | C80: =SUM(C79+C71+C63+C55) -> 5000 | D80: =SUM(D79+D71+D63+D55) -> 5445 | H80: =SUM(H79+H71+H63+H55) -> 4809 | I80: =SUM(I79+I71+I63+I55) -> -191
B81: Period Activity | C81: =D80+C80 -> 10445 | H81: =I80+H80 -> 4618 | I81: =J80+I80 -> -191
C82: Sun 10-4 | D82: After Period Close
B83: Ending Period Count of Amopunt on hand
B85: Number of Cash Drawers
B87: Amount of Each Drawer
B89: Amount of Petty Cash
B91: Period11
B92: Sun 10-4 | C92: 0 | D92: 0 | H92: 0 | I92: =H92-C92 -> 0
B93: Mon 10-5 | C93: 500 | D93: 0 | E93: kg | F93: $500 change order | H93: 0 | I93: =H93-C93 -> -500
B94: Tue 10-6 | C94: 0 | D94: 0 | H94: 0 | I94: =H94-C94 -> 0
B95: Wed 10-7 | C95: 0 | D95: 0 | H95: 0 | I95: =H95-C95 -> 0
B96: Thu 10-8 | C96: 500 | D96: 0 | E96: JA | F96: $500 change order | H96: 0 | I96: =H96-C96 -> -500
B97: Fri 10-9 | C97: 0 | D97: 0 | H97: 0 | I97: =H97-C97 -> 0
B98: Sat 10-10 | C98: 0 | D98: 0 | H98: 0 | I98: =H98-C98 -> 0
B99: Total Week | C99: =SUM(C92:C98) -> 1000 | D99: =SUM(D92:D98) -> 0 | H99: =SUM(H92:H98) -> 0 | I99: =SUM(I92:I98) -> -1000
B100: Sun 10-11 | C100: 0 | D100: 0 | H100: 0 | I100: =H100-C100 -> 0
B101: Mon 10-12 | C101: 0 | D101: 0 | H101: 0 | I101: =H101-C101 -> 0
B102: Tue 10-13 | C102: 0 | D102: 0 | H102: 0 | I102: =H102-C102 -> 0
B103: Wed 10-14 | C103: 0 | D103: 0 | H103: 0 | I103: =H103-C103 -> 0
B104: Thu 10-15 | C104: 0 | D104: 0 | H104: 0 | I104: =H104-C104 -> 0
B105: Fri 10-16 | C105: 0 | D105: 0 | H105: 0 | I105: =H105-C105 -> 0
B106: Sat 10-17 | C106: 0 | D106: 0 | H106: 0 | I106: =H106-C106 -> 0
B107: Total Week | C107: =SUM(C100:C106) -> 0 | D107: =SUM(D100:D106) -> 0 | H107: =SUM(H100:H106) -> 0 | I107: =SUM(I100:I106) -> 0
B108: Sun 10-18 | C108: 0 | D108: 0 | H108: 0 | I108: =H108-C108 -> 0
...

Sheet VN
C1: Van Nuys
C2: Per Restaurant
C3: Chage Order Deposits | D3: Change Order Received | E3: Initials | F3: Comments | H3: Cash over/ (Short) per R365 Flash report | I3: True Over/ (Short)
B4: =Control!$B$3 -> 46243 | C4: 0 | D4: 1970 | E4: MM | H4: -156 | I4: =H4-C4 -> -156
B5: =B4+1 -> 46244 | C5: 0 | D5: 0 | H5: -2 | I5: =H5-C5 -> -2
B6: =B5+1 -> 46245 | C6: 0 | D6: 0 | H6: 17 | I6: =H6-C6 -> 17
B7: =B6+1 -> 46246 | C7: 0 | D7: 0 | H7: 25 | I7: =H7-C7 -> 25
B8: =B7+1 -> 46247 | C8: 0 | D8: 0 | H8: 39 | I8: =H8-C8 -> 39
B9: =B8+1 -> 46248 | C9: 0 | D9: 0 | H9: -1 | I9: =H9-C9 -> -1
B10: =B9+1 -> 46249 | C10: 0 | D10: 2325 | E10: MM | H10: -5 | I10: =H10-C10 -> -5
B11: Total Week | C11: =SUM(C4:C10) -> 0 | D11: =SUM(D4:D10) -> 4295 | H11: =SUM(H4:H10) -> -83 | I11: =SUM(I4:I10) -> -83
B12: =B10+1 -> 46250 | C12: 0 | D12: 0 | H12: -7 | I12: =H12-C12 -> -7
B13: =B12+1 -> 46251 | C13: 1970 | D13: 0 | E13: BC | H13: 1969 | I13: =H13-C13 -> -1
B14: =B13+1 -> 46252 | C14: 0 | D14: 0 | H14: -11 | I14: =H14-C14 -> -11
B15: =B14+1 -> 46253 | C15: 0 | D15: 0 | H15: -24 | I15: =H15-C15 -> -24
B16: =B15+1 -> 46254 | C16: 0 | D16: 0 | H16: -9 | I16: =H16-C16 -> -9
B17: =B16+1 -> 46255 | C17: 0 | D17: 0 | H17: -22 | I17: =H17-C17 -> -22
B18: =B17+1 -> 46256 | C18: 0 | D18: 0 | H18: 15 | I18: =H18-C18 -> 15
B19: Total Week | C19: =SUM(C12:C18) -> 1970 | D19: =SUM(D12:D18) -> 0 | H19: =SUM(H12:H18) -> 1911 | I19: =SUM(I12:I18) -> -59
B20: =B18+1 -> 46257 | C20: 0 | D20: 0 | H20: 0 | I20: =H20-C20 -> 0
B21: =B20+1 -> 46258 | C21: -2325 | D21: 2840 | E21: BC | H21: -9 | I21: =H21-C21 -> 2316
B22: =B21+1 -> 46259 | C22: 0 | D22: 0 | H22: 0 | I22: =H22-C22 -> 0
B23: =B22+1 -> 46260 | C23: 0 | D23: 0 | H23: -23 | I23: =H23-C23 -> -23
B24: =B23+1 -> 46261 | C24: 0 | D24: 0 | H24: -17 | I24: =H24-C24 -> -17
B25: =B24+1 -> 46262 | C25: 0 | D25: 0 | H25: -21 | I25: =H25-C25 -> -21
B26: =B25+1 -> 46263 | C26: 0 | D26: 0 | H26: -24 | I26: =H26-C26 -> -24
B27: Total Week | C27: =SUM(C20:C26) -> -2325 | D27: =SUM(D20:D26) -> 2840 | H27: =SUM(H20:H26) -> -94 | I27: =SUM(I20:I26) -> 2231
B28: =B26+1 -> 46264 | C28: 0 | D28: 0 | H28: -6 | I28: =H28-C28 -> -6
B29: =B28+1 -> 46265 | C29: 0 | D29: 0 | H29: -24 | I29: =H29-C29 -> -24
B30: =B29+1 -> 46266 | C30: 0 | D30: 0 | H30: 5 | I30: =H30-C30 -> 5
B31: =B30+1 -> 46267 | C31: 0 | D31: 0 | H31: -22 | I31: =H31-C31 -> -22
B32: =B31+1 -> 46268 | C32: 0 | D32: 0 | H32: -21 | I32: =H32-C32 -> -21
B33: =B32+1 -> 46269 | C33: -2840 | D33: 2445 | E33: MM | H33: 2792 | I33: =H33-C33 -> 5632
B34: =B33+1 -> 46270 | C34: 0 | D34: 0 | H34: -23 | I34: =H34-C34 -> -23
B35: Total Week | C35: =SUM(C28:C34) -> -2840 | D35: =SUM(D28:D34) -> 2445 | H35: =SUM(H28:H34) -> 2701 | I35: =SUM(I28:I34) -> 5541
B36: Total Period | C36: =SUM(C35+C27+C19+C11) -> -3195 | D36: =SUM(D35+D27+D19+D11) -> 9580 | H36: =SUM(H35+H27+H19+H11) -> 4435 | I36: =SUM(I35+I27+I19+I11) -> 7630
B37: Period Activity | C37: =D36+C36 -> 6385 | H37: =I36+H36 -> 12065 | I37: =J36+I36 -> 7630
C38: =B34+1 -> 46271 | D38: After Period Close
B39: Ending Period Count of Amount on hand | C39: 2445 | F39: Mark, Fresly, Brian
B41: Number of Cash Drawers | C41: 2
B43: Amount of Each Drawer | C43: 200
B45: Amount of Petty Cash | C45: 300
B47: Period10
B48: Sun 9-6 | C48: 0 | D48: 0 | H48: -13 | I48: =H48-C48 -> -13
B49: Mon 9-7 | C49: 0 | D49: 0 | H49: -29 | I49: =H49-C49 -> -29
B50: Tue 9-8 | C50: 0 | D50: 0 | H50: =5 -> 5 | I50: =H50-C50 -> 5
B51: Wed 9-9 | C51: 0 | D51: 0 | H51: -23 | I51: =H51-C51 -> -23
B52: Thu 9-10 | C52: 0 | D52: 0 | H52: -22 | I52: =H52-C52 -> -22
B53: Fri 9-11 | C53: 2445 | D53: 1825 | F53: Recievechange order today | H53: 2510 | I53: =H53-C53 -> 65
B54: Sat 9-12 | C54: 0 | D54: 0 | H54: -81 | I54: =H54-C54 -> -81
B55: Total Week | C55: =SUM(C48:C54) -> 2445 | D55: =SUM(D48:D54) -> 1825 | H55: =SUM(H48:H54) -> 2347 | I55: =SUM(I48:I54) -> -98
B56: Sun 9-13 | C56: 0 | D56: 0 | E56: FV | H56: 2 | I56: =H56-C56 -> 2
B57: Mon 9-14 | C57: 0 | D57: 0 | E57: BC | H57: 1 | I57: =H57-C57 -> 1
B58: Tue 9-15 | C58: 0 | D58: 0 | E58: BC | H58: -6 | I58: =H58-C58 -> -6
B59: Wed 9-16 | C59: 0 | D59: 0 | E59: MM | F59: Drop money late reflect the next day | H59: -275 | I59: =H59-C59 -> -275
B60: Thu 9-17 | C60: 0 | D60: 0 | E60: MM | H60: 212 | I60: =H60-C60 -> 212
B61: Fri 9-18 | C61: 0 | D61: 0 | E61: MM | H61: -6 | I61: =H61-C61 -> -6
B62: Sat 9-19 | C62: 0 | D62: 0 | E62: MM | F62: No Change order this week | H62: 165 | I62: =H62-C62 -> 165
B63: Total Week | C63: =SUM(C56:C62) -> 0 | D63: =SUM(D56:D62) -> 0 | H63: =SUM(H56:H62) -> 93 | I63: =SUM(I56:I62) -> 93
B64: Sun 9-20 | C64: 0 | E64: FV | F64: 2 UGLY $10 taht machine dint accept | H64: -231 | I64: =H64-C64 -> -231
B65: Mon 9-21 | C65: 0 | D65: 1970 | E65: FV | F65: recieve change order today | H65: 19 | I65: =H65-C65 -> 19
B66: Tue 9-22 | C66: 0 | D66: 0 | E66: FV | H66: 16 | I66: =H66-C66 -> 16
B67: Wed 9-23 | C67: 1825 | D67: 0 | E67: mm | H67: 1811 | I67: =H67-C67 -> -14
B68: Thu 9-24 | C68: 0 | D68: 0 | E68: mm | F68: 5 dollars refund for games. Had 1 refund for games total $8 | H68: -26 | I68: =H68-C68 -> -26
B69: Fri 9-25 | C69: 0 | D69: 0 | E69: mm | H69: -90 | I69: =H69-C69 -> -90
B70: Sat 9-26 | C70: 0 | D70: 0 | E70: mm | F70: Over from the day | H70: 198 | I70: =H70-C70 -> 198
B71: Total Week | C71: =SUM(C64:C70) -> 1825 | D71: =SUM(D64:D70) -> 1970 | H71: =SUM(H64:H70) -> 1697 | I71: =SUM(I64:I70) -> -128
B72: Sun 9-27 | C72: 0 | D72: 0 | E72: FV | H72: -5 | I72: =H72-C72 -> -5
B73: Mon 9-28 | C73: 0 | D73: 0 | E73: FV | H73: 32 | I73: =H73-C73 -> 32
B74: Tue 9-29 | C74: 0 | D74: 0 | E74: mm | H74: -2 | I74: =H74-C74 -> -2
B75: Wed 9-30 | C75: 0 | D75: 0 | E75: mm | F75: 90 dollars tip erro will replace when server pays back | H75: -348 | I75: =H75-C75 -> -348
B76: Thu 10-1 | C76: 0 | D76: 0 | H76: 14 | I76: =H76-C76 -> 14
B77: Fri 10-2 | D77: 2270 | E77: bc | H77: 122 | I77: =H77-C77 -> 122
B78: Sat 10-3 | C78: 1970 | D78: 0 | H78: 1916 | I78: =H78-C78 -> -54
B79: Total Week | C79: =SUM(C72:C78) -> 1970 | D79: =SUM(D72:D78) -> 2270 | H79: =SUM(H72:H78) -> 1729 | I79: =SUM(I72:I78) -> -241
B80: Total Period | C80: =SUM(C79+C71+C63+C55) -> 6240 | D80: =SUM(D79+D71+D63+D55) -> 6065 | H80: =SUM(H79+H71+H63+H55) -> 5866 | I80: =SUM(I79+I71+I63+I55) -> -374
B81: Period Activity | C81: =D80+C80 -> 12305 | H81: =I80+H80 -> 5492 | I81: =J80+I80 -> -374
C82: Sun 10-4 | D82: After Period Close
B83: Ending Period Count of Amopunt on hand | C83: 2270 | F83: Mark, Fresly, Brian
B85: Number of Cash Drawers | C85: 2
B87: Amount of Each Drawer | C87: 200
B89: Amount of Petty Cash | C89: 300
B91: Period11
B92: Sun 10-4 | C92: 0 | D92: 0 | E92: FV | H92: -5 | I92: =H92-C92 -> -5
B93: Mon 10-5 | C93: 0 | D93: 0 | E93: FV | H93: 8 | I93: =H93-C93 -> 8
B94: Tue 10-6 | C94: 0 | D94: 0 | E94: mm | H94: -13 | I94: =H94-C94 -> -13
B95: Wed 10-7 | C95: 0 | D95: 0 | E95: mm | H95: -19 | I95: =H95-C95 -> -19
B96: Thu 10-8 | C96: 0 | D96: 0 | E96: mm | H96: 48 | I96: =H96-C96 -> 48
B97: Fri 10-9 | C97: 2270 | D97: 2325 | E97: mm | H97: 2272 | I97: =H97-C97 -> 2
B98: Sat 10-10 | C98: 0 | D98: 0 | H98: 0 | I98: =H98-C98 -> 0
B99: Total Week | C99: =SUM(C92:C98) -> 2270 | D99: =SUM(D92:D98) -> 2325 | I99: =SUM(I92:I98) -> 21
B100: Sun 10-11 | C100: 0 | D100: 0
B101: Mon 10-12 | C101: 0 | D101: 0 | I101: =H101-C101 -> 0
B102: Tue 10-13 | C102: 0 | D102: 0 | H102: 0 | I102: =H102-C102 -> 0
B103: Wed 10-14 | C103: 0 | D103: 0 | H103: 0 | I103: =H103-C103 -> 0
B104: Thu 10-15 | C104: 0 | D104: 0 | H104: 0 | I104: =H104-C104 -> 0
B105: Fri 10-16 | C105: 0 | D105: 0 | H105: 0 | I105: =H105-C105 -> 0
B106: Sat 10-17 | C106: 0 | D106: 0 | H106: 0 | I106: =H106-C106 -> 0
B107: Total Week | C107: =SUM(C100:C106) -> 0 | D107: =SUM(D100:D106) -> 0 | H107: =SUM(H100:H106) -> 0 | I107: =SUM(I100:I106) -> 0
B108: Sun 10-18 | C108: 0 | D108: 0 | H108: 0 | I108: =H108-C108 -> 0
...

Sheet WC
C1: West Covina
C2: Per Restaurant
C3: Chage Order Deposits | D3: Change Order Received | E3: Initials | F3: Comments | H3: Cash over/ (Short) per R365 Flash report | I3: True Over/ (Short)
B4: =Control!$B$3 -> 46243 | C4: 0 | D4: 0 | E4: YZ/GV | H4: 3 | I4: =H4-C4 -> 3
B5: =B4+1 -> 46244 | C5: 0 | D5: 0 | E5: YZ/GV | H5: 12 | I5: =H5-C5 -> 12
B6: =B5+1 -> 46245 | C6: 0 | D6: 1055 | E6: GV | F6: Change Order Received | H6: 12.62 | I6: =H6-C6 -> 12.62
B7: =B6+1 -> 46246 | C7: 0 | D7: 0 | E7: YZ/GV | H7: -33.93 | I7: =H7-C7 -> -33.93
B8: =B7+1 -> 46247 | C8: 450 | D8: 0 | E8: YZ | F8: Change Order Paid | H8: 465.92 | I8: =H8-C8 -> 15.92
B9: =B8+1 -> 46248 | C9: 0 | D9: 0 | H9: 19.6 | I9: =H9-C9 -> 19.6
B10: =B9+1 -> 46249 | C10: 271 | D10: 0 | E10: YZ | F10: Change Order Paid | H10: 2.6 | I10: =H10-C10 -> -268.4
B11: Total Week | C11: =SUM(C4:C10) -> 721 | D11: =SUM(D4:D10) -> 1055 | H11: =SUM(H4:H10) -> 481.81 | I11: =SUM(I4:I10) -> -239.19
B12: =B10+1 -> 46250 | C12: 0 | D12: 0 | H12: 413.17 | I12: =H12-C12 -> 413.17
B13: =B12+1 -> 46251 | C13: 334 | D13: 0 | E13: GV | F13: Change Order Paid | H13: 176.1 | I13: =H13-C13 -> -157.9
B14: =B13+1 -> 46252 | C14: 0 | D14: 1055 | E14: GV | F14: Change Order Received | H14: 57.3 | I14: =H14-C14 -> 57.3
B15: =B14+1 -> 46253 | C15: 280 | D15: 0 | E15: YZ | F15: Change Order Paid | H15: 295.15 | I15: =H15-C15 -> 15.15
B16: =B15+1 -> 46254 | C16: 0 | D16: 0 | H16: 1.68 | I16: =H16-C16 -> 1.68
B17: =B16+1 -> 46255 | C17: 0 | D17: 0 | H17: 37.62 | I17: =H17-C17 -> 37.62
B18: =B17+1 -> 46256 | C18: 0 | D18: 0 | H18: -31.69 | I18: =H18-C18 -> -31.69
B19: Total Week | C19: =SUM(C12:C18) -> 614 | D19: =SUM(D12:D18) -> 1055 | H19: =SUM(H12:H18) -> 949.33 | I19: =SUM(I12:I18) -> 335.33
B20: =B18+1 -> 46257 | C20: 475 | D20: 0 | E20: YZ | F20: Change Order Paid | H20: 471.49 | I20: =H20-C20 -> -3.51
B21: =B20+1 -> 46258 | C21: 0 | D21: 0 | E21: YZ/GV | H21: 13.07 | I21: =H21-C21 -> 13.07
B22: =B21+1 -> 46259 | C22: 300 | D22: 995 | E22: GV/YZ | F22: Change Order Received | H22: 303.48 | I22: =H22-C22 -> 3.48
B23: =B22+1 -> 46260 | C23: 640 | D23: 0 | E23: YZ | F23: Change Order Paid | H23: 630.02 | I23: =H23-C23 -> -9.98
B24: =B23+1 -> 46261 | C24: 0 | D24: 0 | E24: YZ/GV | H24: -4.72 | I24: =H24-C24 -> -4.72
B25: =B24+1 -> 46262 | C25: 0 | D25: 0 | E25: YZ/GV | H25: 25.99 | I25: =H25-C25 -> 25.99
B26: =B25+1 -> 46263 | C26: 0 | D26: 0 | E26: YZ/GV | H26: 68.24 | I26: =H26-C26 -> 68.24
B27: Total Week | C27: =SUM(C20:C26) -> 1415 | D27: =SUM(D20:D26) -> 995 | H27: =SUM(H20:H26) -> 1507.57 | I27: =SUM(I20:I26) -> 92.57
B28: =B26+1 -> 46264 | C28: 355 | D28: 0 | E28: YZ | F28: Change Order Paid | H28: 307 | I28: =H28-C28 -> -48
B29: =B28+1 -> 46265 | C29: 0 | D29: 0 | H29: -13 | I29: =H29-C29 -> -13
B30: =B29+1 -> 46266 | C30: 0 | D30: 1130 | E30: GV | F30: Change Order Received | H30: 92 | I30: =H30-C30 -> 92
B31: =B30+1 -> 46267 | C31: 214 | D31: 0 | E31: YZ | F31: Change Order Paid | H31: 117 | I31: =H31-C31 -> -97
B32: =B31+1 -> 46268 | C32: 0 | D32: 0 | E32: YZ/GV | H32: -5 | I32: =H32-C32 -> -5
B33: =B32+1 -> 46269 | C33: 421 | D33: 0 | E33: YZ | F33: Change Order Paid | H33: 420 | I33: =H33-C33 -> -1
B34: =B33+1 -> 46270 | C34: 495 | D34: 0 | E34: YZ | F34: Change Order Paid | H34: 495 | I34: =H34-C34 -> 0
B35: Total Week | C35: =SUM(C28:C34) -> 1485 | D35: =SUM(D28:D34) -> 1130 | H35: =SUM(H28:H34) -> 1413 | I35: =SUM(I28:I34) -> -72
B36: Total Period | C36: =SUM(C35+C27+C19+C11) -> 4235 | D36: =SUM(D35+D27+D19+D11) -> 4235 | H36: =SUM(H35+H27+H19+H11) -> 4351.71 | I36: =SUM(I35+I27+I19+I11) -> 116.71
B37: Period Activity | C37: =D36+C36 -> 8470 | H37: =I36+H36 -> 4468.42 | I37: =J36+I36 -> 116.71
C38: =B34+1 -> 46271 | D38: After Period Close
B39: Ending Period Count of Amount on hand | C39: 0 | E39: YZ
B41: Number of Cash Drawers | C41: 2
B43: Amount of Each Drawer | C43: 200
B45: Amount of Petty Cash | C45: 300
B47: Period10
B48: Sun 9-6 | D48: 0 | E48: YZ | H48: 51 | I48: =H48-C48 -> 51
B49: Mon 9-7 | C49: 0 | D49: 0 | E49: YZ | F49: Short 0.21 per Aloha Report | H49: -0.21 | I49: =H49-C49 -> -0.21
B50: Tue 9-8 | C50: 0 | D50: 0 | E50: YZ/GV | H50: -2 | I50: =H50-C50 -> -2
B51: Wed 9-9 | C51: 0 | D51: 1129 | E51: YZ/GV | F51: Change Order Received | H51: 2 | I51: =H51-C51 -> 2
B52: Thu 9-10 | C52: 345 | D52: 0 | E52: YZ | F52: Change Order Paid | H52: 357 | I52: =H52-C52 -> 12
B53: Fri 9-11 | C53: 0 | D53: 0 | E53: YZ | H53: -2 | I53: =H53-C53 -> -2
B54: Sat 9-12 | C54: 180 | D54: 0 | E54: YZ | F54: Change Order Paid | H54: 126 | I54: =H54-C54 -> -54
B55: Total Week | C55: =SUM(C48:C54) -> 525 | D55: =SUM(D48:D54) -> 1129 | H55: =SUM(H48:H54) -> 531.79 | I55: =SUM(I48:I54) -> 6.79
B56: Sun 9-13 | C56: 290 | D56: 0 | E56: GV/YZ | F56: Change Order Paid | H56: 286 | I56: =H56-C56 -> -4
B57: Mon 9-14 | C57: 0 | D57: 0 | E57: GV/YZ | H57: 1 | I57: =H57-C57 -> 1
B58: Tue 9-15 | C58: 0 | D58: 1130 | E58: GV/YZ | F58: Change Order Received | H58: 6 | I58: =H58-C58 -> 6
B59: Wed 9-16 | C59: 310 | D59: 0 | E59: YZ | F59: Change Order Paid | H59: 354 | I59: =H59-C59 -> 44
B60: Thu 9-17 | C60: 118 | D60: 0 | E60: YZ | F60: Change Order Paid | H60: 138 | I60: =H60-C60 -> 20
B61: Fri 9-18 | C61: 0 | D61: 0 | E61: YZ/GV | F61: Deposit was made late. Sarah Jensen corrected. | H61: -294.64 | I61: =H61-C61 -> -294.64
B62: Sat 9-19 | C62: 264 | D62: 0 | E62: YZ | F62: Change Order Paid | H62: 593 | I62: =H62-C62 -> 329
B63: Total Week | C63: =SUM(C56:C62) -> 982 | D63: =SUM(D56:D62) -> 1130 | H63: =SUM(H56:H62) -> 1083.36 | I63: =SUM(I56:I62) -> 101.36
B64: Sun 9-20 | C64: 86 | D64: 0 | E64: YZ | F64: Change Order Paid | H64: -387 | I64: =H64-C64 -> -473
B65: Mon 9-21 | C65: 0 | D65: 0 | E65: YZ | H65: 39 | I65: =H65-C65 -> 39
B66: Tue 9-22 | D66: 1020 | E66: YZ/GV | F66: Change Order Received/ Short 0.33 Cents | H66: -0.33 | I66: =H66-C66 -> -0.33
B67: Wed 9-23 | C67: 781 | D67: 0 | E67: YZ | F67: Change Order Paid | H67: 1121 | I67: =H67-C67 -> 340
B68: Thu 9-24 | C68: 0 | D68: 0 | E68: YZ | H68: 18 | I68: =H68-C68 -> 18
B69: Fri 9-25 | C69: 240 | D69: 0 | E69: YZ/GV | H69: 258 | I69: =H69-C69 -> 18
B70: Sat 9-26 | C70: 100 | D70: 0 | E70: yz | H70: 113 | I70: =H70-C70 -> 13
B71: Total Week | C71: =SUM(C64:C70) -> 1207 | D71: =SUM(D64:D70) -> 1020 | H71: =SUM(H64:H70) -> 1161.67 | I71: =SUM(I64:I70) -> -45.33
B72: Sun 9-27 | D72: 0 | E72: GV | F72: $12.31 over for the day | H72: 12 | I72: =H72-C72 -> 12
B73: Mon 9-28 | C73: 0 | D73: 0 | E73: gv | F73: $15.91 over for the day | H73: 16 | I73: =H73-C73 -> 16
B74: Tue 9-29 | C74: 0 | D74: 925 | E74: gv/yz | F74: Change Order Received $1.95 short | H74: -2 | I74: =H74-C74 -> -2
B75: Wed 9-30 | C75: 565 | D75: 0 | E75: yz | F75: Change Order Paid ; Over $11 | H75: 576 | I75: =H75-C75 -> 11
B76: Thu 10-1 | C76: 0 | D76: 0 | E76: YZ | F76: Over $31 | H76: 31 | I76: =H76-C76 -> 31
B77: Fri 10-2 | D77: 0 | E77: YZ | F77: OVER $18 | H77: 18 | I77: =H77-C77 -> 18
B78: Sat 10-3 | C78: 925 | D78: 0 | E78: YZ | F78: Change order Paid. Short $2 | H78: 923 | I78: =H78-C78 -> -2
B79: Total Week | C79: =SUM(C72:C78) -> 1490 | D79: =SUM(D72:D78) -> 925 | H79: =SUM(H72:H78) -> 1574 | I79: =SUM(I72:I78) -> 84
B80: Total Period | C80: =SUM(C79+C71+C63+C55) -> 4204 | D80: =SUM(D79+D71+D63+D55) -> 4204 | H80: =SUM(H79+H71+H63+H55) -> 4350.82 | I80: =SUM(I79+I71+I63+I55) -> 146.82
B81: Period Activity | C81: =D80+C80 -> 8408 | H81: =I80+H80 -> 4497.64 | I81: =J80+I80 -> 146.82
C82: Sun 10-4 | D82: After Period Close
B83: Ending Period Count of Amopunt on hand | C83: 0 | E83: YZ
B85: Number of Cash Drawers | C85: 2
B87: Amount of Each Drawer | C87: 200
B89: Amount of Petty Cash | C89: 300
B91: Period11
B92: Sun 10-4 | C92: 0 | E92: yz | F92: Over $48. | H92: 48 | I92: =H92-C92 -> 48
B93: Mon 10-5 | C93: 0 | D93: 0 | E93: GV | F93: over $16 | H93: 16 | I93: =H93-C93 -> 16
B94: Tue 10-6 | C94: 0 | D94: 1005 | E94: GV/YZ | F94: change order recieved / over for the day $10 | H94: 10 | I94: =H94-C94 -> 10
B95: Wed 10-7 | C95: 419 | D95: 0 | E95: yz | F95: Change Order Paid/ Short 37 | H95: 382 | I95: =H95-C95 -> -37
B96: Thu 10-8 | C96: 0 | D96: 0 | E96: YZ | F96: Short $11 | H96: -11 | I96: =H96-C96 -> -11
B97: Fri 10-9 | C97: 0 | D97: 0 | E97: yz | F97: Deposit was entered late. R365 will not match with actual. Daily deposit of $1180. | H97: -25.25 | I97: =H97-C97 -> -25.25
B98: Sat 10-10 | C98: 100 | D98: 0 | E98: yz | F98: Change order Paid/ Over 10 | H98: 110 | I98: =H98-C98 -> 10
B99: Total Week | C99: =SUM(C92:C98) -> 519 | D99: =SUM(D92:D98) -> 1005 | H99: =SUM(H92:H98) -> 529.75 | I99: =SUM(I92:I98) -> 10.75
B100: Sun 10-11 | C100: 373 | D100: 0 | H100: 0 | I100: =H100-C100 -> -373
B101: Mon 10-12 | C101: 0 | D101: 0 | H101: 0 | I101: =H101-C101 -> 0
B102: Tue 10-13 | C102: 0 | D102: 0 | H102: 0 | I102: =H102-C102 -> 0
B103: Wed 10-14 | C103: 0 | D103: 0 | H103: 0 | I103: =H103-C103 -> 0
B104: Thu 10-15 | C104: 0 | D104: 0 | H104: 0 | I104: =H104-C104 -> 0
B105: Fri 10-16 | C105: 0 | D105: 0 | H105: 0 | I105: =H105-C105 -> 0
B106: Sat 10-17 | C106: 0 | D106: 0 | H106: 0 | I106: =H106-C106 -> 0
B107: Total Week | C107: =SUM(C100:C106) -> 373 | D107: =SUM(D100:D106) -> 0 | H107: =SUM(H100:H106) -> 0 | I107: =SUM(I100:I106) -> -373
B108: Sun 10-18 | C108: 0 | D108: 0 | H108: 0 | I108: =H108-C108 -> 0
...

Sheet WH
C1: Whittier
C2: Per Restaurant
C3: Chage Order Deposits | D3: Change Order Received | E3: Initials | F3: Comments | H3: Cash over/ (Short) per R365 Flash report | I3: True Over/ (Short)
B4: =Control!$B$3 -> 46243 | C4: 0 | D4: 0 | I4: =H4-C4 -> 0
B5: =B4+1 -> 46244 | C5: -700 | D5: 0 | E5: NG | I5: =H5-C5 -> 700
B6: =B5+1 -> 46245 | C6: -155 | D6: 0 | E6: NG | I6: =H6-C6 -> 155
B7: =B6+1 -> 46246 | C7: -700 | D7: 0 | E7: LF | I7: =H7-C7 -> 700
B8: =B7+1 -> 46247 | C8: 0 | D8: 2255 | E8: LF | I8: =H8-C8 -> 0
B9: =B8+1 -> 46248 | C9: 0 | D9: 0 | I9: =H9-C9 -> 0
B10: =B9+1 -> 46249 | C10: -700 | D10: 0 | E10: LF | I10: =H10-C10 -> 700
B11: Total Week | C11: =SUM(C4:C10) -> -2255 | D11: =SUM(D4:D10) -> 2255 | H11: =SUM(H4:H10) -> 0 | I11: =SUM(I4:I10) -> 2255
B12: =B10+1 -> 46250 | C12: 0 | D12: 0 | I12: =H12-C12 -> 0
B13: =B12+1 -> 46251 | C13: -855 | D13: 0 | E13: NG | I13: =H13-C13 -> 855
B14: =B13+1 -> 46252 | C14: 0 | D14: 0 | I14: =H14-C14 -> 0
B15: =B14+1 -> 46253 | C15: 0 | D15: 0 | I15: =H15-C15 -> 0
B16: =B15+1 -> 46254 | C16: -700 | D16: 0 | E16: LF | I16: =H16-C16 -> 700
B17: =B16+1 -> 46255 | C17: 0 | D17: 0 | I17: =H17-C17 -> 0
B18: =B17+1 -> 46256 | C18: 0 | D18: 0 | I18: =H18-C18 -> 0
B19: Total Week | C19: =SUM(C12:C18) -> -1555 | D19: =SUM(D12:D18) -> 0 | H19: =SUM(H12:H18) -> 0 | I19: =SUM(I12:I18) -> 1555
B20: =B18+1 -> 46257 | C20: -700 | D20: 0 | E20: NG | I20: =H20-C20 -> 700
B21: =B20+1 -> 46258 | C21: -100 | D21: 1500 | E21: NG | F21: Changed was order late and was delivered Monday not Thursday | I21: =H21-C21 -> 100
B22: =B21+1 -> 46259 | C22: 0 | D22: 0 | I22: =H22-C22 -> 0
B23: =B22+1 -> 46260 | C23: -700 | D23: 0 | E23: LF | I23: =H23-C23 -> 700
B24: =B23+1 -> 46261 | C24: 0 | D24: 0 | I24: =H24-C24 -> 0
B25: =B24+1 -> 46262 | C25: 175 | D25: 1575 | E25: LF | I25: =H25-C25 -> -175
B26: =B25+1 -> 46263 | C26: 700 | D26: 0 | I26: =H26-C26 -> -700
B27: Total Week | C27: =SUM(C20:C26) -> -625 | D27: =SUM(D20:D26) -> 3075 | H27: =SUM(H20:H26) -> 0 | I27: =SUM(I20:I26) -> 625
B28: =B26+1 -> 46264 | C28: 0 | D28: 0 | I28: =H28-C28 -> 0
B29: =B28+1 -> 46265 | C29: 0 | D29: 0 | I29: =H29-C29 -> 0
B30: =B29+1 -> 46266 | C30: 0 | D30: 0 | I30: =H30-C30 -> 0
B31: =B30+1 -> 46267 | C31: 0 | D31: 0 | I31: =H31-C31 -> 0
B32: =B31+1 -> 46268 | C32: 805 | D32: 2310 | E32: LF | F32: change order received. | I32: =H32-C32 -> -805
B33: =B32+1 -> 46269 | C33: 0 | D33: 0 | I33: =H33-C33 -> 0
B34: =B33+1 -> 46270 | C34: 0 | D34: 0 | H34: -19.09 | I34: =H34-C34 -> -19.09
B35: Total Week | C35: =SUM(C28:C34) -> 805 | D35: =SUM(D28:D34) -> 2310 | H35: =SUM(H28:H34) -> -19.09 | I35: =SUM(I28:I34) -> -824.09
B36: Total Period | C36: =SUM(C35+C27+C19+C11) -> -3630 | D36: =SUM(D35+D27+D19+D11) -> 7640 | H36: =SUM(H35+H27+H19+H11) -> -19.09 | I36: =SUM(I35+I27+I19+I11) -> 3610.91
B37: Period Activity | C37: =D36+C36 -> 4010 | H37: =I36+H36 -> 3591.82 | I37: =J36+I36 -> 3610.91
C38: =B34+1 -> 46271 | D38: After Period Close
B39: Ending Period Count of Amount on hand | C39: 2800 | E39: LF
B41: Number of Cash Drawers | C41: 2
B43: Amount of Each Drawer | C43: 200
B45: Amount of Petty Cash | C45: 300
B47: Period10
B48: Sun 9-6 | C48: 700 | D48: 0 | E48: NG | F48: $700 Change order droped | H48: 622.63 | I48: =H48-C48 -> -77.37
B49: Mon 9-7 | C49: 0 | D49: 0 | E49: OC | H49: 0.52 | I49: =H49-C49 -> 0.52
B50: Tue 9-8 | C50: 0 | D50: 0 | E50: OC | H50: 0.48 | I50: =H50-C50 -> 0.48
B51: Wed 9-9 | C51: 0 | D51: 0 | E51: LF | H51: 44.34 | I51: =H51-C51 -> 44.34
B52: Thu 9-10 | C52: 175 | D52: 2275 | E52: LF | F52: change order received. $175 paid | H52: 170.63 | I52: =H52-C52 -> -4.37
B53: Fri 9-11 | C53: 0 | D53: 0 | E53: LF | H53: -65.22 | I53: =H53-C53 -> -65.22
B54: Sat 9-12 | C54: 700 | D54: 0 | E54: LF | H54: 713.28 | I54: =H54-C54 -> 13.28
B55: Total Week | C55: =SUM(C48:C54) -> 1575 | D55: =SUM(D48:D54) -> 2275 | H55: =SUM(H48:H54) -> 1486.66 | I55: =SUM(I48:I54) -> -88.34
B56: Sun 9-13 | C56: 0 | D56: 0 | E56: OC | H56: 20.19 | I56: =H56-C56 -> 20.19
B57: Mon 9-14 | C57: 0 | D57: 0 | E57: OC | H57: -62.29 | I57: =H57-C57 -> -62.29
B58: Tue 9-15 | C58: 700 | D58: 0 | E58: LF | F58: Chef had entered a negative deposit on aloha deposit by Nubia | H58: 703 | I58: =H58-C58 -> 3
B59: Wed 9-16 | C59: 0 | D59: 0 | E59: LF | F59: Brianna will be coached on shortages | H59: -46.44 | I59: =H59-C59 -> -46.44
B60: Thu 9-17 | C60: 150 | D60: 1550 | E60: LF | F60: change order received and $150 Paid | H60: 183.59 | I60: =H60-C60 -> 33.59
B61: Fri 9-18 | C61: 700 | D61: 0 | E61: LF | F61: $700 Change Paid | H61: 716.35 | I61: =H61-C61 -> 16.35
B62: Sat 9-19 | C62: 0 | D62: 0 | E62: LF | H62: -20.77 | I62: =H62-C62 -> -20.77
B63: Total Week | C63: =SUM(C56:C62) -> 1550 | D63: =SUM(D56:D62) -> 1550 | H63: =SUM(H56:H62) -> 1493.63 | I63: =SUM(I56:I62) -> -56.37
B64: Sun 9-20 | C64: 0 | D64: 0 | E64: LF | H64: -44 | I64: =H64-C64 -> -44
B65: Mon 9-21 | C65: 0 | D65: 0 | E65: LF | F65: Chef found $300 after closing the day | H65: -385 | I65: =H65-C65 -> -385
B66: Tue 9-22 | C66: 0 | D66: 0 | E66: LF | F66: bounce from previous day. | H66: 294.82 | I66: =H66-C66 -> 294.82
B67: Wed 9-23 | C67: 700 | D67: 0 | E67: LF | F67: $700 Change Paid | H67: 718.02 | I67: =H67-C67 -> 18.02
B68: Thu 9-24 | C68: 150 | D68: 150 | E68: LF | F68: $850 change order received orderd 9/23 $850 change paid | H68: 153.61 | I68: =H68-C68 -> 3.61
B69: Fri 9-25 | C69: 0 | D69: 0 | E69: LF | F69: short again will coach cashiers | H69: -62.57 | I69: =H69-C69 -> -62.57
B70: Sat 9-26 | C70: 0 | D70: 0 | E70: LF | F70: short again will coach cashiers | H70: -60.17 | I70: =H70-C70 -> -60.17
B71: Total Week | C71: =SUM(C64:C70) -> 850 | D71: =SUM(D64:D70) -> 150 | H71: =SUM(H64:H70) -> 614.71 | I71: =SUM(I64:I70) -> -235.29
B72: Sun 9-27 | C72: 0 | D72: 0 | E72: LF | F72: Managers will count drawers at the end of cashiers shift | H72: -69.14 | I72: =H72-C72 -> -69.14
B73: Mon 9-28 | E73: LF | F73: Managers need to count drawer at the end of every single cashier shift | H73: -32.99 | I73: =H73-C73 -> -32.99
B74: Tue 9-29 | C74: 0 | D74: 0 | E74: LF | H74: 19.39 | I74: =H74-C74 -> 19.39
B75: Wed 9-30 | C75: 0 | D75: 0 | E75: LF | F75: Had a check tranferred to kiosk and should be closed once it reset | H75: 76.75 | I75: =H75-C75 -> 76.75
B76: Thu 10-1 | C76: 150 | D76: 850 | E76: LF | F76: $850 change order received-ordered 9/30 $150 change paid | H76: 159.7 | I76: =H76-C76 -> 9.7
B77: Fri 10-2 | C77: 700 | D77: 0 | E77: LF | F77: $700 Change Paid | H77: 524.8 | I77: =H77-C77 -> -175.2
B78: Sat 10-3 | D78: 0 | E78: LF | H78: 27.86 | I78: =H78-C78 -> 27.86
B79: Total Week | C79: =SUM(C72:C78) -> 850 | D79: =SUM(D72:D78) -> 850 | H79: =SUM(H72:H78) -> 706.37 | I79: =SUM(I72:I78) -> -143.63
B80: Total Period | C80: =SUM(C79+C71+C63+C55) -> 4825 | D80: =SUM(D79+D71+D63+D55) -> 4825 | H80: =SUM(H79+H71+H63+H55) -> 4301.37 | I80: =SUM(I79+I71+I63+I55) -> -523.63
B81: Period Activity | C81: =D80+C80 -> 9650 | H81: =I80+H80 -> 3777.74 | I81: =J80+I80 -> -523.63
C82: Sun 10-4 | D82: After Period Close
B83: Ending Period Count of Amopunt on hand | C83: 2100 | E83: LAFP | F83: all counts verified
B85: Number of Cash Drawers | C85: 2
B87: Amount of Each Drawer | C87: 200
B89: Amount of Petty Cash | C89: 300
B91: Period11
B92: Sun 10-4 | C92: 0 | D92: 0 | E92: LF | F92: over from last server not getting tips. Tranfer check to ziozk | H92: 106.3 | I92: =H92-C92 -> 106.3
B93: Mon 10-5 | C93: 700 | D93: 0 | E93: LF | F93: Chef entered negative deposit on aloha. Emailed to get it corrected. | H93: 630.06 | I93: =H93-C93 -> -69.94
B94: Tue 10-6 | C94: 0 | D94: 0 | E94: LF | F94: Paid briannas tips from previous day $44.93 | H94: -88.33 | I94: =H94-C94 -> -88.33
B95: Wed 10-7 | C95: 0 | D95: 0 | E95: LF | H95: 46.45 | I95: =H95-C95 -> 46.45
B96: Thu 10-8 | C96: 105 | D96: 1505 | E96: LF | F96: $1505 change order received. Ordered 10/7... $105 change paid | H96: 120.43 | I96: =H96-C96 -> 15.43
B97: Fri 10-9 | C97: 0 | D97: 0 | E97: LF | F97: short on grave yard drawer | H97: -44.81 | I97: =H97-C97 -> -44.81
B98: Sat 10-10 | C98: 0 | D98: 0 | E98: LF | H98: 29.85 | I98: =H98-C98 -> 29.85
B99: Total Week | C99: =SUM(C92:C98) -> 805 | D99: =SUM(D92:D98) -> 1505 | H99: =SUM(H92:H98) -> 799.95 | I99: =SUM(I92:I98) -> -5.05
B100: Sun 10-11 | C100: 700 | D100: 0 | E100: LF | F100: $700 Change Paid | H100: 0 | I100: =H100-C100 -> -700
B101: Mon 10-12 | C101: 0 | D101: 0 | H101: 0 | I101: =H101-C101 -> 0
B102: Tue 10-13 | C102: 0 | D102: 0 | H102: 0 | I102: =H102-C102 -> 0
B103: Wed 10-14 | C103: 0 | D103: 0 | H103: 0 | I103: =H103-C103 -> 0
B104: Thu 10-15 | C104: 0 | D104: 0 | H104: 0 | I104: =H104-C104 -> 0
B105: Fri 10-16 | C105: 0 | D105: 0 | H105: 0 | I105: =H105-C105 -> 0
B106: Sat 10-17 | C106: 0 | D106: 0 | H106: 0 | I106: =H106-C106 -> 0
B107: Total Week | C107: =SUM(C100:C106) -> 700 | D107: =SUM(D100:D106) -> 0 | H107: =SUM(H100:H106) -> 0 | I107: =SUM(I100:I106) -> -700
B108: Sun 10-18 | C108: 0 | D108: 0 | H108: 0 | I108: =H108-C108 -> 0
...

Sheet Control
A1: Period | B1: 9
A3: Start Date | B3: 46243 | E3: 217 | F3: AN | G3: Anaheim
E4: 225 | F4: CL | G4: Claremont
E5: 220 | F5: CM | G5: Costa Mesa
E6: 263 | F6: CR | G6: Carson
E7: 244 | F7: DN | G7: Downey
E8: 262 | F8: EM | G8: El Monte
E9: 219 | F9: HB | G9: Huntington Beach
E10: 269 | F10: HO | G10: Hollywood
E11: 264 | F11: IG | G11: Inglewood
E12: 250 | F12: LC | G12: La Cienega
E13: 215 | F13: LK | G13: Lakewood
E14: 272 | F14: LV | G14: Las Vegas
E15: 270 | F15: ON | G15: Ontario
... E26: 222 | F26: WH | G26: Whittier
